Workbook

Sheet TONG_HOP
A1: Bảng TH Chênh Lệch Từ Tháng 5 Đến tháng 5/2026 | E1: CHÊNH LỆCH | I1: Bảng CT Chênh Lệch Từ Tháng 5 Đến tháng 5/2026 | M1: CHÊNH LỆCH
A2: {=VLOOKUP(INDEX(DSDVI!$D$2:$D$25,MATCH(TRUE,DSDVI!D2:D25<>"",0)),DSDVI!$A$2:$C$25,2,0)} -> HCMC - Công ty Điện lực Vũng Tàu | I2: {=VLOOKUP(INDEX(DSDVI!$D$2:$D$25,MATCH(TRUE,DSDVI!$D$2:$D$25<>"",0)),DSDVI!$A$2:$C$25,2,0)} -> HCMC - Công ty Điện lực Vũng Tàu
A3: 1363111 | B3: 3363111 | C3: =SUMIFS(DATA_TONGHOP!N:N,DATA_TONGHOP!C:C,"080100",DATA_TONGHOP!A:A,TONG_HOP!A3) -> -934199717138 | D3: {=SUMIFS(DATA_TONGHOP!N:N,DATA_TONGHOP!C:C,INDEX(DSDVI!$D$2:$D$25,MATCH(TRUE,DSDVI!$D$2:$D$25<>"",0)),DATA_TONGHOP!A:A,TONG_HOP!B3)} -> 488183646170 | E3: =IF(C3-D3=0,0,HYPERLINK("#'"&A3&"_"&B3&"'!A1",C3-D3)) -> -1422383363308 | I3: 1363111 | J3: 3363111 | K3: =SUMIFS(DATA_PHATSINH!T:T,DATA_PHATSINH!M:M,"080100",DATA_PHATSINH!A:A,TONG_HOP!I3) -> -1361722492155 | L3: {=SUMIFS(DATA_PHATSINH!T:T,DATA_PHATSINH!M:M,INDEX(DSDVI!$D$2:$D$25,MATCH(TRUE,DSDVI!$D$2:$D$25<>"",0)),DATA_PHATSINH!A:A,TONG_HOP!J3)} -> 60660871153 | M3: =IF(K3-L3=0,0,HYPERLINK("#'"&A3&"_"&B3&"'!A1",K3-L3)) -> -1422383363308
A4: 1363112 | B4: 3363112 | C4: =SUMIFS(DATA_TONGHOP!N:N,DATA_TONGHOP!C:C,"080100",DATA_TONGHOP!A:A,TONG_HOP!A4) -> -4548652836 | D4: {=SUMIFS(DATA_TONGHOP!N:N,DATA_TONGHOP!C:C,INDEX(DSDVI!$D$2:$D$25,MATCH(TRUE,DSDVI!$D$2:$D$25<>"",0)),DATA_TONGHOP!A:A,TONG_HOP!B4)} -> -3876382947 | E4: =IF(C4-D4=0,0,HYPERLINK("#'"&A4&"_"&B4&"'!A1",C4-D4)) -> -672269889 | I4: 1363112 | J4: 3363112 | K4: =SUMIFS(DATA_PHATSINH!T:T,DATA_PHATSINH!M:M,"080100",DATA_PHATSINH!A:A,TONG_HOP!I4) -> -641017536 | L4: {=SUMIFS(DATA_PHATSINH!T:T,DATA_PHATSINH!M:M,INDEX(DSDVI!$D$2:$D$25,MATCH(TRUE,DSDVI!$D$2:$D$25<>"",0)),DATA_PHATSINH!A:A,TONG_HOP!J4)} -> 31252353 | M4: =IF(K4-L4=0,0,HYPERLINK("#'"&A4&"_"&B4&"'!A1",K4-L4)) -> -672269889
A5: 136312 | B5: 336312 | C5: =SUMIFS(DATA_TONGHOP!N:N,DATA_TONGHOP!C:C,"080100",DATA_TONGHOP!A:A,TONG_HOP!A5) -> 0 | D5: {=SUMIFS(DATA_TONGHOP!N:N,DATA_TONGHOP!C:C,INDEX(DSDVI!$D$2:$D$25,MATCH(TRUE,DSDVI!$D$2:$D$25<>"",0)),DATA_TONGHOP!A:A,TONG_HOP!B5)} -> 0 | E5: =IF(C5-D5=0,0,HYPERLINK("#'"&A5&"_"&B5&"'!A1",C5-D5)) -> 0 | I5: 136312 | J5: 336312 | K5: =SUMIFS(DATA_PHATSINH!T:T,DATA_PHATSINH!M:M,"080100",DATA_PHATSINH!A:A,TONG_HOP!I5) -> 0 | L5: {=SUMIFS(DATA_PHATSINH!T:T,DATA_PHATSINH!M:M,INDEX(DSDVI!$D$2:$D$25,MATCH(TRUE,DSDVI!$D$2:$D$25<>"",0)),DATA_PHATSINH!A:A,TONG_HOP!J5)} -> 0 | M5: =IF(K5-L5=0,0,HYPERLINK("#'"&A5&"_"&B5&"'!A1",K5-L5)) -> 0
A6: 136313 | B6: 336313 | C6: =SUMIFS(DATA_TONGHOP!N:N,DATA_TONGHOP!C:C,"080100",DATA_TONGHOP!A:A,TONG_HOP!A6) -> 0 | D6: {=SUMIFS(DATA_TONGHOP!N:N,DATA_TONGHOP!C:C,INDEX(DSDVI!$D$2:$D$25,MATCH(TRUE,DSDVI!$D$2:$D$25<>"",0)),DATA_TONGHOP!A:A,TONG_HOP!B6)} -> 0 | E6: =IF(C6-D6=0,0,HYPERLINK("#'"&A6&"_"&B6&"'!A1",C6-D6)) -> 0 | I6: 136313 | J6: 336313 | K6: =SUMIFS(DATA_PHATSINH!T:T,DATA_PHATSINH!M:M,"080100",DATA_PHATSINH!A:A,TONG_HOP!I6) -> 0 | L6: {=SUMIFS(DATA_PHATSINH!T:T,DATA_PHATSINH!M:M,INDEX(DSDVI!$D$2:$D$25,MATCH(TRUE,DSDVI!$D$2:$D$25<>"",0)),DATA_PHATSINH!A:A,TONG_HOP!J6)} -> 0 | M6: =IF(K6-L6=0,0,HYPERLINK("#'"&A6&"_"&B6&"'!A1",K6-L6)) -> 0
A7: 136314 | B7: 336314 | C7: =SUMIFS(DATA_TONGHOP!N:N,DATA_TONGHOP!C:C,"080100",DATA_TONGHOP!A:A,TONG_HOP!A7) -> 7987850607 | D7: {=SUMIFS(DATA_TONGHOP!N:N,DATA_TONGHOP!C:C,INDEX(DSDVI!$D$2:$D$25,MATCH(TRUE,DSDVI!$D$2:$D$25<>"",0)),DATA_TONGHOP!A:A,TONG_HOP!B7)} -> 8241423967 | E7: =IF(C7-D7=0,0,HYPERLINK("#'"&A7&"_"&B7&"'!A1",C7-D7)) -> -253573360 | I7: 136314 | J7: 336314 | K7: =SUMIFS(DATA_PHATSINH!T:T,DATA_PHATSINH!M:M,"080100",DATA_PHATSINH!A:A,TONG_HOP!I7) -> 0 | L7: {=SUMIFS(DATA_PHATSINH!T:T,DATA_PHATSINH!M:M,INDEX(DSDVI!$D$2:$D$25,MATCH(TRUE,DSDVI!$D$2:$D$25<>"",0)),DATA_PHATSINH!A:A,TONG_HOP!J7)} -> 253573360 | M7: =IF(K7-L7=0,0,HYPERLINK("#'"&A7&"_"&B7&"'!A1",K7-L7)) -> -253573360
A8: 136315 | B8: 336315 | C8: =SUMIFS(DATA_TONGHOP!N:N,DATA_TONGHOP!C:C,"080100",DATA_TONGHOP!A:A,TONG_HOP!A8) -> 0 | D8: {=SUMIFS(DATA_TONGHOP!N:N,DATA_TONGHOP!C:C,INDEX(DSDVI!$D$2:$D$25,MATCH(TRUE,DSDVI!$D$2:$D$25<>"",0)),DATA_TONGHOP!A:A,TONG_HOP!B8)} -> 0 | E8: =IF(C8-D8=0,0,HYPERLINK("#'"&A8&"_"&B8&"'!A1",C8-D8)) -> 0 | I8: 136315 | J8: 336315 | K8: =SUMIFS(DATA_PHATSINH!T:T,DATA_PHATSINH!M:M,"080100",DATA_PHATSINH!A:A,TONG_HOP!I8) -> 0 | L8: {=SUMIFS(DATA_PHATSINH!T:T,DATA_PHATSINH!M:M,INDEX(DSDVI!$D$2:$D$25,MATCH(TRUE,DSDVI!$D$2:$D$25<>"",0)),DATA_PHATSINH!A:A,TONG_HOP!J8)} -> 0 | M8: =IF(K8-L8=0,0,HYPERLINK("#'"&A8&"_"&B8&"'!A1",K8-L8)) -> 0
A9: 136318 | B9: 336318 | C9: =SUMIFS(DATA_TONGHOP!N:N,DATA_TONGHOP!C:C,"080100",DATA_TONGHOP!A:A,TONG_HOP!A9) -> 0 | D9: {=SUMIFS(DATA_TONGHOP!N:N,DATA_TONGHOP!C:C,INDEX(DSDVI!$D$2:$D$25,MATCH(TRUE,DSDVI!$D$2:$D$25<>"",0)),DATA_TONGHOP!A:A,TONG_HOP!B9)} -> 0 | E9: =IF(C9-D9=0,0,HYPERLINK("#'"&A9&"_"&B9&"'!A1",C9-D9)) -> 0 | I9: 136318 | J9: 336318 | K9: =SUMIFS(DATA_PHATSINH!T:T,DATA_PHATSINH!M:M,"080100",DATA_PHATSINH!A:A,TONG_HOP!I9) -> 0 | L9: {=SUMIFS(DATA_PHATSINH!T:T,DATA_PHATSINH!M:M,INDEX(DSDVI!$D$2:$D$25,MATCH(TRUE,DSDVI!$D$2:$D$25<>"",0)),DATA_PHATSINH!A:A,TONG_HOP!J9)} -> 0 | M9: =IF(K9-L9=0,0,HYPERLINK("#'"&A9&"_"&B9&"'!A1",K9-L9)) -> 0
A10: 136321 | B10: 336321 | C10: =SUMIFS(DATA_TONGHOP!N:N,DATA_TONGHOP!C:C,"080100",DATA_TONGHOP!A:A,TONG_HOP!A10) -> 0 | D10: {=SUMIFS(DATA_TONGHOP!N:N,DATA_TONGHOP!C:C,INDEX(DSDVI!$D$2:$D$25,MATCH(TRUE,DSDVI!$D$2:$D$25<>"",0)),DATA_TONGHOP!A:A,TONG_HOP!B10)} -> 0 | E10: =IF(C10-D10=0,0,HYPERLINK("#'"&A10&"_"&B10&"'!A1",C10-D10)) -> 0 | I10: 136321 | J10: 336321 | K10: =SUMIFS(DATA_PHATSINH!T:T,DATA_PHATSINH!M:M,"080100",DATA_PHATSINH!A:A,TONG_HOP!I10) -> 0 | L10: {=SUMIFS(DATA_PHATSINH!T:T,DATA_PHATSINH!M:M,INDEX(DSDVI!$D$2:$D$25,MATCH(TRUE,DSDVI!$D$2:$D$25<>"",0)),DATA_PHATSINH!A:A,TONG_HOP!J10)} -> 0 | M10: =IF(K10-L10=0,0,HYPERLINK("#'"&A10&"_"&B10&"'!A1",K10-L10)) -> 0
A11: 136322 | B11: 336322 | C11: =SUMIFS(DATA_TONGHOP!N:N,DATA_TONGHOP!C:C,"080100",DATA_TONGHOP!A:A,TONG_HOP!A11) -> 0 | D11: {=SUMIFS(DATA_TONGHOP!N:N,DATA_TONGHOP!C:C,INDEX(DSDVI!$D$2:$D$25,MATCH(TRUE,DSDVI!$D$2:$D$25<>"",0)),DATA_TONGHOP!A:A,TONG_HOP!B11)} -> 0 | E11: =IF(C11-D11=0,0,HYPERLINK("#'"&A11&"_"&B11&"'!A1",C11-D11)) -> 0 | I11: 136322 | J11: 336322 | K11: =SUMIFS(DATA_PHATSINH!T:T,DATA_PHATSINH!M:M,"080100",DATA_PHATSINH!A:A,TONG_HOP!I11) -> 0 | L11: {=SUMIFS(DATA_PHATSINH!T:T,DATA_PHATSINH!M:M,INDEX(DSDVI!$D$2:$D$25,MATCH(TRUE,DSDVI!$D$2:$D$25<>"",0)),DATA_PHATSINH!A:A,TONG_HOP!J11)} -> 0 | M11: =IF(K11-L11=0,0,HYPERLINK("#'"&A11&"_"&B11&"'!A1",K11-L11)) -> 0
A12: 136323 | B12: 336323 | C12: =SUMIFS(DATA_TONGHOP!N:N,DATA_TONGHOP!C:C,"080100",DATA_TONGHOP!A:A,TONG_HOP!A12) -> 0 | D12: {=SUMIFS(DATA_TONGHOP!N:N,DATA_TONGHOP!C:C,INDEX(DSDVI!$D$2:$D$25,MATCH(TRUE,DSDVI!$D$2:$D$25<>"",0)),DATA_TONGHOP!A:A,TONG_HOP!B12)} -> 0 | E12: =IF(C12-D12=0,0,HYPERLINK("#'"&A12&"_"&B12&"'!A1",C12-D12)) -> 0 | I12: 136323 | J12: 336323 | K12: =SUMIFS(DATA_PHATSINH!T:T,DATA_PHATSINH!M:M,"080100",DATA_PHATSINH!A:A,TONG_HOP!I12) -> 0 | L12: {=SUMIFS(DATA_PHATSINH!T:T,DATA_PHATSINH!M:M,INDEX(DSDVI!$D$2:$D$25,MATCH(TRUE,DSDVI!$D$2:$D$25<>"",0)),DATA_PHATSINH!A:A,TONG_HOP!J12)} -> 0 | M12: =IF(K12-L12=0,0,HYPERLINK("#'"&A12&"_"&B12&"'!A1",K12-L12)) -> 0
A13: 136331 | B13: 336331 | C13: =SUMIFS(DATA_TONGHOP!N:N,DATA_TONGHOP!C:C,"080100",DATA_TONGHOP!A:A,TONG_HOP!A13) -> -392951167430 | D13: {=SUMIFS(DATA_TONGHOP!N:N,DATA_TONGHOP!C:C,INDEX(DSDVI!$D$2:$D$25,MATCH(TRUE,DSDVI!$D$2:$D$25<>"",0)),DATA_TONGHOP!A:A,TONG_HOP!B13)} -> -399274041310 | E13: =IF(C13-D13=0,0,HYPERLINK("#'"&A13&"_"&B13&"'!A1",C13-D13)) -> 6322873880 | I13: 136331 | J13: 336331 | K13: =SUMIFS(DATA_PHATSINH!T:T,DATA_PHATSINH!M:M,"080100",DATA_PHATSINH!A:A,TONG_HOP!I13) -> 14964537632 | L13: {=SUMIFS(DATA_PHATSINH!T:T,DATA_PHATSINH!M:M,INDEX(DSDVI!$D$2:$D$25,MATCH(TRUE,DSDVI!$D$2:$D$25<>"",0)),DATA_PHATSINH!A:A,TONG_HOP!J13)} -> 8641663752 | M13: =IF(K13-L13=0,0,HYPERLINK("#'"&A13&"_"&B13&"'!A1",K13-L13)) -> 6322873880
A14: 136332 | B14: 336332 | C14: =SUMIFS(DATA_TONGHOP!N:N,DATA_TONGHOP!C:C,"080100",DATA_TONGHOP!A:A,TONG_HOP!A14) -> 0 | D14: {=SUMIFS(DATA_TONGHOP!N:N,DATA_TONGHOP!C:C,INDEX(DSDVI!$D$2:$D$25,MATCH(TRUE,DSDVI!$D$2:$D$25<>"",0)),DATA_TONGHOP!A:A,TONG_HOP!B14)} -> 877629907 | E14: =IF(C14-D14=0,0,HYPERLINK("#'"&A14&"_"&B14&"'!A1",C14-D14)) -> -877629907 | I14: 136332 | J14: 336332 | K14: =SUMIFS(DATA_PHATSINH!T:T,DATA_PHATSINH!M:M,"080100",DATA_PHATSINH!A:A,TONG_HOP!I14) -> 0 | L14: {=SUMIFS(DATA_PHATSINH!T:T,DATA_PHATSINH!M:M,INDEX(DSDVI!$D$2:$D$25,MATCH(TRUE,DSDVI!$D$2:$D$25<>"",0)),DATA_PHATSINH!A:A,TONG_HOP!J14)} -> 877629907 | M14: =IF(K14-L14=0,0,HYPERLINK("#'"&A14&"_"&B14&"'!A1",K14-L14)) -> -877629907
... A51: 13688 | B51: 33688 | C51: =SUMIFS(DATA_TONGHOP!N:N,DATA_TONGHOP!C:C,"080100",DATA_TONGHOP!A:A,TONG_HOP!A51) -> 0 | D51: {=SUMIFS(DATA_TONGHOP!N:N,DATA_TONGHOP!C:C,INDEX(DSDVI!$D$2:$D$25,MATCH(TRUE,DSDVI!$D$2:$D$25<>"",0)),DATA_TONGHOP!A:A,TONG_HOP!B51)} -> 0 | E51: =IF(C51-D51=0,0,HYPERLINK("#'"&A51&"_"&B51&"'!A1",C51-D51)) -> 0 | I51: 13688 | J51: 33688 | K51: =SUMIFS(DATA_PHATSINH!T:T,DATA_PHATSINH!M:M,"080100",DATA_PHATSINH!A:A,TONG_HOP!I51) -> 0 | L51: {=SUMIFS(DATA_PHATSINH!T:T,DATA_PHATSINH!M:M,INDEX(DSDVI!$D$2:$D$25,MATCH(TRUE,DSDVI!$D$2:$D$25<>"",0)),DATA_PHATSINH!A:A,TONG_HOP!J51)} -> 0 | M51: =IF(K51-L51=0,0,HYPERLINK("#'"&A51&"_"&B51&"'!A1",K51-L51)) -> 0
A52: 33688 | B52: 13688 | C52: =SUMIFS(DATA_TONGHOP!N:N,DATA_TONGHOP!C:C,"080100",DATA_TONGHOP!A:A,TONG_HOP!A52) -> 0 | D52: {=SUMIFS(DATA_TONGHOP!N:N,DATA_TONGHOP!C:C,INDEX(DSDVI!$D$2:$D$25,MATCH(TRUE,DSDVI!$D$2:$D$25<>"",0)),DATA_TONGHOP!A:A,TONG_HOP!B52)} -> 0 | E52: =IF(C52-D52=0,0,HYPERLINK("#'"&A52&"_"&B52&"'!A1",C52-D52)) -> 0 | I52: 33688 | J52: 13688 | K52: =SUMIFS(DATA_PHATSINH!T:T,DATA_PHATSINH!M:M,"080100",DATA_PHATSINH!A:A,TONG_HOP!I52) -> 0 | L52: {=SUMIFS(DATA_PHATSINH!T:T,DATA_PHATSINH!M:M,INDEX(DSDVI!$D$2:$D$25,MATCH(TRUE,DSDVI!$D$2:$D$25<>"",0)),DATA_PHATSINH!A:A,TONG_HOP!J52)} -> 0 | M52: =IF(K52-L52=0,0,HYPERLINK("#'"&A52&"_"&B52&"'!A1",K52-L52)) -> 0
A53: 3363888 | B53: 1363888 | C53: =SUMIFS(DATA_TONGHOP!N:N,DATA_TONGHOP!C:C,"080100",DATA_TONGHOP!A:A,TONG_HOP!A53) -> -338901499 | D53: {=SUMIFS(DATA_TONGHOP!N:N,DATA_TONGHOP!C:C,INDEX(DSDVI!$D$2:$D$25,MATCH(TRUE,DSDVI!$D$2:$D$25<>"",0)),DATA_TONGHOP!A:A,TONG_HOP!B53)} -> -338901499 | E53: =IF(C53-D53=0,0,HYPERLINK("#'"&A53&"_"&B53&"'!A1",C53-D53)) -> 0 | I53: 3363888 | J53: 1363888 | K53: =SUMIFS(DATA_PHATSINH!T:T,DATA_PHATSINH!M:M,"080100",DATA_PHATSINH!A:A,TONG_HOP!I53) -> -40655098 | L53: {=SUMIFS(DATA_PHATSINH!T:T,DATA_PHATSINH!M:M,INDEX(DSDVI!$D$2:$D$25,MATCH(TRUE,DSDVI!$D$2:$D$25<>"",0)),DATA_PHATSINH!A:A,TONG_HOP!J53)} -> -40655098 | M53: =IF(K53-L53=0,0,HYPERLINK("#'"&A53&"_"&B53&"'!A1",K53-L53)) -> 0
A54: 13681 | B54: 33681 | C54: {=0-SUMIFS(DATA_TONGHOP!N:N,DATA_TONGHOP!C:C,INDEX(DSDVI!$D$2:$D$25,MATCH(TRUE,DSDVI!$D$2:$D$25<>"",0)),DATA_TONGHOP!A:A,TONG_HOP!A54)} -> 14383337492 | D54: {=SUMIFS(DATA_TONGHOP!N:N,DATA_TONGHOP!C:C,INDEX(DSDVI!$D$2:$D$25,MATCH(TRUE,DSDVI!$D$2:$D$25<>"",0)),DATA_TONGHOP!A:A,TONG_HOP!B54)} -> 15100381544 | E54: =IF(C54-D54=0,0,HYPERLINK("#'"&A54&"_"&B54&"'!A1",C54-D54)) -> -717044052 | I54: 13681 | J54: 33681 | K54: {=0-SUMIFS(DATA_PHATSINH!T:T,DATA_PHATSINH!M:M,INDEX(DSDVI!$D$2:$D$25,MATCH(TRUE,DSDVI!$D$2:$D$25<>"",0)),DATA_PHATSINH!A:A,TONG_HOP!I54)} -> -138039697 | L54: {=SUMIFS(DATA_PHATSINH!T:T,DATA_PHATSINH!M:M,INDEX(DSDVI!$D$2:$D$25,MATCH(TRUE,DSDVI!$D$2:$D$25<>"",0)),DATA_PHATSINH!A:A,TONG_HOP!J54)} -> -138039697 | M54: =IF(K54-L54=0,0,HYPERLINK("#'"&A54&"_"&B54&"'!A1",K54-L54)) -> 0
C55: =SUMIFS(DATA_TONGHOP!N:N,DATA_TONGHOP!C:C,"080100",DATA_TONGHOP!A:A,TONG_HOP!A55) -> 0 | D55: {=SUMIFS(DATA_TONGHOP!N:N,DATA_TONGHOP!C:C,INDEX(DSDVI!$D$2:$D$25,MATCH(TRUE,DSDVI!$D$2:$D$25<>"",0)),DATA_TONGHOP!A:A,TONG_HOP!B55)} -> 0 | E55: =IF(C55-D55=0,0,HYPERLINK("#'"&A55&"_"&B55&"'!A1",C55-D55)) -> 0 | K55: =SUMIFS(DATA_PHATSINH!T:T,DATA_PHATSINH!M:M,"080100",DATA_PHATSINH!A:A,TONG_HOP!I55) -> 0 | L55: {=SUMIFS(DATA_PHATSINH!T:T,DATA_PHATSINH!M:M,INDEX(DSDVI!$D$2:$D$25,MATCH(TRUE,DSDVI!$D$2:$D$25<>"",0)),DATA_PHATSINH!A:A,TONG_HOP!J55)} -> 0 | M55: =IF(K55-L55=0,0,HYPERLINK("#'"&A55&"_"&B55&"'!A1",K55-L55)) -> 0
A56: Created with a trial version of Syncfusion Excel library or registered the wrong key in your application. Click here to obtain the valid key.

Sheet DSDVI
P1: Quay về TONG_HOP sheet
A5: 82900 | B5: HCMC - Công ty Điện lực Vũng Tàu | C5: HCMC - Công ty Điện lực Vũng Tàu | D5: 82900
A6: Created with a trial version of Syncfusion Excel library or registered the wrong key in your application. Click here to obtain the valid key.

Sheet DATA_TONGHOP
A1: SHTK | B1: SHTK GỐC | C1: MÃ ĐVI | D1: MÃ ĐVI NB | E1: SỐ DƯ NỢ ĐK | F1: SỐ DƯ CÓ ĐK | G1: SỐ PS NỢ | H1: SỐ PS CÓ | I1: SỐ DƯ NỢ CK | J1: SỐ DƯ CÓ CK | K1: ID | L1: ROW ORDER | M1: MA | N1: NET
A2: 1363111 | B2: 13631110000 | C2: 080100 | D2: 082900 | E2: 427522775017 | F2: 0 | G2: 103348536698 | H2: 1465071028853 | I2: 0 | J2: 934199717138 | K2: DATA_TONGHOP1 | L2: 0 | M2: =A2&C2 -> 1363111080100 | N2: =IF(C2="080100",I2-J2,J2-I2) -> -934199717138
A3: 1363112 | B3: 13631120000 | C3: 080100 | D3: 082900 | E3: 0 | F3: 3907635300 | G3: 51797384 | H3: 692814920 | I3: 0 | J3: 4548652836 | K3: DATA_TONGHOP2 | L3: 1 | M3: =A3&C3 -> 1363112080100 | N3: =IF(C3="080100",I3-J3,J3-I3) -> -4548652836
A4: 136314 | B4: 13631400000 | C4: 080100 | D4: 082900 | E4: 7987850607 | F4: 0 | G4: 0 | H4: 0 | I4: 7987850607 | J4: 0 | K4: DATA_TONGHOP3 | L4: 2 | M4: =A4&C4 -> 136314080100 | N4: =IF(C4="080100",I4-J4,J4-I4) -> 7987850607
A5: 136321 | B5: 13632100000 | C5: 080100 | D5: 082900 | E5: 0 | F5: 0 | G5: 0 | H5: 0 | I5: 0 | J5: 0 | K5: DATA_TONGHOP4 | L5: 3 | M5: =A5&C5 -> 136321080100 | N5: =IF(C5="080100",I5-J5,J5-I5) -> 0
A6: 136331 | B6: 13633100000 | C6: 080100 | D6: 082900 | E6: 0 | F6: 407915705062 | G6: 14964537632 | H6: 0 | I6: 0 | J6: 392951167430 | K6: DATA_TONGHOP5 | L6: 4 | M6: =A6&C6 -> 136331080100 | N6: =IF(C6="080100",I6-J6,J6-I6) -> -392951167430
A7: 136341 | B7: 13634100000 | C7: 080100 | D7: 082900 | E7: 0 | F7: 583672582158 | G7: 0 | H7: 0 | I7: 0 | J7: 583672582158 | K7: DATA_TONGHOP6 | L7: 5 | M7: =A7&C7 -> 136341080100 | N7: =IF(C7="080100",I7-J7,J7-I7) -> -583672582158
A8: 136351 | B8: 13635100000 | C8: 080100 | D8: 082900 | E8: 0 | F8: 19256042629 | G8: 1652341116 | H8: 0 | I8: 0 | J8: 17603701513 | K8: DATA_TONGHOP7 | L8: 6 | M8: =A8&C8 -> 136351080100 | N8: =IF(C8="080100",I8-J8,J8-I8) -> -17603701513
A9: 136351 | B9: 13635100000 | C9: 082900 | D9: 080100 | E9: 0 | F9: 0 | G9: 1074355839 | H9: 1074355839 | I9: 0 | J9: 0 | K9: DATA_TONGHOP8 | L9: 7 | M9: =A9&C9 -> 136351082900 | N9: =IF(C9="080100",I9-J9,J9-I9) -> 0
A10: 136352 | B10: 13635200000 | C10: 080100 | D10: 082900 | E10: 0 | F10: 0 | G10: 0 | H10: 0 | I10: 0 | J10: 0 | K10: DATA_TONGHOP9 | L10: 8 | M10: =A10&C10 -> 136352080100 | N10: =IF(C10="080100",I10-J10,J10-I10) -> 0
A11: 136352 | B11: 13635200000 | C11: 082900 | D11: 080100 | E11: 0 | F11: 0 | G11: 14287394776 | H11: 14287394776 | I11: 0 | J11: 0 | K11: DATA_TONGHOP10 | L11: 9 | M11: =A11&C11 -> 136352082900 | N11: =IF(C11="080100",I11-J11,J11-I11) -> 0
A12: 136358 | B12: 13635800000 | C12: 080100 | D12: 082900 | E12: 358880212978 | F12: 0 | G12: 54705959588 | H12: 104978986773 | I12: 308607185793 | J12: 0 | K12: DATA_TONGHOP11 | L12: 10 | M12: =A12&C12 -> 136358080100 | N12: =IF(C12="080100",I12-J12,J12-I12) -> 308607185793
A13: 136358 | B13: 13635800000 | C13: 082900 | D13: 080100 | E13: 0 | F13: 0 | G13: 1352970353650 | H13: 1352970353650 | I13: 0 | J13: 0 | K13: DATA_TONGHOP12 | L13: 11 | M13: =A13&C13 -> 136358082900 | N13: =IF(C13="080100",I13-J13,J13-I13) -> 0
... A46: 33693 | B46: 33693000000 | C46: 082900 | D46: 080100 | E46: 7044640797 | F46: 0 | G46: 0 | H46: 0 | I46: 7044640797 | J46: 0 | K46: DATA_TONGHOP45 | L46: 44 | M46: =A46&C46 -> 33693082900 | N46: =IF(C46="080100",I46-J46,J46-I46) -> -7044640797
A47: 13681 | B47: 13681000000 | C47: 082900 | D47: 080100 | E47: 0 | F47: 717044052 | G47: 0 | H47: 0 | I47: 0 | J47: 717044052 | M47: =A47&C47 -> 13681082900 | N47: =IF(C47="080100",I47-J47,J47-I47) -> 717044052
A48: 13681 | B48: 13681000000 | C48: 082900 | D48: 082900 | E48: 15955465293 | F48: 0 | G48: 452790220 | H48: 590829917 | I48: 15817425596 | J48: 0 | M48: =A48&C48 -> 13681082900 | N48: =IF(C48="080100",I48-J48,J48-I48) -> -15817425596
A49: 33681 | B49: 33681000000 | C49: 082900 | D49: 080100 | E49: 0 | F49: 0 | G49: 0 | H49: 0 | I49: 0 | J49: 0 | M49: =A49&C49 -> 33681082900 | N49: =IF(C49="080100",I49-J49,J49-I49) -> 0
A50: 33681 | B50: 33681000000 | C50: 082900 | D50: 082900 | E50: 0 | F50: 15238421241 | G50: 590829917 | H50: 452790220 | I50: 0 | J50: 15100381544 | M50: =A50&C50 -> 33681082900 | N50: =IF(C50="080100",I50-J50,J50-I50) -> 15100381544
M51: =A51&C51 | N51: =IF(C51="080100",I51-J51,J51-I51) -> 0
M52: =A52&C52 | N52: =IF(C52="080100",I52-J52,J52-I52) -> 0
M53: =A53&C53 | N53: =IF(C53="080100",I53-J53,J53-I53) -> 0
M54: =A54&C54 | N54: =IF(C54="080100",I54-J54,J54-I54) -> 0
M55: =A55&C55 | N55: =IF(C55="080100",I55-J55,J55-I55) -> 0
M56: =A56&C56 | N56: =IF(C56="080100",I56-J56,J56-I56) -> 0
M57: =A57&C57 | N57: =IF(C57="080100",I57-J57,J57-I57) -> 0
M58: =A58&C58 | N58: =IF(C58="080100",I58-J58,J58-I58) -> 0
M59: =A59&C59 | N59: =IF(C59="080100",I59-J59,J59-I59) -> 0
M60: =A60&C60 | N60: =IF(C60="080100",I60-J60,J60-I60) -> 0
M61: =A61&C61 | N61: =IF(C61="080100",I61-J61,J61-I61) -> 0
M62: =A62&C62 | N62: =IF(C62="080100",I62-J62,J62-I62) -> 0
... M1298: =A1298&C1298 | N1298: =IF(C1298="080100",I1298-J1298,J1298-I1298) -> 0
A1299: Created with a trial version of Syncfusion Excel library or registered the wrong key in your application. Click here to obtain the valid key.

Sheet DATA_PHATSINH
A1: SHTK | B1: SHTK GỐC | C1: NGUỒN | D1: TK CHA | E1: NHÓM TK | F1: NGÀY CT | G1: SỐ CT PHÂN HỆ PHỤ | H1: SỐ CT PHÂN HỆ GL | I1: DIỄN GIẢI | J1: SỐ PS NỢ | K1: SỐ PS CÓ | L1: NGƯỜI LẬP CT | M1: MÃ ĐVI | N1: MÃ ĐVI NB | O1: THANG | P1: NAM | Q1: ID | R1: ROW ORDER | S1: MA | T1: NET
A2: 336358 | B2: 33635800000 | C2: Cost Management-Inventory | D2: 336 | E2: 2 | F2: 2026-05-20T00:00:00+07:00 | G2: 30734260 | H2: 1574 | I2: Xuất TI Trung thế qua Đội TH2- Cty Thí Nghiệm Điện lực Thí Nghiệm | J2: 45000000 | K2: 0 | L2: THANH5DT.HCM.VTA | M2: 082900 | N2: 080100 | O2: 5 | P2: 2026 | Q2: DATA_PHATSINH1 | R2: 0 | S2: =A2&M2 -> 336358082900 | T2: =IF(M2="080100",J2-K2,K2-J2) -> -45000000
A3: 336358 | B3: 33635800000 | C3: Cost Management-Inventory | D3: 336 | E3: 2 | F3: 2026-05-20T00:00:00+07:00 | G3: 30734261 | H3: 1574 | I3: Xuất TI Trung thế qua Đội TH2- Cty Thí Nghiệm Điện lực Thí Nghiệm | J3: 45000000 | K3: 0 | L3: THANH5DT.HCM.VTA | M3: 082900 | N3: 080100 | O3: 5 | P3: 2026 | Q3: DATA_PHATSINH2 | R3: 1 | S3: =A3&M3 -> 336358082900 | T3: =IF(M3="080100",J3-K3,K3-J3) -> -45000000
A4: 336358 | B4: 33635800000 | C4: Cost Management-Inventory | D4: 336 | E4: 2 | F4: 2026-05-20T00:00:00+07:00 | G4: 30734259 | H4: 1574 | I4: Xuất TI Trung thế qua Đội TH2- Cty Thí Nghiệm Điện lực Thí Nghiệm | J4: 45000000 | K4: 0 | L4: THANH5DT.HCM.VTA | M4: 082900 | N4: 080100 | O4: 5 | P4: 2026 | Q4: DATA_PHATSINH3 | R4: 2 | S4: =A4&M4 -> 336358082900 | T4: =IF(M4="080100",J4-K4,K4-J4) -> -45000000
A5: 336358 | B5: 33635800000 | C5: Cost Management-Inventory | D5: 336 | E5: 2 | F5: 2026-05-20T00:00:00+07:00 | G5: 30734244 | H5: 1574 | I5: Xuất TI Trung thế qua Đội TH2- Cty Thí Nghiệm Điện lực Thí Nghiệm | J5: 49200000 | K5: 0 | L5: THANH5DT.HCM.VTA | M5: 082900 | N5: 080100 | O5: 5 | P5: 2026 | Q5: DATA_PHATSINH4 | R5: 3 | S5: =A5&M5 -> 336358082900 | T5: =IF(M5="080100",J5-K5,K5-J5) -> -49200000
A6: 336358 | B6: 33635800000 | C6: Cost Management-Inventory | D6: 336 | E6: 2 | F6: 2026-05-20T00:00:00+07:00 | G6: 30734245 | H6: 1574 | I6: Xuất TI Trung thế qua Đội TH2- Cty Thí Nghiệm Điện lực Thí Nghiệm | J6: 52800000 | K6: 0 | L6: THANH5DT.HCM.VTA | M6: 082900 | N6: 080100 | O6: 5 | P6: 2026 | Q6: DATA_PHATSINH5 | R6: 4 | S6: =A6&M6 -> 336358082900 | T6: =IF(M6="080100",J6-K6,K6-J6) -> -52800000
A7: 336358 | B7: 33635800000 | C7: Cost Management-Inventory | D7: 336 | E7: 2 | F7: 2026-05-20T00:00:00+07:00 | G7: 30734258 | H7: 1574 | I7: Xuất TI Trung thế qua Đội TH2- Cty Thí Nghiệm Điện lực Thí Nghiệm | J7: 54000000 | K7: 0 | L7: THANH5DT.HCM.VTA | M7: 082900 | N7: 080100 | O7: 5 | P7: 2026 | Q7: DATA_PHATSINH6 | R7: 5 | S7: =A7&M7 -> 336358082900 | T7: =IF(M7="080100",J7-K7,K7-J7) -> -54000000
A8: 336358 | B8: 33635800000 | C8: Cost Management-Inventory | D8: 336 | E8: 2 | F8: 2026-05-11T00:00:00+07:00 | G8: 30682048 | H8: 1573 | I8: Xuất công tơ lên Cty Thí Nghiệm kiểm định ( VB : 2005/PCVT-KHVT ) | J8: 61055399 | K8: 0 | L8: THANH5DT.HCM.VTA | M8: 082900 | N8: 080100 | O8: 5 | P8: 2026 | Q8: DATA_PHATSINH7 | R8: 6 | S8: =A8&M8 -> 336358082900 | T8: =IF(M8="080100",J8-K8,K8-J8) -> -61055399
A9: 336358 | B9: 33635800000 | C9: Cost Management-Inventory | D9: 336 | E9: 2 | F9: 2026-05-29T00:00:00+07:00 | G9: 30793502 | H9: 1585 | I9: Xuất công tơ 1 pha 3 giá lên kiểm định | J9: 70059644 | K9: 0 | L9: THANH5DT.HCM.VTA | M9: 082900 | N9: 080100 | O9: 5 | P9: 2026 | Q9: DATA_PHATSINH8 | R9: 7 | S9: =A9&M9 -> 336358082900 | T9: =IF(M9="080100",J9-K9,K9-J9) -> -70059644
A10: 336358 | B10: 33635800000 | C10: Cost Management-Inventory | D10: 336 | E10: 2 | F10: 2026-05-20T00:00:00+07:00 | G10: 30734246 | H10: 1574 | I10: Xuất TI Trung thế qua Đội TH2- Cty Thí Nghiệm Điện lực Thí Nghiệm | J10: 74711443 | K10: 0 | L10: THANH5DT.HCM.VTA | M10: 082900 | N10: 080100 | O10: 5 | P10: 2026 | Q10: DATA_PHATSINH9 | R10: 8 | S10: =A10&M10 -> 336358082900 | T10: =IF(M10="080100",J10-K10,K10-J10) -> -74711443
A11: 336358 | B11: 33635800000 | C11: Cost Management-Inventory | D11: 336 | E11: 2 | F11: 2026-05-20T00:00:00+07:00 | G11: 30734242 | H11: 1574 | I11: Xuất TI Trung thế qua Đội TH2- Cty Thí Nghiệm Điện lực Thí Nghiệm | J11: 79200000 | K11: 0 | L11: THANH5DT.HCM.VTA | M11: 082900 | N11: 080100 | O11: 5 | P11: 2026 | Q11: DATA_PHATSINH10 | R11: 9 | S11: =A11&M11 -> 336358082900 | T11: =IF(M11="080100",J11-K11,K11-J11) -> -79200000
A12: 336358 | B12: 33635800000 | C12: Cost Management-Inventory | D12: 336 | E12: 2 | F12: 2026-05-20T00:00:00+07:00 | G12: 30734262 | H12: 1574 | I12: Xuất TI Trung thế qua Đội TH2- Cty Thí Nghiệm Điện lực Thí Nghiệm | J12: 30000000 | K12: 0 | L12: THANH5DT.HCM.VTA | M12: 082900 | N12: 080100 | O12: 5 | P12: 2026 | Q12: DATA_PHATSINH11 | R12: 10 | S12: =A12&M12 -> 336358082900 | T12: =IF(M12="080100",J12-K12,K12-J12) -> -30000000
A13: 336358 | B13: 33635800000 | C13: Cost Management-Inventory | D13: 336 | E13: 2 | F13: 2026-05-25T00:00:00+07:00 | G13: 30757320 | H13: 1580 | I13: Xuất công tơ lên Cty Thí Nghiệm cài đặt lại tỉ số | J13: 89940000 | K13: 0 | L13: THANH5DT.HCM.VTA | M13: 082900 | N13: 080100 | O13: 5 | P13: 2026 | Q13: DATA_PHATSINH12 | R13: 11 | S13: =A13&M13 -> 336358082900 | T13: =IF(M13="080100",J13-K13,K13-J13) -> -89940000
... A118: 3363883 | B118: 33638830000 | C118: Cost Management-Inventory | D118: 336 | E118: 2 | F118: 2026-05-27T00:00:00+07:00 | G118: 30777785 | H118: 1587 | I118: 25041: Nhập Vtư điều động TB 2431/TB-EVNHCMC ngày 15.5.26, theo HD số 761/26.05.26 của TCty ĐLTPHCM (03.UVL.57.0047/26.05.26) | J118: 0 | K118: 4700000000 | L118: THANH5DT.HCM.VTA | M118: 082900 | N118: 080100 | O118: 5 | P118: 2026 | Q118: DATA_PHATSINH117 | R118: 116 | S118: =A118&M118 -> 3363883082900 | T118: =IF(M118="080100",J118-K118,K118-J118) -> 4700000000
A119: 1363111 | B119: 13631110000 | C119: GL-MANUAL | D119: 136 | E119: 1 | F119: 2026-05-31T00:00:00+07:00 | H119: 5092 | I119: KC PTNB TIEN DIEN THANG 5-2026 - PCVT | J119: 0 | K119: 1006728865803 | L119: ANHTTL.HCM.NG | M119: 080100 | N119: 082900 | O119: 5 | P119: 2026 | Q119: DATA_PHATSINH118 | R119: 117 | S119: =A119&M119 -> 1363111080100 | T119: =IF(M119="080100",J119-K119,K119-J119) -> -1006728865803
A120: 1363111 | B120: 13631110000 | C120: GL-MANUAL | D120: 136 | E120: 1 | F120: 2026-05-31T00:00:00+07:00 | H120: 5047 | I120: THOÁI HOÀN TIỀN ĐIỆN THÁNG 05/2026 Vũng Tàu | J120: 40655098 | K120: 0 | L120: TRANGLTT.HCM.NG | M120: 080100 | N120: 082900 | O120: 5 | P120: 2026 | Q120: DATA_PHATSINH119 | R120: 118 | S120: =A120&M120 -> 1363111080100 | T120: =IF(M120="080100",J120-K120,K120-J120) -> 40655098
A121: 136358 | B121: 13635800000 | C121: GL-MANUAL | D121: 136 | E121: 1 | F121: 2026-05-31T00:00:00+07:00 | H121: 5029 | I121: VTDD T5/2026 VT (SXKD) | J121: 0 | K121: 1619307789 | L121: NAM7NH.HCM.NG | M121: 080100 | N121: 082900 | O121: 5 | P121: 2026 | Q121: DATA_PHATSINH120 | R121: 119 | S121: =A121&M121 -> 136358080100 | T121: =IF(M121="080100",J121-K121,K121-J121) -> -1619307789
A122: 1363883 | B122: 13638830000 | C122: GL-MANUAL | D122: 136 | E122: 1 | F122: 2026-05-31T00:00:00+07:00 | H122: 5035 | I122: VTDD T05/2026 DVĐL -> VT | J122: 17718778000 | K122: 0 | L122: NAM7NH.HCM.NG | M122: 080100 | N122: 082900 | O122: 5 | P122: 2026 | Q122: DATA_PHATSINH121 | R122: 120 | S122: =A122&M122 -> 1363883080100 | T122: =IF(M122="080100",J122-K122,K122-J122) -> 17718778000
A123: 3363888 | B123: 33638880000 | C123: GL-MANUAL | D123: 336 | E123: 2 | F123: 2026-05-31T00:00:00+07:00 | H123: 5047 | I123: THOÁI HOÀN TIỀN ĐIỆN T.05/2026 | J123: 0 | K123: 40655098 | L123: TRANGLTT.HCM.NG | M123: 080100 | N123: 082900 | O123: 5 | P123: 2026 | Q123: DATA_PHATSINH122 | R123: 121 | S123: =A123&M123 -> 3363888080100 | T123: =IF(M123="080100",J123-K123,K123-J123) -> -40655098
A124: 136358 | B124: 13635800000 | C124: GL-MANUAL | D124: 136 | E124: 1 | F124: 2026-05-31T00:00:00+07:00 | H124: 5032 | I124: VTDD T5/2026 TNĐL -> VT | J124: 1579969634 | K124: 0 | L124: NAM7NH.HCM.NG | M124: 080100 | N124: 082900 | O124: 5 | P124: 2026 | Q124: DATA_PHATSINH123 | R124: 122 | S124: =A124&M124 -> 136358080100 | T124: =IF(M124="080100",J124-K124,K124-J124) -> 1579969634
A125: 136358 | B125: 13635800000 | C125: GL-MANUAL | D125: 136 | E125: 1 | F125: 2026-05-31T00:00:00+07:00 | H125: 5035 | I125: VTDD T05/2026 DVĐL -> VT | J125: 1397373643 | K125: 0 | L125: NAM7NH.HCM.NG | M125: 080100 | N125: 082900 | O125: 5 | P125: 2026 | Q125: DATA_PHATSINH124 | R125: 123 | S125: =A125&M125 -> 136358080100 | T125: =IF(M125="080100",J125-K125,K125-J125) -> 1397373643
A126: 33688 | B126: 33688000000 | C126: GL-MANUAL | D126: 336 | E126: 2 | F126: 2026-05-31T00:00:00+07:00 | H126: 5092 | I126: KC PTNB TIEN DIEN THANG 5-2026 - PCVT | J126: 1006728865803 | K126: 0 | L126: ANHTTL.HCM.NG | M126: 080100 | N126: 082900 | O126: 5 | P126: 2026 | Q126: DATA_PHATSINH125 | R126: 124 | S126: =A126&M126 -> 33688080100 | T126: =IF(M126="080100",J126-K126,K126-J126) -> 1006728865803
A127: 33688 | B127: 33688000000 | C127: GL-MANUAL | D127: 336 | E127: 2 | F127: 2026-05-31T00:00:00+07:00 | H127: 5092 | I127: KC PTNB TIEN DIEN THANG 5-2026 - PCVT (VC) | J127: 301236589 | K127: 0 | L127: ANHTTL.HCM.NG | M127: 080100 | N127: 082900 | O127: 5 | P127: 2026 | Q127: DATA_PHATSINH126 | R127: 125 | S127: =A127&M127 -> 33688080100 | T127: =IF(M127="080100",J127-K127,K127-J127) -> 301236589
A128: 1363112 | B128: 13631120000 | C128: GL-MANUAL | D128: 136 | E128: 1 | F128: 2026-05-31T00:00:00+07:00 | H128: 5092 | I128: KC PTNB TIEN DIEN THANG 5-2026 - PCVT (VC) | J128: 0 | K128: 301236589 | L128: ANHTTL.HCM.NG | M128: 080100 | N128: 082900 | O128: 5 | P128: 2026 | Q128: DATA_PHATSINH127 | R128: 126 | S128: =A128&M128 -> 1363112080100 | T128: =IF(M128="080100",J128-K128,K128-J128) -> -301236589
A129: 336358 | B129: 33635800000 | C129: GL-MANUAL | D129: 336 | E129: 2 | F129: 2026-05-31T00:00:00+07:00 | H129: 1631 | I129: Kết chuyển công nợ nội bộ tháng 05/2026 | J129: 47447508936 | K129: 0 | L129: DUYENTT.HCM.VTA | M129: 082900 | N129: 080100 | O129: 5 | P129: 2026 | Q129: DATA_PHATSINH128 | R129: 127 | S129: =A129&M129 -> 336358082900 | T129: =IF(M129="080100",J129-K129,K129-J129) -> -47447508936
A130: 3363883 | B130: 33638830000 | C130: GL-MANUAL | D130: 336 | E130: 2 | F130: 2026-05-31T00:00:00+07:00 | H130: 1361 | I130: Thuế GTGT VTĐĐ- hđơn 666-11.05.26-TỔNG CÔNG TY ĐIỆN LỰC THÀNH PHỐ HỒ CHÍ MINH | J130: 0 | K130: 25728000 | L130: THANH5DT.HCM.VTA | M130: 082900 | N130: 080100 | O130: 5 | P130: 2026 | Q130: DATA_PHATSINH129 | R130: 128 | S130: =A130&M130 -> 3363883082900 | T130: =IF(M130="080100",J130-K130,K130-J130) -> 25728000
... A326: 136358 | B326: 13635800000 | C326: MassAllocation-Allocation | D326: 136 | E326: 1 | F326: 2026-05-31T00:00:00+07:00 | H326: 1613 | I326: K/c 64298 (Điện) > 136358 | J326: 824548335 | K326: 0 | L326: DUYENTT.HCM.VTA | M326: 082900 | N326: 080100 | O326: 5 | P326: 2026 | Q326: DATA_PHATSINH325 | R326: 324 | S326: =A326&M326 -> 136358082900 | T326: =IF(M326="080100",J326-K326,K326-J326) -> -824548335
A327: 3363112 | B327: 33631120000 | C327: Receivables-Credit Memos | D327: 336 | E327: 2 | F327: 2026-05-29T00:00:00+07:00 | G327: 1635 | H327: 1431 | I327: Giải trừ tiền vô công thu hộ CTĐLVT ngày 29/05/2026 | J327: 250601 | K327: 0 | L327: CHAULTN.HCM.VTA | M327: 082900 | N327: 080100 | O327: 5 | P327: 2026 | Q327: DATA_PHATSINH326 | R327: 325 | S327: =A327&M327 -> 3363112082900 | T327: =IF(M327="080100",J327-K327,K327-J327) -> -250601
A328: 3363112 | B328: 33631120000 | C328: Receivables-Credit Memos | D328: 336 | E328: 2 | F328: 2026-05-20T00:00:00+07:00 | G328: 1581 | H328: 1424 | I328: Giải trừ tiền vô công thu hộ CTĐLVT ngày 20/05/2026 | J328: 556655 | K328: 0 | L328: CHAULTN.HCM.VTA | M328: 082900 | N328: 080100 | O328: 5 | P328: 2026 | Q328: DATA_PHATSINH327 | R328: 326 | S328: =A328&M328 -> 3363112082900 | T328: =IF(M328="080100",J328-K328,K328-J328) -> -556655
A329: 3363112 | B329: 33631120000 | C329: Receivables-Credit Memos | D329: 336 | E329: 2 | F329: 2026-05-21T00:00:00+07:00 | G329: 1611 | H329: 1436 | I329: Giải trừ tiền vô công thu hộ CTĐLVT ngày 21/05/2026 | J329: 928022 | K329: 0 | L329: CHAULTN.HCM.VTA | M329: 082900 | N329: 080100 | O329: 5 | P329: 2026 | Q329: DATA_PHATSINH328 | R329: 327 | S329: =A329&M329 -> 3363112082900 | T329: =IF(M329="080100",J329-K329,K329-J329) -> -928022
A330: 3363112 | B330: 33631120000 | C330: Receivables-Credit Memos | D330: 336 | E330: 2 | F330: 2026-05-11T00:00:00+07:00 | G330: 1591 | H330: 1435 | I330: Giải trừ tiền vô công thu hộ CTĐLVT ngày 11/05/2026 | J330: 1195232 | K330: 0 | L330: CHAULTN.HCM.VTA | M330: 082900 | N330: 080100 | O330: 5 | P330: 2026 | Q330: DATA_PHATSINH329 | R330: 328 | S330: =A330&M330 -> 3363112082900 | T330: =IF(M330="080100",J330-K330,K330-J330) -> -1195232
A331: 3363112 | B331: 33631120000 | C331: Receivables-Credit Memos | D331: 336 | E331: 2 | F331: 2026-05-19T00:00:00+07:00 | G331: 1578 | H331: 1418 | I331: Giải trừ tiền vô công thu hộ CTĐLVT ngày 19/05/2026 | J331: 2635359 | K331: 0 | L331: CHAULTN.HCM.VTA | M331: 082900 | N331: 080100 | O331: 5 | P331: 2026 | Q331: DATA_PHATSINH330 | R331: 329 | S331: =A331&M331 -> 3363112082900 | T331: =IF(M331="080100",J331-K331,K331-J331) -> -2635359
A332: 3363112 | B332: 33631120000 | C332: Receivables-Credit Memos | D332: 336 | E332: 2 | F332: 2026-05-13T00:00:00+07:00 | G332: 1594 | H332: 1421 | I332: Giải trừ tiền vô công thu hộ CTĐLVT ngày 13/05/2026 | J332: 3954874 | K332: 0 | L332: CHAULTN.HCM.VTA | M332: 082900 | N332: 080100 | O332: 5 | P332: 2026 | Q332: DATA_PHATSINH331 | R332: 330 | S332: =A332&M332 -> 3363112082900 | T332: =IF(M332="080100",J332-K332,K332-J332) -> -3954874
A333: 3363111 | B333: 33631110000 | C333: Receivables-Credit Memos | D333: 336 | E333: 2 | F333: 2026-05-01T00:00:00+07:00 | G333: 1555 | H333: 1423 | I333: Giải trừ tiền điện thu hộ CTĐLVT ngày 01/05/2026 | J333: 18128980 | K333: 0 | L333: CHAULTN.HCM.VTA | M333: 082900 | N333: 080100 | O333: 5 | P333: 2026 | Q333: DATA_PHATSINH332 | R333: 331 | S333: =A333&M333 -> 3363111082900 | T333: =IF(M333="080100",J333-K333,K333-J333) -> -18128980
A334: 3363111 | B334: 33631110000 | C334: Receivables-Credit Memos | D334: 336 | E334: 2 | F334: 2026-05-02T00:00:00+07:00 | G334: 1556 | H334: 1426 | I334: Giải trừ tiền điện thu hộ CTĐLVT ngày 02/05/2026 | J334: 26816550 | K334: 0 | L334: CHAULTN.HCM.VTA | M334: 082900 | N334: 080100 | O334: 5 | P334: 2026 | Q334: DATA_PHATSINH333 | R334: 332 | S334: =A334&M334 -> 3363111082900 | T334: =IF(M334="080100",J334-K334,K334-J334) -> -26816550
A335: 3363111 | B335: 33631110000 | C335: Receivables-Credit Memos | D335: 336 | E335: 2 | F335: 2026-05-31T00:00:00+07:00 | G335: 1637 | H335: 1410 | I335: Giải trừ tiền điện thu hộ CTĐLVT ngày 31/05/2026 | J335: 124625041 | K335: 0 | L335: CHAULTN.HCM.VTA | M335: 082900 | N335: 080100 | O335: 5 | P335: 2026 | Q335: DATA_PHATSINH334 | R335: 333 | S335: =A335&M335 -> 3363111082900 | T335: =IF(M335="080100",J335-K335,K335-J335) -> -124625041
A336: 3363111 | B336: 33631110000 | C336: Receivables-Credit Memos | D336: 336 | E336: 2 | F336: 2026-05-29T00:00:00+07:00 | G336: 1634 | H336: 1431 | I336: Giải trừ tiền điện thu hộ CTĐLVT ngày 29/05/2026 | J336: 213369327 | K336: 0 | L336: CHAULTN.HCM.VTA | M336: 082900 | N336: 080100 | O336: 5 | P336: 2026 | Q336: DATA_PHATSINH335 | R336: 334 | S336: =A336&M336 -> 3363111082900 | T336: =IF(M336="080100",J336-K336,K336-J336) -> -213369327
A337: 3363111 | B337: 33631110000 | C337: Receivables-Credit Memos | D337: 336 | E337: 2 | F337: 2026-05-30T00:00:00+07:00 | G337: 1636 | H337: 1432 | I337: Giải trừ tiền điện thu hộ CTĐLVT ngày 30/05/2026 | J337: 240583866 | K337: 0 | L337: CHAULTN.HCM.VTA | M337: 082900 | N337: 080100 | O337: 5 | P337: 2026 | Q337: DATA_PHATSINH336 | R337: 335 | S337: =A337&M337 -> 3363111082900 | T337: =IF(M337="080100",J337-K337,K337-J337) -> -240583866
A338: 3363111 | B338: 33631110000 | C338: Receivables-Credit Memos | D338: 336 | E338: 2 | F338: 2026-05-28T00:00:00+07:00 | G338: 1645 | H338: 1434 | I338: Giải trừ tiền điện thu hộ CTĐLVT ngày 28/05/2026 | J338: 261690745 | K338: 0 | L338: CHAULTN.HCM.VTA | M338: 082900 | N338: 080100 | O338: 5 | P338: 2026 | Q338: DATA_PHATSINH337 | R338: 336 | S338: =A338&M338 -> 3363111082900 | T338: =IF(M338="080100",J338-K338,K338-J338) -> -261690745
... A373: 3363112 | B373: 33631120000 | C373: Receivables-Credit Memos | D373: 336 | E373: 2 | F373: 2026-05-04T00:00:00+07:00 | G373: 1568 | H373: 1419 | I373: Giải trừ tiền vô công thu hộ CTĐLVT ngày 04/05/2026 | J373: 121340050 | K373: 0 | L373: CHAULTN.HCM.VTA | M373: 082900 | N373: 080100 | O373: 5 | P373: 2026 | Q373: DATA_PHATSINH372 | R373: 371 | S373: =A373&M373 -> 3363112082900 | T373: =IF(M373="080100",J373-K373,K373-J373) -> -121340050
A374: 1363111 | B374: 13631110000 | C374: Receivables-Misc Receipts | D374: 136 | E374: 1 | F374: 2026-05-20T00:00:00+07:00 | G374: SCBO202605200 | H374: 5110 | I374: TD - SCB - VTA | J374: 0 | K374: 88933877 | L374: VIETDT.HCM.NG | M374: 080100 | N374: 082900 | O374: 5 | P374: 2026 | Q374: DATA_PHATSINH373 | R374: 372 | S374: =A374&M374 -> 1363111080100 | T374: =IF(M374="080100",J374-K374,K374-J374) -> -88933877
A375: 1363111 | B375: 13631110000 | C375: Receivables-Misc Receipts | D375: 136 | E375: 1 | F375: 2026-05-12T00:00:00+07:00 | G375: MSBO202605120 | H375: 5103 | I375: TD - MSB - VTA | J375: 0 | K375: 84516579 | L375: VIETDT.HCM.NG | M375: 080100 | N375: 082900 | O375: 5 | P375: 2026 | Q375: DATA_PHATSINH374 | R375: 373 | S375: =A375&M375 -> 1363111080100 | T375: =IF(M375="080100",J375-K375,K375-J375) -> -84516579
A376: 1363111 | B376: 13631110000 | C376: Receivables-Misc Receipts | D376: 136 | E376: 1 | F376: 2026-05-27T00:00:00+07:00 | G376: MBBO202605270 | H376: 5097 | I376: TD - MBB - VTA | J376: 0 | K376: 86866749 | L376: VIETDT.HCM.NG | M376: 080100 | N376: 082900 | O376: 5 | P376: 2026 | Q376: DATA_PHATSINH375 | R376: 374 | S376: =A376&M376 -> 1363111080100 | T376: =IF(M376="080100",J376-K376,K376-J376) -> -86866749
A377: 1363111 | B377: 13631110000 | C377: Receivables-Misc Receipts | D377: 136 | E377: 1 | F377: 2026-05-22T00:00:00+07:00 | G377: MSBO202605220 | H377: 5116 | I377: TD - MSB - VTA | J377: 0 | K377: 88493407 | L377: VIETDT.HCM.NG | M377: 080100 | N377: 082900 | O377: 5 | P377: 2026 | Q377: DATA_PHATSINH376 | R377: 375 | S377: =A377&M377 -> 1363111080100 | T377: =IF(M377="080100",J377-K377,K377-J377) -> -88493407
A378: 1363111 | B378: 13631110000 | C378: Receivables-Misc Receipts | D378: 136 | E378: 1 | F378: 2026-05-16T00:00:00+07:00 | G378: TCBO202605160 | H378: 5118 | I378: TD - TCB - VTA | J378: 0 | K378: 94160779 | L378: VIETDT.HCM.NG | M378: 080100 | N378: 082900 | O378: 5 | P378: 2026 | Q378: DATA_PHATSINH377 | R378: 376 | S378: =A378&M378 -> 1363111080100 | T378: =IF(M378="080100",J378-K378,K378-J378) -> -94160779
A379: 1363111 | B379: 13631110000 | C379: Receivables-Misc Receipts | D379: 136 | E379: 1 | F379: 2026-05-17T00:00:00+07:00 | G379: MBBO202605170 | H379: 5093 | I379: TD - MBB - VTA | J379: 0 | K379: 75050451 | L379: VIETDT.HCM.NG | M379: 080100 | N379: 082900 | O379: 5 | P379: 2026 | Q379: DATA_PHATSINH378 | R379: 377 | S379: =A379&M379 -> 1363111080100 | T379: =IF(M379="080100",J379-K379,K379-J379) -> -75050451
A380: 1363111 | B380: 13631110000 | C380: Receivables-Misc Receipts | D380: 136 | E380: 1 | F380: 2026-05-03T00:00:00+07:00 | G380: SGBO202605030 | H380: 5113 | I380: TD - SGB - VTA | J380: 0 | K380: 75051682 | L380: VIETDT.HCM.NG | M380: 080100 | N380: 082900 | O380: 5 | P380: 2026 | Q380: DATA_PHATSINH379 | R380: 378 | S380: =A380&M380 -> 1363111080100 | T380: =IF(M380="080100",J380-K380,K380-J380) -> -75051682
A381: 1363111 | B381: 13631110000 | C381: Receivables-Misc Receipts | D381: 136 | E381: 1 | F381: 2026-05-10T00:00:00+07:00 | G381: PVCBO202605100 | H381: 5120 | I381: TD - PVCB - VTA | J381: 0 | K381: 76018486 | L381: VIETDT.HCM.NG | M381: 080100 | N381: 082900 | O381: 5 | P381: 2026 | Q381: DATA_PHATSINH380 | R381: 379 | S381: =A381&M381 -> 1363111080100 | T381: =IF(M381="080100",J381-K381,K381-J381) -> -76018486
A382: 1363111 | B382: 13631110000 | C382: Receivables-Misc Receipts | D382: 136 | E382: 1 | F382: 2026-05-12T00:00:00+07:00 | G382: OCBO202605120 | H382: 5103 | I382: TD - OCB - VTA | J382: 0 | K382: 76280856 | L382: VIETDT.HCM.NG | M382: 080100 | N382: 082900 | O382: 5 | P382: 2026 | Q382: DATA_PHATSINH381 | R382: 380 | S382: =A382&M382 -> 1363111080100 | T382: =IF(M382="080100",J382-K382,K382-J382) -> -76280856
A383: 1363111 | B383: 13631110000 | C383: Receivables-Misc Receipts | D383: 136 | E383: 1 | F383: 2026-05-19T00:00:00+07:00 | G383: BIDVO202605190 | H383: 5095 | I383: TD - BIDV - VTA | J383: 0 | K383: 77043715 | L383: VIETDT.HCM.NG | M383: 080100 | N383: 082900 | O383: 5 | P383: 2026 | Q383: DATA_PHATSINH382 | R383: 381 | S383: =A383&M383 -> 1363111080100 | T383: =IF(M383="080100",J383-K383,K383-J383) -> -77043715
A384: 1363111 | B384: 13631110000 | C384: Receivables-Misc Receipts | D384: 136 | E384: 1 | F384: 2026-05-07T00:00:00+07:00 | G384: ABBO202605070 | H384: 5112 | I384: TD - ABB - VTA | J384: 0 | K384: 77819230 | L384: VIETDT.HCM.NG | M384: 080100 | N384: 082900 | O384: 5 | P384: 2026 | Q384: DATA_PHATSINH383 | R384: 382 | S384: =A384&M384 -> 1363111080100 | T384: =IF(M384="080100",J384-K384,K384-J384) -> -77819230
A385: 1363111 | B385: 13631110000 | C385: Receivables-Misc Receipts | D385: 136 | E385: 1 | F385: 2026-05-19T00:00:00+07:00 | G385: PVCBO202605190 | H385: 5095 | I385: TD - PVCB - VTA | J385: 0 | K385: 78345218 | L385: VIETDT.HCM.NG | M385: 080100 | N385: 082900 | O385: 5 | P385: 2026 | Q385: DATA_PHATSINH384 | R385: 383 | S385: =A385&M385 -> 1363111080100 | T385: =IF(M385="080100",J385-K385,K385-J385) -> -78345218
... A1005: 336358 | B1005: 33635800000 | C1005: Receivables-Misc Receipts | D1005: 336 | E1005: 2 | F1005: 2026-05-21T00:00:00+07:00 | G1005: G0526AG024 | H1005: 1453 | I1005: Nhập tiền Tổng công ty HCM cấp tiền thanh toán Điện MTMN T04-2026 Đợt 1 | J1005: 0 | K1005: 22000000000 | L1005: CHAULTN.HCM.VTA | M1005: 082900 | N1005: 080100 | O1005: 5 | P1005: 2026 | Q1005: DATA_PHATSINH1004 | R1005: 1003 | S1005: =A1005&M1005 -> 336358082900 | T1005: =IF(M1005="080100",J1005-K1005,K1005-J1005) -> 22000000000
A1006: 1363111 | B1006: 13631110000 | C1006: Receivables-Sales Invoices | D1006: 136 | E1006: 1 | F1006: 2026-05-31T00:00:00+07:00 | G1006: 42445 | H1006: 5162 | I1006: Viettel 31/05/2026 | J1006: 0 | K1006: 2220205 | L1006: VIETDT.HCM.NG | M1006: 080100 | N1006: 082900 | O1006: 5 | P1006: 2026 | Q1006: DATA_PHATSINH1005 | R1006: 1004 | S1006: =A1006&M1006 -> 1363111080100 | T1006: =IF(M1006="080100",J1006-K1006,K1006-J1006) -> -2220205
A1007: 1363111 | B1007: 13631110000 | C1007: Receivables-Sales Invoices | D1007: 136 | E1007: 1 | F1007: 2026-05-10T00:00:00+07:00 | G1007: 42597 | H1007: 5164 | I1007: MService 10/05/2026 | J1007: 0 | K1007: 1459203482 | L1007: VIETDT.HCM.NG | M1007: 080100 | N1007: 082900 | O1007: 5 | P1007: 2026 | Q1007: DATA_PHATSINH1006 | R1007: 1005 | S1007: =A1007&M1007 -> 1363111080100 | T1007: =IF(M1007="080100",J1007-K1007,K1007-J1007) -> -1459203482
A1008: 1363111 | B1008: 13631110000 | C1008: Receivables-Sales Invoices | D1008: 136 | E1008: 1 | F1008: 2026-05-09T00:00:00+07:00 | G1008: 42643 | H1008: 5178 | I1008: Payoo 09/05/2026 | J1008: 0 | K1008: 1112524013 | L1008: VIETDT.HCM.NG | M1008: 080100 | N1008: 082900 | O1008: 5 | P1008: 2026 | Q1008: DATA_PHATSINH1007 | R1008: 1006 | S1008: =A1008&M1008 -> 1363111080100 | T1008: =IF(M1008="080100",J1008-K1008,K1008-J1008) -> -1112524013
A1009: 1363111 | B1009: 13631110000 | C1009: Receivables-Sales Invoices | D1009: 136 | E1009: 1 | F1009: 2026-05-13T00:00:00+07:00 | G1009: 42600 | H1009: 5183 | I1009: MService 13/05/2026 | J1009: 0 | K1009: 1141796009 | L1009: VIETDT.HCM.NG | M1009: 080100 | N1009: 082900 | O1009: 5 | P1009: 2026 | Q1009: DATA_PHATSINH1008 | R1009: 1007 | S1009: =A1009&M1009 -> 1363111080100 | T1009: =IF(M1009="080100",J1009-K1009,K1009-J1009) -> -1141796009
A1010: 1363111 | B1010: 13631110000 | C1010: Receivables-Sales Invoices | D1010: 136 | E1010: 1 | F1010: 2026-05-01T00:00:00+07:00 | G1010: 42631 | H1010: 5185 | I1010: Airpay 01/05/2026 | J1010: 0 | K1010: 2881440 | L1010: VIETDT.HCM.NG | M1010: 080100 | N1010: 082900 | O1010: 5 | P1010: 2026 | Q1010: DATA_PHATSINH1009 | R1010: 1008 | S1010: =A1010&M1010 -> 1363111080100 | T1010: =IF(M1010="080100",J1010-K1010,K1010-J1010) -> -2881440
A1011: 1363111 | B1011: 13631110000 | C1011: Receivables-Sales Invoices | D1011: 136 | E1011: 1 | F1011: 2026-05-16T00:00:00+07:00 | G1011: 42484 | H1011: 5175 | I1011: Paytech 16/05/2026 | J1011: 0 | K1011: 2897311 | L1011: VIETDT.HCM.NG | M1011: 080100 | N1011: 082900 | O1011: 5 | P1011: 2026 | Q1011: DATA_PHATSINH1010 | R1011: 1009 | S1011: =A1011&M1011 -> 1363111080100 | T1011: =IF(M1011="080100",J1011-K1011,K1011-J1011) -> -2897311
A1012: 1363111 | B1012: 13631110000 | C1012: Receivables-Sales Invoices | D1012: 136 | E1012: 1 | F1012: 2026-05-12T00:00:00+07:00 | G1012: 42599 | H1012: 5170 | I1012: MService 12/05/2026 | J1012: 0 | K1012: 1128217913 | L1012: VIETDT.HCM.NG | M1012: 080100 | N1012: 082900 | O1012: 5 | P1012: 2026 | Q1012: DATA_PHATSINH1011 | R1012: 1010 | S1012: =A1012&M1012 -> 1363111080100 | T1012: =IF(M1012="080100",J1012-K1012,K1012-J1012) -> -1128217913
A1013: 1363111 | B1013: 13631110000 | C1013: Receivables-Sales Invoices | D1013: 136 | E1013: 1 | F1013: 2026-05-07T00:00:00+07:00 | G1013: 42452 | H1013: 5176 | I1013: ZaloPay 07/05/2026 | J1013: 0 | K1013: 1031274050 | L1013: VIETDT.HCM.NG | M1013: 080100 | N1013: 082900 | O1013: 5 | P1013: 2026 | Q1013: DATA_PHATSINH1012 | R1013: 1011 | S1013: =A1013&M1013 -> 1363111080100 | T1013: =IF(M1013="080100",J1013-K1013,K1013-J1013) -> -1031274050
A1014: 1363111 | B1014: 13631110000 | C1014: Receivables-Sales Invoices | D1014: 136 | E1014: 1 | F1014: 2026-05-10T00:00:00+07:00 | G1014: 42644 | H1014: 5164 | I1014: Payoo 10/05/2026 | J1014: 0 | K1014: 1052685805 | L1014: VIETDT.HCM.NG | M1014: 080100 | N1014: 082900 | O1014: 5 | P1014: 2026 | Q1014: DATA_PHATSINH1013 | R1014: 1012 | S1014: =A1014&M1014 -> 1363111080100 | T1014: =IF(M1014="080100",J1014-K1014,K1014-J1014) -> -1052685805
A1015: 1363111 | B1015: 13631110000 | C1015: Receivables-Sales Invoices | D1015: 136 | E1015: 1 | F1015: 2026-05-26T00:00:00+07:00 | G1015: 42518 | H1015: 5166 | I1015: VNPTPay 26/05/2026 | J1015: 0 | K1015: 2503494 | L1015: VIETDT.HCM.NG | M1015: 080100 | N1015: 082900 | O1015: 5 | P1015: 2026 | Q1015: DATA_PHATSINH1014 | R1015: 1013 | S1015: =A1015&M1015 -> 1363111080100 | T1015: =IF(M1015="080100",J1015-K1015,K1015-J1015) -> -2503494
A1016: 1363111 | B1016: 13631110000 | C1016: Receivables-Sales Invoices | D1016: 136 | E1016: 1 | F1016: 2026-05-28T00:00:00+07:00 | G1016: 42584 | H1016: 5167 | I1016: VNPay 28/05/2026 | J1016: 0 | K1016: 2530358 | L1016: VIETDT.HCM.NG | M1016: 080100 | N1016: 082900 | O1016: 5 | P1016: 2026 | Q1016: DATA_PHATSINH1015 | R1016: 1014 | S1016: =A1016&M1016 -> 1363111080100 | T1016: =IF(M1016="080100",J1016-K1016,K1016-J1016) -> -2530358
A1017: 1363111 | B1017: 13631110000 | C1017: Receivables-Sales Invoices | D1017: 136 | E1017: 1 | F1017: 2026-05-01T00:00:00+07:00 | G1017: 42635 | H1017: 5185 | I1017: Payoo 01/05/2026 | J1017: 0 | K1017: 2348836 | L1017: VIETDT.HCM.NG | M1017: 080100 | N1017: 082900 | O1017: 5 | P1017: 2026 | Q1017: DATA_PHATSINH1016 | R1017: 1015 | S1017: =A1017&M1017 -> 1363111080100 | T1017: =IF(M1017="080100",J1017-K1017,K1017-J1017) -> -2348836
... A1258: 1363111 | B1258: 13631110000 | C1258: Receivables-Sales Invoices | D1258: 136 | E1258: 1 | F1258: 2026-05-07T00:00:00+07:00 | G1258: 42594 | H1258: 5176 | I1258: MService 07/05/2026 | J1258: 0 | K1258: 2839929721 | L1258: VIETDT.HCM.NG | M1258: 080100 | N1258: 082900 | O1258: 5 | P1258: 2026 | Q1258: DATA_PHATSINH1257 | R1258: 1256 | S1258: =A1258&M1258 -> 1363111080100 | T1258: =IF(M1258="080100",J1258-K1258,K1258-J1258) -> -2839929721
A1259: 13681 | B1259: 13681000000 | C1259: Cost Management-Inventory | D1259: 136 | E1259: 1 | F1259: 46168 | G1259: 30768803 | H1259: 1572 | I1259: 25039-SX:Xuất vtư từ SXKD đ/c cho Ctr Trang bị Tbị REC, LBS có Scada trên LĐ PCVT | J1259: 2370368 | K1259: 0 | L1259: THANH5DT.HCM.VTA | M1259: 082900 | N1259: 082900 | O1259: 5 | P1259: 2026 | S1259: =A1259&M1259 -> 13681082900 | T1259: =IF(M1259="080100",J1259-K1259,K1259-J1259) -> -2370368
A1260: 13681 | B1260: 13681000000 | C1260: Cost Management-Inventory | D1260: 136 | E1260: 1 | F1260: 46168 | G1260: 30768802 | H1260: 1572 | I1260: 25039-SX:Xuất vtư từ SXKD đ/c cho Ctr Trang bị Tbị REC, LBS có Scada trên LĐ PCVT | J1260: 2382761 | K1260: 0 | L1260: THANH5DT.HCM.VTA | M1260: 082900 | N1260: 082900 | O1260: 5 | P1260: 2026 | S1260: =A1260&M1260 -> 13681082900 | T1260: =IF(M1260="080100",J1260-K1260,K1260-J1260) -> -2382761
A1261: 13681 | B1261: 13681000000 | C1261: Cost Management-Inventory | D1261: 136 | E1261: 1 | F1261: 46168 | G1261: 30768882 | H1261: 1572 | I1261: 25039-SX:Xuất vtư từ SXKD đ/c cho Ctr Trang bị Tbị REC, LBS có Scada trên LĐ PCVT | J1261: 2490000 | K1261: 0 | L1261: THANH5DT.HCM.VTA | M1261: 082900 | N1261: 082900 | O1261: 5 | P1261: 2026 | S1261: =A1261&M1261 -> 13681082900 | T1261: =IF(M1261="080100",J1261-K1261,K1261-J1261) -> -2490000
A1262: 13681 | B1262: 13681000000 | C1262: Cost Management-Inventory | D1262: 136 | E1262: 1 | F1262: 46168 | G1262: 30768797 | H1262: 1572 | I1262: 25039-SX:Xuất vtư từ SXKD đ/c cho Ctr Trang bị Tbị REC, LBS có Scada trên LĐ PCVT | J1262: 2780000 | K1262: 0 | L1262: THANH5DT.HCM.VTA | M1262: 082900 | N1262: 082900 | O1262: 5 | P1262: 2026 | S1262: =A1262&M1262 -> 13681082900 | T1262: =IF(M1262="080100",J1262-K1262,K1262-J1262) -> -2780000
A1263: 13681 | B1263: 13681000000 | C1263: Cost Management-Inventory | D1263: 136 | E1263: 1 | F1263: 46168 | G1263: 30768799 | H1263: 1572 | I1263: 25039-SX:Xuất vtư từ SXKD đ/c cho Ctr Trang bị Tbị REC, LBS có Scada trên LĐ PCVT | J1263: 3749854 | K1263: 0 | L1263: THANH5DT.HCM.VTA | M1263: 082900 | N1263: 082900 | O1263: 5 | P1263: 2026 | S1263: =A1263&M1263 -> 13681082900 | T1263: =IF(M1263="080100",J1263-K1263,K1263-J1263) -> -3749854
A1264: 33681 | B1264: 33681000000 | C1264: Cost Management-Inventory | D1264: 336 | E1264: 2 | F1264: 46172 | G1264: 30799868 | H1264: 1570 | I1264: 25039-SX:Nhập vtư từ SXKD đ/c cho Ctr Trang bị Tbị REC, LBS có Scada trên LĐ PCVT | J1264: 0 | K1264: 1295000 | L1264: THANH5DT.HCM.VTA | M1264: 082900 | N1264: 082900 | O1264: 5 | P1264: 2026 | S1264: =A1264&M1264 -> 33681082900 | T1264: =IF(M1264="080100",J1264-K1264,K1264-J1264) -> 1295000
A1265: 33681 | B1265: 33681000000 | C1265: Cost Management-Inventory | D1265: 336 | E1265: 2 | F1265: 46168 | G1265: 30771097 | H1265: 1572 | I1265: 25039-SX:Nhập vtư từ SXKD đ/c cho Ctr Trang bị Tbị REC, LBS có Scada trên LĐ PCVT | J1265: 0 | K1265: 1780352 | L1265: THANH5DT.HCM.VTA | M1265: 082900 | N1265: 082900 | O1265: 5 | P1265: 2026 | S1265: =A1265&M1265 -> 33681082900 | T1265: =IF(M1265="080100",J1265-K1265,K1265-J1265) -> 1780352
A1266: 33681 | B1266: 33681000000 | C1266: Cost Management-Inventory | D1266: 336 | E1266: 2 | F1266: 46168 | G1266: 30771123 | H1266: 1572 | I1266: 25039-SX:Nhập vtư từ SXKD đ/c cho Ctr Trang bị Tbị REC, LBS có Scada trên LĐ PCVT | J1266: 0 | K1266: 1945935 | L1266: THANH5DT.HCM.VTA | M1266: 082900 | N1266: 082900 | O1266: 5 | P1266: 2026 | S1266: =A1266&M1266 -> 33681082900 | T1266: =IF(M1266="080100",J1266-K1266,K1266-J1266) -> 1945935
A1267: 33681 | B1267: 33681000000 | C1267: Cost Management-Inventory | D1267: 336 | E1267: 2 | F1267: 46168 | G1267: 30771096 | H1267: 1572 | I1267: 25039-SX:Nhập vtư từ SXKD đ/c cho Ctr Trang bị Tbị REC, LBS có Scada trên LĐ PCVT | J1267: 0 | K1267: 2370368 | L1267: THANH5DT.HCM.VTA | M1267: 082900 | N1267: 082900 | O1267: 5 | P1267: 2026 | S1267: =A1267&M1267 -> 33681082900 | T1267: =IF(M1267="080100",J1267-K1267,K1267-J1267) -> 2370368
A1268: 33681 | B1268: 33681000000 | C1268: Cost Management-Inventory | D1268: 336 | E1268: 2 | F1268: 46168 | G1268: 30771095 | H1268: 1572 | I1268: 25039-SX:Nhập vtư từ SXKD đ/c cho Ctr Trang bị Tbị REC, LBS có Scada trên LĐ PCVT | J1268: 0 | K1268: 2382761 | L1268: THANH5DT.HCM.VTA | M1268: 082900 | N1268: 082900 | O1268: 5 | P1268: 2026 | S1268: =A1268&M1268 -> 33681082900 | T1268: =IF(M1268="080100",J1268-K1268,K1268-J1268) -> 2382761
A1269: 33681 | B1269: 33681000000 | C1269: Cost Management-Inventory | D1269: 336 | E1269: 2 | F1269: 46168 | G1269: 30771122 | H1269: 1572 | I1269: 25039-SX:Nhập vtư từ SXKD đ/c cho Ctr Trang bị Tbị REC, LBS có Scada trên LĐ PCVT | J1269: 0 | K1269: 2490000 | L1269: THANH5DT.HCM.VTA | M1269: 082900 | N1269: 082900 | O1269: 5 | P1269: 2026 | S1269: =A1269&M1269 -> 33681082900 | T1269: =IF(M1269="080100",J1269-K1269,K1269-J1269) -> 2490000
A1270: 33681 | B1270: 33681000000 | C1270: Cost Management-Inventory | D1270: 336 | E1270: 2 | F1270: 46168 | G1270: 30771090 | H1270: 1572 | I1270: 25039-SX:Nhập vtư từ SXKD đ/c cho Ctr Trang bị Tbị REC, LBS có Scada trên LĐ PCVT | J1270: 0 | K1270: 2780000 | L1270: THANH5DT.HCM.VTA | M1270: 082900 | N1270: 082900 | O1270: 5 | P1270: 2026 | S1270: =A1270&M1270 -> 33681082900 | T1270: =IF(M1270="080100",J1270-K1270,K1270-J1270) -> 2780000
... A1272: 33681 | B1272: 33681000000 | C1272: Cost Management-Inventory | D1272: 336 | E1272: 2 | F1272: 46168 | G1272: 30771094 | H1272: 1572 | I1272: 25039-SX:Nhập vtư từ SXKD đ/c cho Ctr Trang bị Tbị REC, LBS có Scada trên LĐ PCVT | J1272: 0 | K1272: 4787165 | L1272: THANH5DT.HCM.VTA | M1272: 082900 | N1272: 082900 | O1272: 5 | P1272: 2026 | S1272: =A1272&M1272 -> 33681082900 | T1272: =IF(M1272="080100",J1272-K1272,K1272-J1272) -> 4787165
A1273: 33681 | B1273: 33681000000 | C1273: GL-PAYABLE-MANUAL | D1273: 336 | E1273: 2 | F1273: 46143 | H1273: 1353 | I1273: Điều chỉnh 13681-33681-từ CT23009 sang CT25009 do nhầm đối tượng | J1273: 0 | K1273: -10022533 | L1273: HIENNTK.HCM.VTA | M1273: 082900 | N1273: 082900 | O1273: 5 | P1273: 2026 | S1273: =A1273&M1273 -> 33681082900 | T1273: =IF(M1273="080100",J1273-K1273,K1273-J1273) -> -10022533
A1274: 33681 | B1274: 33681000000 | C1274: GL-PAYABLE-MANUAL | D1274: 336 | E1274: 2 | F1274: 46143 | H1274: 1353 | I1274: Điều chỉnh 13681-33681-từ CT23009 sang CT25009 do nhầm đối tượng -CP BHXH,BHYT...tháng 4-Ban QLDA | J1274: 0 | K1274: 10022533 | L1274: HIENNTK.HCM.VTA | M1274: 082900 | N1274: 082900 | O1274: 5 | P1274: 2026 | S1274: =A1274&M1274 -> 33681082900 | T1274: =IF(M1274="080100",J1274-K1274,K1274-J1274) -> 10022533
A1275: 33681 | B1275: 33681000000 | C1275: GL-PAYABLE-MANUAL | D1275: 336 | E1275: 2 | F1275: 46143 | H1275: 1353 | I1275: Điều chỉnh 13681-lương thêm giờ tháng 3/2025 của Ban QLDA do hạch toán trùng 2 lần | J1275: 0 | K1275: -109089718 | L1275: HIENNTK.HCM.VTA | M1275: 082900 | N1275: 082900 | O1275: 5 | P1275: 2026 | S1275: =A1275&M1275 -> 33681082900 | T1275: =IF(M1275="080100",J1275-K1275,K1275-J1275) -> -109089718
A1276: 13681 | B1276: 13681000000 | C1276: GL-PAYABLE-MANUAL | D1276: 136 | E1276: 1 | F1276: 46143 | H1276: 1353 | I1276: Điều chỉnh 13681-33681-từ CT23009 sang CT25009 do nhầm đối tượng | J1276: -10022533 | K1276: 0 | L1276: HIENNTK.HCM.VTA | M1276: 082900 | N1276: 082900 | O1276: 5 | P1276: 2026 | S1276: =A1276&M1276 -> 13681082900 | T1276: =IF(M1276="080100",J1276-K1276,K1276-J1276) -> 10022533
A1277: 13681 | B1277: 13681000000 | C1277: GL-PAYABLE-MANUAL | D1277: 136 | E1277: 1 | F1277: 46143 | H1277: 1353 | I1277: Điều chỉnh 13681-33681-từ CT23009 sang CT25009 do nhầm đối tượng -CP BHXH,BHYT...tháng 4-Ban QLDA | J1277: 10022533 | K1277: 0 | L1277: HIENNTK.HCM.VTA | M1277: 082900 | N1277: 082900 | O1277: 5 | P1277: 2026 | S1277: =A1277&M1277 -> 13681082900 | T1277: =IF(M1277="080100",J1277-K1277,K1277-J1277) -> -10022533
A1278: 13681 | B1278: 13681000000 | C1278: GL-PAYABLE-MANUAL | D1278: 136 | E1278: 1 | F1278: 46143 | H1278: 1353 | I1278: Điều chỉnh 13681-lương thêm giờ tháng 3/2025 của Ban QLDA do hạch toán trùng 2 lần | J1278: -109089718 | K1278: 0 | L1278: HIENNTK.HCM.VTA | M1278: 082900 | N1278: 082900 | O1278: 5 | P1278: 2026 | S1278: =A1278&M1278 -> 13681082900 | T1278: =IF(M1278="080100",J1278-K1278,K1278-J1278) -> 109089718
A1279: 13681 | B1279: 13681000000 | C1279: Cost Management-Inventory | D1279: 136 | E1279: 1 | F1279: 46172 | G1279: 30799839 | H1279: 1570 | I1279: 25039-SX:Xuất vtư từ SXKD đ/c cho Ctr Trang bị Tbị REC, LBS có Scada trên LĐ PCVT | J1279: 12000 | K1279: 0 | L1279: THANH5DT.HCM.VTA | M1279: 082900 | N1279: 082900 | O1279: 5 | P1279: 2026 | S1279: =A1279&M1279 -> 13681082900 | T1279: =IF(M1279="080100",J1279-K1279,K1279-J1279) -> -12000
A1280: 13681 | B1280: 13681000000 | C1280: Cost Management-Inventory | D1280: 136 | E1280: 1 | F1280: 46172 | G1280: 30799844 | H1280: 1570 | I1280: 25039-SX:Xuất vtư từ SXKD đ/c cho Ctr Trang bị Tbị REC, LBS có Scada trên LĐ PCVT | J1280: 30207 | K1280: 0 | L1280: THANH5DT.HCM.VTA | M1280: 082900 | N1280: 082900 | O1280: 5 | P1280: 2026 | S1280: =A1280&M1280 -> 13681082900 | T1280: =IF(M1280="080100",J1280-K1280,K1280-J1280) -> -30207
A1281: 13681 | B1281: 13681000000 | C1281: Cost Management-Inventory | D1281: 136 | E1281: 1 | F1281: 46172 | G1281: 30799842 | H1281: 1570 | I1281: 25039-SX:Xuất vtư từ SXKD đ/c cho Ctr Trang bị Tbị REC, LBS có Scada trên LĐ PCVT | J1281: 33600 | K1281: 0 | L1281: THANH5DT.HCM.VTA | M1281: 082900 | N1281: 082900 | O1281: 5 | P1281: 2026 | S1281: =A1281&M1281 -> 13681082900 | T1281: =IF(M1281="080100",J1281-K1281,K1281-J1281) -> -33600
A1282: 13681 | B1282: 13681000000 | C1282: Cost Management-Inventory | D1282: 136 | E1282: 1 | F1282: 46172 | G1282: 30799845 | H1282: 1570 | I1282: 25039-SX:Xuất vtư từ SXKD đ/c cho Ctr Trang bị Tbị REC, LBS có Scada trên LĐ PCVT | J1282: 36646 | K1282: 0 | L1282: THANH5DT.HCM.VTA | M1282: 082900 | N1282: 082900 | O1282: 5 | P1282: 2026 | S1282: =A1282&M1282 -> 13681082900 | T1282: =IF(M1282="080100",J1282-K1282,K1282-J1282) -> -36646
A1283: 13681 | B1283: 13681000000 | C1283: Cost Management-Inventory | D1283: 136 | E1283: 1 | F1283: 46170 | G1283: 30786944 | H1283: 1571 | I1283: 25039-SX:Xuất vtư từ SXKD đ/c cho Ctr Trang bị Tbị REC, LBS có Scada trên LĐ PCVT | J1283: 48000 | K1283: 0 | L1283: THANH5DT.HCM.VTA | M1283: 082900 | N1283: 082900 | O1283: 5 | P1283: 2026 | S1283: =A1283&M1283 -> 13681082900 | T1283: =IF(M1283="080100",J1283-K1283,K1283-J1283) -> -48000
A1284: 33681 | B1284: 33681000000 | C1284: Cost Management-Inventory | D1284: 336 | E1284: 2 | F1284: 46153 | G1284: 30680999 | H1284: 1573 | I1284: 24017-SX:Xuất VTTB từ Ctr KNCT 2024 điều chuyển SXKD phục vụ SCTX | J1284: 45558700 | K1284: 0 | L1284: THANH5DT.HCM.VTA | M1284: 082900 | N1284: 082900 | O1284: 5 | P1284: 2026 | S1284: =A1284&M1284 -> 33681082900 | T1284: =IF(M1284="080100",J1284-K1284,K1284-J1284) -> -45558700
A1285: 33681 | B1285: 33681000000 | C1285: Cost Management-Inventory | D1285: 336 | E1285: 2 | F1285: 46153 | G1285: 30680917 | H1285: 1573 | I1285: 25001-SX:Xuất VTTB từ Ctr NC THT TPVT,BR điều chuyển SXKD phục vụ SCTX | J1285: 85399035 | K1285: 0 | L1285: THANH5DT.HCM.VTA | M1285: 082900 | N1285: 082900 | O1285: 5 | P1285: 2026 | S1285: =A1285&M1285 -> 33681082900 | T1285: =IF(M1285="080100",J1285-K1285,K1285-J1285) -> -85399035
A1286: 33681 | B1286: 33681000000 | C1286: Cost Management-Inventory | D1286: 336 | E1286: 2 | F1286: 46153 | G1286: 30680867 | H1286: 1573 | I1286: 24027-SX:Xuất VTTB từ Ctr CQT Tx Phú Mỹ điều chuyển SXKD phục vụ SCTX | J1286: 153964800 | K1286: 0 | L1286: THANH5DT.HCM.VTA | M1286: 082900 | N1286: 082900 | O1286: 5 | P1286: 2026 | S1286: =A1286&M1286 -> 33681082900 | T1286: =IF(M1286="080100",J1286-K1286,K1286-J1286) -> -153964800
A1287: 33681 | B1287: 33681000000 | C1287: Cost Management-Inventory | D1287: 336 | E1287: 2 | F1287: 46153 | G1287: 30680918 | H1287: 1573 | I1287: 25001-SX:Xuất VTTB từ Ctr NC THT TPVT,BR điều chuyển SXKD phục vụ SCTX | J1287: 205962600 | K1287: 0 | L1287: THANH5DT.HCM.VTA | M1287: 082900 | N1287: 082900 | O1287: 5 | P1287: 2026 | S1287: =A1287&M1287 -> 33681082900 | T1287: =IF(M1287="080100",J1287-K1287,K1287-J1287) -> -205962600
A1288: 33681 | B1288: 33681000000 | C1288: Cost Management-Inventory | D1288: 336 | E1288: 2 | F1288: 46172 | G1288: 30799885 | H1288: 1570 | I1288: 25039-SX:Nhập vtư từ SXKD đ/c cho Ctr Trang bị Tbị REC, LBS có Scada trên LĐ PCVT | J1288: 0 | K1288: 12000 | L1288: THANH5DT.HCM.VTA | M1288: 082900 | N1288: 082900 | O1288: 5 | P1288: 2026 | S1288: =A1288&M1288 -> 33681082900 | T1288: =IF(M1288="080100",J1288-K1288,K1288-J1288) -> 12000
A1289: 33681 | B1289: 33681000000 | C1289: Cost Management-Inventory | D1289: 336 | E1289: 2 | F1289: 46172 | G1289: 30799890 | H1289: 1570 | I1289: 25039-SX:Nhập vtư từ SXKD đ/c cho Ctr Trang bị Tbị REC, LBS có Scada trên LĐ PCVT | J1289: 0 | K1289: 30207 | L1289: THANH5DT.HCM.VTA | M1289: 082900 | N1289: 082900 | O1289: 5 | P1289: 2026 | S1289: =A1289&M1289 -> 33681082900 | T1289: =IF(M1289="080100",J1289-K1289,K1289-J1289) -> 30207
A1290: 33681 | B1290: 33681000000 | C1290: Cost Management-Inventory | D1290: 336 | E1290: 2 | F1290: 46172 | G1290: 30799888 | H1290: 1570 | I1290: 25039-SX:Nhập vtư từ SXKD đ/c cho Ctr Trang bị Tbị REC, LBS có Scada trên LĐ PCVT | J1290: 0 | K1290: 33600 | L1290: THANH5DT.HCM.VTA | M1290: 082900 | N1290: 082900 | O1290: 5 | P1290: 2026 | S1290: =A1290&M1290 -> 33681082900 | T1290: =IF(M1290="080100",J1290-K1290,K1290-J1290) -> 33600
... A1334: 13681 | B1334: 13681000000 | C1334: Cost Management-Inventory | D1334: 136 | E1334: 1 | F1334: 46153 | G1334: 30683307 | H1334: 1573 | I1334: 25001 SX Nhập vật tư từ kho ĐTXD sang SXKD | J1334: 0 | K1334: 205962600 | L1334: THANH5DT.HCM.VTA | M1334: 082900 | N1334: 082900 | O1334: 5 | P1334: 2026 | S1334: =A1334&M1334 -> 13681082900 | T1334: =IF(M1334="080100",J1334-K1334,K1334-J1334) -> 205962600
A1335: 13681 | B1335: 13681000000 | C1335: GL-PAYABLE-MANUAL | D1335: 136 | E1335: 1 | F1335: 46143 | H1335: 1353 | I1335: Điều chỉnh 13681-33681- do PX01.VH9.53.0102 ngày 10.12.25 xuất vật tư (điều từ sxkd) từ CT24028 sang CT25033 - | J1335: -422173 | K1335: 0 | L1335: HIENNTK.HCM.VTA | M1335: 082900 | N1335: 082900 | O1335: 5 | P1335: 2026 | S1335: =A1335&M1335 -> 13681082900 | T1335: =IF(M1335="080100",J1335-K1335,K1335-J1335) -> 422173
A1336: 13681 | B1336: 13681000000 | C1336: GL-PAYABLE-MANUAL | D1336: 136 | E1336: 1 | F1336: 46143 | H1336: 1353 | I1336: Điều chỉnh 13681-33681- do PX01.VH9.53.0102 ngày 10.12.25 xuất vật tư (điều từ sxkd) từ CT24028 sang CT25033 - | J1336: 422173 | K1336: 0 | L1336: HIENNTK.HCM.VTA | M1336: 082900 | N1336: 082900 | O1336: 5 | P1336: 2026 | S1336: =A1336&M1336 -> 13681082900 | T1336: =IF(M1336="080100",J1336-K1336,K1336-J1336) -> -422173
...

Sheet 1363111_3363111
A1: Madonvi | B1: NhomTK | C1: SoHieuTaiKhoan | D1: NGUON | E1: DienGiai | F1: SoCTPhanHePhu | G1: SoCTPhanHeGL | H1: SoPSNo | I1: SoPSCo | J1: NguoiLapCT | K1: Thang | L1: NET | M1: Trung | N1: VLOOKUP_NET | O1: id | P1: =HYPERLINK("#TONG_HOP!G1","TRO VE") -> TRO VE
A2: 80100 | B2: 1 | C2: 1363111 | D2: GL-MANUAL | E2: KC PTNB TIEN DIEN THANG 5-2026 - PCVT | G2: 5092 | H2: 0 | I2: 1006728865803 | J2: ANHTTL.HCM.NG | K2: 5 | L2: -1006728865803 | M2: FALSE | N2: -1006728865803_5 | O2: CHITIET1 | P2: 0
A3: 82900 | B3: 2 | C3: 3363111 | D3: GL-MANUAL | E3: KC Thuế GTGT VTĐĐ- hđơn 666-11.05.26-TỔNG CÔNG TY ĐIỆN LỰC THÀNH PHỐ HỒ CHÍ MINH | G3: 1361 | H3: 0 | I3: 25728000 | J3: THANH5DT.HCM.VTA | K3: 5 | L3: 25728000 | M3: FALSE | N3: 25728000_5 | O3: CHITIET2 | P3: 1
A4: 82900 | B4: 2 | C4: 3363111 | D4: GL-MANUAL | E4: KC Thuế GTGT VTĐĐ- hđơn 681-13.05.26-TỔNG CÔNG TY ĐIỆN LỰC THÀNH PHỐ HỒ CHÍ MINH | G4: 1361 | H4: 0 | I4: 102912000 | J4: THANH5DT.HCM.VTA | K4: 5 | L4: 102912000 | M4: FALSE | N4: 102912000_5 | O4: CHITIET3 | P4: 2
A5: 82900 | B5: 2 | C5: 3363111 | D5: GL-MANUAL | E5: KC Thuế GTGT VTĐĐ- hđơn 760-26.05.26-TỔNG CÔNG TY ĐIỆN LỰC THÀNH PHỐ HỒ CHÍ MINH | G5: 1361 | H5: 0 | I5: 376000000 | J5: THANH5DT.HCM.VTA | K5: 5 | L5: 376000000 | M5: FALSE | N5: 376000000_5 | O5: CHITIET4 | P5: 3
A6: 82900 | B6: 2 | C6: 3363111 | D6: GL-MANUAL | E6: KC Thuế GTGT VTĐĐ- hđơn 761-26.05.26-TỔNG CÔNG TY ĐIỆN LỰC THÀNH PHỐ HỒ CHÍ MINH | G6: 1361 | H6: 0 | I6: 376000000 | J6: THANH5DT.HCM.VTA | K6: 5 | L6: 376000000 | M6: FALSE | N6: 376000000_5 | O6: CHITIET5 | P6: 4
A7: 82900 | B7: 2 | C7: 3363111 | D7: GL-MANUAL | E7: KC Thuế GTGT VTĐĐ- hđơn 752-25.05.26-TỔNG CÔNG TY ĐIỆN LỰC THÀNH PHỐ HỒ CHÍ MINH | G7: 1361 | H7: 0 | I7: 144771840 | J7: THANH5DT.HCM.VTA | K7: 5 | L7: 144771840 | M7: FALSE | N7: 144771840_5 | O7: CHITIET6 | P7: 5
A8: 82900 | B8: 2 | C8: 3363111 | D8: GL-MANUAL | E8: KC Thuế GTGT VTĐĐ- hđơn 762-26.05.26-TỔNG CÔNG TY ĐIỆN LỰC THÀNH PHỐ HỒ CHÍ MINH | G8: 1361 | H8: 0 | I8: 289543680 | J8: THANH5DT.HCM.VTA | K8: 5 | L8: 289543680 | M8: FALSE | N8: 289543680_5 | O8: CHITIET7 | P8: 6
A9: 82900 | B9: 2 | C9: 3363111 | D9: GL-MANUAL | E9: KC Thuế GTGT VTĐĐ- hđơn 780-27.05.26-TỔNG CÔNG TY ĐIỆN LỰC THÀNH PHỐ HỒ CHÍ MINH | G9: 1361 | H9: 0 | I9: 102546720 | J9: THANH5DT.HCM.VTA | K9: 5 | L9: 102546720 | M9: FALSE | N9: 102546720_5 | O9: CHITIET8 | P9: 7
A10: 82900 | B10: 2 | C10: 3363111 | D10: GL-MANUAL | E10: KC Thuế GTGT VTĐĐ- hđơn 709-19.05.26-TỔNG CÔNG TY ĐIỆN LỰC THÀNH PHỐ HỒ CHÍ MINH | G10: 1361 | H10: 0 | I10: 13464000 | J10: THANH5DT.HCM.VTA | K10: 5 | L10: 13464000 | M10: FALSE | N10: 13464000_5 | O10: CHITIET9 | P10: 8
A11: 82900 | B11: 2 | C11: 3363111 | D11: GL-MANUAL | E11: KC Thuế GTGT VTĐĐ- hđơn 710-19.05.26-TỔNG CÔNG TY ĐIỆN LỰC THÀNH PHỐ HỒ CHÍ MINH | G11: 1361 | H11: 0 | I11: 18072915 | J11: THANH5DT.HCM.VTA | K11: 5 | L11: 18072915 | M11: FALSE | N11: 18072915_5 | O11: CHITIET10 | P11: 9
A12: 82900 | B12: 2 | C12: 3363111 | D12: GL-MANUAL | E12: KC Thuế GTGT VTĐĐ- hđơn 708-19.05.26-TỔNG CÔNG TY ĐIỆN LỰC THÀNH PHỐ HỒ CHÍ MINH | G12: 1361 | H12: 0 | I12: 26588976 | J12: THANH5DT.HCM.VTA | K12: 5 | L12: 26588976 | M12: FALSE | N12: 26588976_5 | O12: CHITIET11 | P12: 10
A13: 82900 | B13: 2 | C13: 3363111 | D13: GL-MANUAL | E13: KC Thuế GTGT VTĐĐ- hđơn 679-13.05.26-TỔNG CÔNG TY ĐIỆN LỰC THÀNH PHỐ HỒ CHÍ MINH | G13: 1361 | H13: 0 | I13: 53664000 | J13: THANH5DT.HCM.VTA | K13: 5 | L13: 53664000 | M13: FALSE | N13: 53664000_5 | O13: CHITIET12 | P13: 11
... A16: 82900 | B16: 2 | C16: 3363111 | D16: MassAllocation-Allocation | E16: K/c 51111 > 3363111 (k/c doanh thu điện) | G16: 1622 | H16: 0 | I16: 1420763729435 | J16: DUYENTT.HCM.VTA | K16: 5 | L16: 1420763729435 | M16: FALSE | N16: 1420763729435_5 | O16: CHITIET15 | P16: 14
A17: 82900 | B17: 2 | C17: 3363111 | D17: Receivables-Credit Memos | E17: Giải trừ tiền điện thu hộ CTĐLVT ngày 01/05/2026 | F17: 1555 | G17: 1423 | H17: 18128980 | I17: 0 | J17: CHAULTN.HCM.VTA | K17: 5 | L17: -18128980 | M17: FALSE | N17: -18128980_5 | O17: CHITIET16 | P17: 15
A18: 82900 | B18: 2 | C18: 3363111 | D18: Receivables-Credit Memos | E18: Giải trừ tiền điện thu hộ CTĐLVT ngày 02/05/2026 | F18: 1556 | G18: 1426 | H18: 26816550 | I18: 0 | J18: CHAULTN.HCM.VTA | K18: 5 | L18: -26816550 | M18: FALSE | N18: -26816550_5 | O18: CHITIET17 | P18: 16
A19: 82900 | B19: 2 | C19: 3363111 | D19: Receivables-Credit Memos | E19: Giải trừ tiền điện thu hộ CTĐLVT ngày 31/05/2026 | F19: 1637 | G19: 1410 | H19: 124625041 | I19: 0 | J19: CHAULTN.HCM.VTA | K19: 5 | L19: -124625041 | M19: FALSE | N19: -124625041_5 | O19: CHITIET18 | P19: 17
A20: 82900 | B20: 2 | C20: 3363111 | D20: Receivables-Credit Memos | E20: Giải trừ tiền điện thu hộ CTĐLVT ngày 29/05/2026 | F20: 1634 | G20: 1431 | H20: 213369327 | I20: 0 | J20: CHAULTN.HCM.VTA | K20: 5 | L20: -213369327 | M20: FALSE | N20: -213369327_5 | O20: CHITIET19 | P20: 18
A21: 82900 | B21: 2 | C21: 3363111 | D21: Receivables-Credit Memos | E21: Giải trừ tiền điện thu hộ CTĐLVT ngày 30/05/2026 | F21: 1636 | G21: 1432 | H21: 240583866 | I21: 0 | J21: CHAULTN.HCM.VTA | K21: 5 | L21: -240583866 | M21: FALSE | N21: -240583866_5 | O21: CHITIET20 | P21: 19
A22: 82900 | B22: 2 | C22: 3363111 | D22: Receivables-Credit Memos | E22: Giải trừ tiền điện thu hộ CTĐLVT ngày 28/05/2026 | F22: 1645 | G22: 1434 | H22: 261690745 | I22: 0 | J22: CHAULTN.HCM.VTA | K22: 5 | L22: -261690745 | M22: FALSE | N22: -261690745_5 | O22: CHITIET21 | P22: 20
A23: 82900 | B23: 2 | C23: 3363111 | D23: Receivables-Credit Memos | E23: Giải trừ tiền điện thu hộ CTĐLVT ngày 27/05/2026 | F23: 1644 | G23: 1433 | H23: 589602156 | I23: 0 | J23: CHAULTN.HCM.VTA | K23: 5 | L23: -589602156 | M23: FALSE | N23: -589602156_5 | O23: CHITIET22 | P23: 21
A24: 82900 | B24: 2 | C24: 3363111 | D24: Receivables-Credit Memos | E24: Giải trừ tiền điện thu hộ CTĐLVT ngày 21/05/2026 | F24: 1610 | G24: 1436 | H24: 2031335542 | I24: 0 | J24: CHAULTN.HCM.VTA | K24: 5 | L24: -2031335542 | M24: FALSE | N24: -2031335542_5 | O24: CHITIET23 | P24: 22
A25: 82900 | B25: 2 | C25: 3363111 | D25: Receivables-Credit Memos | E25: Giải trừ tiền điện thu hộ CTĐLVT ngày 23/05/2026 | F25: 1619 | G25: 1440 | H25: 2196560832 | I25: 0 | J25: CHAULTN.HCM.VTA | K25: 5 | L25: -2196560832 | M25: FALSE | N25: -2196560832_5 | O25: CHITIET24 | P25: 23
A26: 82900 | B26: 2 | C26: 3363111 | D26: Receivables-Credit Memos | E26: Giải trừ tiền điện thu hộ CTĐLVT ngày 19/05/2026 | F26: 1577 | G26: 1418 | H26: 2571762995 | I26: 0 | J26: CHAULTN.HCM.VTA | K26: 5 | L26: -2571762995 | M26: FALSE | N26: -2571762995_5 | O26: CHITIET25 | P26: 24
A27: 82900 | B27: 2 | C27: 3363111 | D27: Receivables-Credit Memos | E27: Giải trừ tiền điện thu hộ CTĐLVT ngày 26/05/2026 | F27: 1629 | G27: 1425 | H27: 2884615550 | I27: 0 | J27: CHAULTN.HCM.VTA | K27: 5 | L27: -2884615550 | M27: FALSE | N27: -2884615550_5 | O27: CHITIET26 | P27: 25
A28: 82900 | B28: 2 | C28: 3363111 | D28: Receivables-Credit Memos | E28: Giải trừ tiền điện thu hộ CTĐLVT ngày 20/05/2026 | F28: 1580 | G28: 1424 | H28: 3039901153 | I28: 0 | J28: CHAULTN.HCM.VTA | K28: 5 | L28: -3039901153 | M28: FALSE | N28: -3039901153_5 | O28: CHITIET27 | P28: 26
... A43: 82900 | B43: 2 | C43: 3363111 | D43: Receivables-Credit Memos | E43: Giải trừ tiền điện thu hộ CTĐLVT ngày 04/05/2026 | F43: 1567 | G43: 1419 | H43: 172475203824 | I43: 0 | J43: CHAULTN.HCM.VTA | K43: 5 | L43: -172475203824 | M43: FALSE | N43: -172475203824_5 | O43: CHITIET42 | P43: 41
A44: 80100 | B44: 1 | C44: 1363111 | D44: Receivables-Misc Receipts | E44: TD - ACB - VTA | F44: ACBO202605310 | G44: 5114 | H44: 0 | I44: 4466593 | J44: VIETDT.HCM.NG | K44: 5 | L44: -4466593 | M44: FALSE | N44: -4466593_5 | O44: CHITIET43 | P44: 42
A45: 80100 | B45: 1 | C45: 1363111 | D45: Receivables-Misc Receipts | E45: TD - NAB - VTA | F45: NABO202605110 | G45: 5121 | H45: 0 | I45: 4708410 | J45: VIETDT.HCM.NG | K45: 5 | L45: -4708410 | M45: FALSE | N45: -4708410_5 | O45: CHITIET44 | P45: 43
A46: 80100 | B46: 1 | C46: 1363111 | D46: Receivables-Misc Receipts | E46: TD - BIDV - VTA | F46: BIDVO202605010 | G46: 5122 | H46: 0 | I46: 4937332 | J46: VIETDT.HCM.NG | K46: 5 | L46: -4937332 | M46: FALSE | N46: -4937332_5 | O46: CHITIET45 | P46: 44
A47: 80100 | B47: 1 | C47: 1363111 | D47: Receivables-Misc Receipts | E47: TD - ICB - VTA | F47: ICBO202605290 | G47: 5100 | H47: 0 | I47: 3986735 | J47: VIETDT.HCM.NG | K47: 5 | L47: -3986735 | M47: FALSE | N47: -3986735_5 | O47: CHITIET46 | P47: 45
A48: 80100 | B48: 1 | C48: 1363111 | D48: Receivables-Misc Receipts | E48: TD - NAB - VTA | F48: NABO202605130 | G48: 5123 | H48: 0 | I48: 3993560 | J48: VIETDT.HCM.NG | K48: 5 | L48: -3993560 | M48: FALSE | N48: -3993560_5 | O48: CHITIET47 | P48: 46
A49: 80100 | B49: 1 | C49: 1363111 | D49: Receivables-Misc Receipts | E49: TD - VPB - VTA | F49: VPBO202605230 | G49: 5101 | H49: 0 | I49: 4157374 | J49: VIETDT.HCM.NG | K49: 5 | L49: -4157374 | M49: FALSE | N49: -4157374_5 | O49: CHITIET48 | P49: 47
A50: 80100 | B50: 1 | C50: 1363111 | D50: Receivables-Misc Receipts | E50: TD - VPB - VTA | F50: VPBO202605210 | G50: 5099 | H50: 0 | I50: 4242149 | J50: VIETDT.HCM.NG | K50: 5 | L50: -4242149 | M50: FALSE | N50: -4242149_5 | O50: CHITIET49 | P50: 48
A51: 80100 | B51: 1 | C51: 1363111 | D51: Receivables-Misc Receipts | E51: TD - SCB - VTA | F51: SCBO202605310 | G51: 5114 | H51: 0 | I51: 4249109 | J51: VIETDT.HCM.NG | K51: 5 | L51: -4249109 | M51: FALSE | N51: -4249109_5 | O51: CHITIET50 | P51: 49
A52: 80100 | B52: 1 | C52: 1363111 | D52: Receivables-Misc Receipts | E52: TD - ACB - VTA | F52: ACBO202605300 | G52: 5115 | H52: 0 | I52: 4354374 | J52: VIETDT.HCM.NG | K52: 5 | L52: -4354374 | M52: FALSE | N52: -4354374_5 | O52: CHITIET51 | P52: 50
A53: 80100 | B53: 1 | C53: 1363111 | D53: Receivables-Misc Receipts | E53: TD - TCB - VTA | F53: TCBO202605270 | G53: 5097 | H53: 0 | I53: 3683392 | J53: VIETDT.HCM.NG | K53: 5 | L53: -3683392 | M53: FALSE | N53: -3683392_5 | O53: CHITIET52 | P53: 51
A54: 80100 | B54: 1 | C54: 1363111 | D54: Receivables-Misc Receipts | E54: TD - LVB - VTA | F54: LVBO202605250 | G54: 5108 | H54: 0 | I54: 3774535 | J54: VIETDT.HCM.NG | K54: 5 | L54: -3774535 | M54: FALSE | N54: -3774535_5 | O54: CHITIET53 | P54: 52
A55: 80100 | B55: 1 | C55: 1363111 | D55: Receivables-Misc Receipts | E55: TD - SCB - VTA | F55: SCBO202605260 | G55: 5109 | H55: 0 | I55: 3786340 | J55: VIETDT.HCM.NG | K55: 5 | L55: -3786340 | M55: FALSE | N55: -3786340_5 | O55: CHITIET54 | P55: 53
... A536: 82900 | B536: 2 | C536: 3363111 | D536: Receivables-Misc Receipts | E536: CTĐLVT chuyển tiền điện về TCT ĐL HCM qua NH BIDV | F536: R0526ĐTT0330 | G536: 1477 | H536: 4020393459 | I536: 0 | J536: CHAULTN.HCM.VTA | K536: 5 | L536: -4020393459 | M536: FALSE | N536: -4020393459_5 | O536: CHITIET535 | P536: 534
A537: 80100 | B537: 1 | C537: 1363111 | D537: Receivables-Sales Invoices | E537: Airpay 30/05/2026 | F537: 42629 | G537: 5168 | H537: 0 | I537: 3252260 | J537: VIETDT.HCM.NG | K537: 5 | L537: -3252260 | M537: FALSE | N537: -3252260_5 | O537: CHITIET536 | P537: 535
A538: 80100 | B538: 1 | C538: 1363111 | D538: Receivables-Sales Invoices | E538: Viettel 28/05/2026 | F538: 42442 | G538: 5167 | H538: 0 | I538: 3941307 | J538: VIETDT.HCM.NG | K538: 5 | L538: -3941307 | M538: FALSE | N538: -3941307_5 | O538: CHITIET537 | P538: 536
A539: 80100 | B539: 1 | C539: 1363111 | D539: Receivables-Sales Invoices | E539: VNPay 31/05/2026 | F539: 42587 | G539: 5162 | H539: 0 | I539: 4377736 | J539: VIETDT.HCM.NG | K539: 5 | L539: -4377736 | M539: FALSE | N539: -4377736_5 | O539: CHITIET538 | P539: 537
A540: 80100 | B540: 1 | C540: 1363111 | D540: Receivables-Sales Invoices | E540: VNPTPay 14/05/2026 | F540: 42506 | G540: 5171 | H540: 0 | I540: 4422589 | J540: VIETDT.HCM.NG | K540: 5 | L540: -4422589 | M540: FALSE | N540: -4422589_5 | O540: CHITIET539 | P540: 538
A541: 80100 | B541: 1 | C541: 1363111 | D541: Receivables-Sales Invoices | E541: Paytech 10/05/2026 | F541: 42478 | G541: 5164 | H541: 0 | I541: 4459418 | J541: VIETDT.HCM.NG | K541: 5 | L541: -4459418 | M541: FALSE | N541: -4459418_5 | O541: CHITIET540 | P541: 539
A542: 80100 | B542: 1 | C542: 1363111 | D542: Receivables-Sales Invoices | E542: Viettel 02/05/2026 | F542: 42336 | G542: 5173 | H542: 0 | I542: 4283026 | J542: VIETDT.HCM.NG | K542: 5 | L542: -4283026 | M542: FALSE | N542: -4283026_5 | O542: CHITIET541 | P542: 540
A543: 80100 | B543: 1 | C543: 1363111 | D543: Receivables-Sales Invoices | E543: Payoo 03/05/2026 | F543: 42637 | G543: 5177 | H543: 0 | I543: 2079215417 | J543: VIETDT.HCM.NG | K543: 5 | L543: -2079215417 | M543: FALSE | N543: -2079215417_5 | O543: CHITIET542 | P543: 541
A544: 80100 | B544: 1 | C544: 1363111 | D544: Receivables-Sales Invoices | E544: ZaloPay 29/05/2026 | F544: 42554 | G544: 5163 | H544: 0 | I544: 4850648 | J544: VIETDT.HCM.NG | K544: 5 | L544: -4850648 | M544: FALSE | N544: -4850648_5 | O544: CHITIET543 | P544: 542
A545: 80100 | B545: 1 | C545: 1363111 | D545: Receivables-Sales Invoices | E545: Paytech 18/05/2026 | F545: 42486 | G545: 5174 | H545: 0 | I545: 4656420 | J545: VIETDT.HCM.NG | K545: 5 | L545: -4656420 | M545: FALSE | N545: -4656420_5 | O545: CHITIET544 | P545: 543
A546: 80100 | B546: 1 | C546: 1363111 | D546: Receivables-Sales Invoices | E546: VNPay 04/05/2026 | F546: 42560 | G546: 5172 | H546: 0 | I546: 2118568081 | J546: VIETDT.HCM.NG | K546: 5 | L546: -2118568081 | M546: FALSE | N546: -2118568081_5 | O546: CHITIET545 | P546: 544
A547: 80100 | B547: 1 | C547: 1363111 | D547: Receivables-Sales Invoices | E547: ZaloPay 27/05/2026 | F547: 42552 | G547: 5155 | H547: 0 | I547: 9535666 | J547: VIETDT.HCM.NG | K547: 5 | L547: -9535666 | M547: FALSE | N547: -9535666_5 | O547: CHITIET546 | P547: 545
A548: 80100 | B548: 1 | C548: 1363111 | D548: Receivables-Sales Invoices | E548: Paytech 22/05/2026 | F548: 42490 | G548: 5159 | H548: 0 | I548: 3542616 | J548: VIETDT.HCM.NG | K548: 5 | L548: -3542616 | M548: FALSE | N548: -3542616_5 | O548: CHITIET547 | P548: 546
... A770: 80100 | B770: 1 | C770: 1363111 | D770: Receivables-Sales Invoices | E770: Viettel 11/05/2026 | F770: 42425 | G770: 5184 | H770: 0 | I770: 248573588 | J770: VIETDT.HCM.NG | K770: 5 | L770: -248573588 | M770: FALSE | N770: -248573588_5 | O770: CHITIET769 | P770: 768
A771: Created with a trial version of Syncfusion Excel library or registered the wrong key in your application. Click here to obtain the valid key.

Sheet 1363112_3363112
A1: Madonvi | B1: NhomTK | C1: SoHieuTaiKhoan | D1: NGUON | E1: DienGiai | F1: SoCTPhanHePhu | G1: SoCTPhanHeGL | H1: SoPSNo | I1: SoPSCo | J1: NguoiLapCT | K1: Thang | L1: NET | M1: Trung | N1: VLOOKUP_NET | O1: id | P1: =HYPERLINK("#TONG_HOP!G1","TRO VE") -> TRO VE
A2: 80100 | B2: 1 | C2: 1363112 | D2: GL-MANUAL | E2: KC PTNB TIEN DIEN THANG 5-2026 - PCVT (VC) | G2: 5092 | H2: 0 | I2: 301236589 | J2: ANHTTL.HCM.NG | K2: 5 | L2: -301236589 | M2: FALSE | N2: -301236589_5 | O2: CHITIET1 | P2: 0
A3: 82900 | B3: 2 | C3: 3363112 | D3: GL-MANUAL | E3: Điều chỉnh tiền vô công chuyển về TCT ĐL HCM T05/2026 | G3: 1496 | H3: 0 | I3: 301236589 | J3: QUYENNN.HCM.VTA | K3: 5 | L3: 301236589 | M3: FALSE | N3: 301236589_5 | O3: CHITIET2 | P3: 1
A4: 82900 | B4: 2 | C4: 3363112 | D4: MassAllocation-Allocation | E4: K/c 51113 > 3363112 (k/c dthu công suất phản kháng) | G4: 1623 | H4: 0 | I4: 762611631 | J4: DUYENTT.HCM.VTA | K4: 5 | L4: 762611631 | M4: FALSE | N4: 762611631_5 | O4: CHITIET3 | P4: 2
A5: 82900 | B5: 2 | C5: 3363112 | D5: Receivables-Credit Memos | E5: Giải trừ tiền vô công thu hộ CTĐLVT ngày 22/05/2026 | F5: 1614 | G5: 1417 | H5: 18204661 | I5: 0 | J5: CHAULTN.HCM.VTA | K5: 5 | L5: -18204661 | M5: FALSE | N5: -18204661_5 | O5: CHITIET4 | P5: 3
A6: 82900 | B6: 2 | C6: 3363112 | D6: Receivables-Credit Memos | E6: Giải trừ tiền vô công thu hộ CTĐLVT ngày 09/05/2026 | F6: 1588 | G6: 1430 | H6: 22621067 | I6: 0 | J6: CHAULTN.HCM.VTA | K6: 5 | L6: -22621067 | M6: FALSE | N6: -22621067_5 | O6: CHITIET5 | P6: 4
A7: 82900 | B7: 2 | C7: 3363112 | D7: Receivables-Credit Memos | E7: Giải trừ tiền vô công thu hộ CTĐLVT ngày 18/05/2026 | F7: 1609 | G7: 1428 | H7: 24675649 | I7: 0 | J7: CHAULTN.HCM.VTA | K7: 5 | L7: -24675649 | M7: FALSE | N7: -24675649_5 | O7: CHITIET6 | P7: 5
A8: 82900 | B8: 2 | C8: 3363112 | D8: Receivables-Credit Memos | E8: Giải trừ tiền vô công thu hộ CTĐLVT ngày 05/05/2026 | F8: 1571 | G8: 1422 | H8: 29308455 | I8: 0 | J8: CHAULTN.HCM.VTA | K8: 5 | L8: -29308455 | M8: FALSE | N8: -29308455_5 | O8: CHITIET7 | P8: 6
A9: 82900 | B9: 2 | C9: 3363112 | D9: Receivables-Credit Memos | E9: Giải trừ tiền vô công thu hộ CTĐLVT ngày 06/05/2026 | F9: 1559 | G9: 1438 | H9: 75633744 | I9: 0 | J9: CHAULTN.HCM.VTA | K9: 5 | L9: -75633744 | M9: FALSE | N9: -75633744_5 | O9: CHITIET8 | P9: 7
A10: 82900 | B10: 2 | C10: 3363112 | D10: Receivables-Credit Memos | E10: Giải trừ tiền vô công thu hộ CTĐLVT ngày 04/05/2026 | F10: 1568 | G10: 1419 | H10: 121340050 | I10: 0 | J10: CHAULTN.HCM.VTA | K10: 5 | L10: -121340050 | M10: FALSE | N10: -121340050_5 | O10: CHITIET9 | P10: 8
A11: 82900 | B11: 2 | C11: 3363112 | D11: Receivables-Credit Memos | E11: Giải trừ tiền vô công thu hộ CTĐLVT ngày 11/05/2026 | F11: 1591 | G11: 1435 | H11: 1195232 | I11: 0 | J11: CHAULTN.HCM.VTA | K11: 5 | L11: -1195232 | M11: FALSE | N11: -1195232_5 | O11: CHITIET10 | P11: 9
A12: 82900 | B12: 2 | C12: 3363112 | D12: Receivables-Credit Memos | E12: Giải trừ tiền vô công thu hộ CTĐLVT ngày 13/05/2026 | F12: 1594 | G12: 1421 | H12: 3954874 | I12: 0 | J12: CHAULTN.HCM.VTA | K12: 5 | L12: -3954874 | M12: FALSE | N12: -3954874_5 | O12: CHITIET11 | P12: 10
A13: 82900 | B13: 2 | C13: 3363112 | D13: Receivables-Credit Memos | E13: Giải trừ tiền vô công thu hộ CTĐLVT ngày 08/05/2026 | F13: 1585 | G13: 1439 | H13: 10361251 | I13: 0 | J13: CHAULTN.HCM.VTA | K13: 5 | L13: -10361251 | M13: FALSE | N13: -10361251_5 | O13: CHITIET12 | P13: 11
A14: 82900 | B14: 2 | C14: 3363112 | D14: Receivables-Credit Memos | E14: Giải trừ tiền vô công thu hộ CTĐLVT ngày 26/05/2026 | F14: 1630 | G14: 1425 | H14: 11589615 | I14: 0 | J14: CHAULTN.HCM.VTA | K14: 5 | L14: -11589615 | M14: FALSE | N14: -11589615_5 | O14: CHITIET13 | P14: 12
A15: 82900 | B15: 2 | C15: 3363112 | D15: Receivables-Credit Memos | E15: Giải trừ tiền vô công thu hộ CTĐLVT ngày 16/05/2026 | F15: 1602 | G15: 1441 | H15: 12047809 | I15: 0 | J15: CHAULTN.HCM.VTA | K15: 5 | L15: -12047809 | M15: FALSE | N15: -12047809_5 | O15: CHITIET14 | P15: 13
A16: 82900 | B16: 2 | C16: 3363112 | D16: Receivables-Credit Memos | E16: Giải trừ tiền vô công thu hộ CTĐLVT ngày 14/05/2026 | F16: 1596 | G16: 1416 | H16: 13566695 | I16: 0 | J16: CHAULTN.HCM.VTA | K16: 5 | L16: -13566695 | M16: FALSE | N16: -13566695_5 | O16: CHITIET15 | P16: 14
... A18: 82900 | B18: 2 | C18: 3363112 | D18: Receivables-Credit Memos | E18: Giải trừ tiền vô công thu hộ CTĐLVT ngày 07/05/2026 | F18: 1582 | G18: 1420 | H18: 17562735 | I18: 0 | J18: CHAULTN.HCM.VTA | K18: 5 | L18: -17562735 | M18: FALSE | N18: -17562735_5 | O18: CHITIET17 | P18: 16
A19: 80100 | B19: 1 | C19: 1363112 | D19: Receivables-Misc Receipts | E19: VC - ABB - VTA | F19: ABBO202605061 | G19: 5106 | H19: 0 | I19: 11278650 | J19: VIETDT.HCM.NG | K19: 5 | L19: -11278650 | M19: FALSE | N19: -11278650_5 | O19: CHITIET18 | P19: 17
A20: 80100 | B20: 1 | C20: 1363112 | D20: Receivables-Misc Receipts | E20: VC - ABB - VTA | F20: ABBO202605161 | G20: 5118 | H20: 0 | I20: 11381580 | J20: VIETDT.HCM.NG | K20: 5 | L20: -11381580 | M20: FALSE | N20: -11381580_5 | O20: CHITIET19 | P20: 18
A21: 80100 | B21: 1 | C21: 1363112 | D21: Receivables-Misc Receipts | E21: VC - BIDV - VTA | F21: BIDVO202605031 | G21: 5113 | H21: 0 | I21: 11769401 | J21: VIETDT.HCM.NG | K21: 5 | L21: -11769401 | M21: FALSE | N21: -11769401_5 | O21: CHITIET20 | P21: 19
A22: 80100 | B22: 1 | C22: 1363112 | D22: Receivables-Misc Receipts | E22: VC - ICB - VTA | F22: ICBO202605071 | G22: 5112 | H22: 0 | I22: 11901571 | J22: VIETDT.HCM.NG | K22: 5 | L22: -11901571 | M22: FALSE | N22: -11901571_5 | O22: CHITIET21 | P22: 20
A23: 80100 | B23: 1 | C23: 1363112 | D23: Receivables-Misc Receipts | E23: VC - EXB - VTA | F23: EXBO202605031 | G23: 5113 | H23: 0 | I23: 12182159 | J23: VIETDT.HCM.NG | K23: 5 | L23: -12182159 | M23: FALSE | N23: -12182159_5 | O23: CHITIET22 | P23: 21
A24: 80100 | B24: 1 | C24: 1363112 | D24: Receivables-Misc Receipts | E24: VC - VCB - VTA | F24: VCBO202605051 | G24: 5117 | H24: 0 | I24: 12217266 | J24: VIETDT.HCM.NG | K24: 5 | L24: -12217266 | M24: FALSE | N24: -12217266_5 | O24: CHITIET23 | P24: 22
A25: 80100 | B25: 1 | C25: 1363112 | D25: Receivables-Misc Receipts | E25: VC - ICB - VTA | F25: ICBO202605141 | G25: 5096 | H25: 0 | I25: 13452674 | J25: VIETDT.HCM.NG | K25: 5 | L25: -13452674 | M25: FALSE | N25: -13452674_5 | O25: CHITIET24 | P25: 23
A26: 80100 | B26: 1 | C26: 1363112 | D26: Receivables-Misc Receipts | E26: VC - AGRI - VTA | F26: AGRIO202605051 | G26: 5117 | H26: 0 | I26: 14198403 | J26: VIETDT.HCM.NG | K26: 5 | L26: -14198403 | M26: FALSE | N26: -14198403_5 | O26: CHITIET25 | P26: 24
A27: 80100 | B27: 1 | C27: 1363112 | D27: Receivables-Misc Receipts | E27: VC - MBB - VTA | F27: MBBO202605091 | G27: 5102 | H27: 0 | I27: 19277739 | J27: VIETDT.HCM.NG | K27: 5 | L27: -19277739 | M27: FALSE | N27: -19277739_5 | O27: CHITIET26 | P27: 25
A28: 80100 | B28: 1 | C28: 1363112 | D28: Receivables-Misc Receipts | E28: VC - VCB - VTA | F28: VCBO202605061 | G28: 5106 | H28: 0 | I28: 33280661 | J28: VIETDT.HCM.NG | K28: 5 | L28: -33280661 | M28: FALSE | N28: -33280661_5 | O28: CHITIET27 | P28: 26
A29: 80100 | B29: 1 | C29: 1363112 | D29: Receivables-Misc Receipts | E29: VC - VCB - VTA | F29: VCBO202605041 | G29: 5107 | H29: 0 | I29: 53233830 | J29: VIETDT.HCM.NG | K29: 5 | L29: -53233830 | M29: FALSE | N29: -53233830_5 | O29: CHITIET28 | P29: 27
A30: 80100 | B30: 1 | C30: 1363112 | D30: Receivables-Misc Receipts | E30: VC - ACB - VTA | F30: ACBO202605041 | G30: 5107 | H30: 0 | I30: 23080 | J30: VIETDT.HCM.NG | K30: 5 | L30: -23080 | M30: FALSE | N30: -23080_5 | O30: CHITIET29 | P30: 28
... A86: 82900 | B86: 2 | C86: 3363112 | D86: Receivables-Misc Receipts | E86: CTĐLVT chuyển tiền vô công về TCT ĐL HCM qua NH BIDV | F86: R0526ĐTT0352A | G86: 1449 | H86: 692814920 | I86: 0 | J86: CHAULTN.HCM.VTA | K86: 5 | L86: -692814920 | M86: FALSE | N86: -692814920_5 | O86: CHITIET85 | P86: 84
A87: 80100 | B87: 1 | C87: 1363112 | D87: Receivables-Sales Invoices | E87: VNPay 18/05/2026 | F87: 42574 | G87: 5174 | H87: 0 | I87: 18498840 | J87: VIETDT.HCM.NG | K87: 5 | L87: -18498840 | M87: FALSE | N87: -18498840_5 | O87: CHITIET86 | P87: 85
A88: 80100 | B88: 1 | C88: 1363112 | D88: Receivables-Sales Invoices | E88: MService 09/05/2026 | F88: 42596 | G88: 5178 | H88: 0 | I88: 833117 | J88: VIETDT.HCM.NG | K88: 5 | L88: -833117 | M88: FALSE | N88: -833117_5 | O88: CHITIET87 | P88: 86
A89: 80100 | B89: 1 | C89: 1363112 | D89: Receivables-Sales Invoices | E89: MService 12/05/2026 | F89: 42599 | G89: 5170 | H89: 0 | I89: 2278237 | J89: VIETDT.HCM.NG | K89: 5 | L89: -2278237 | M89: FALSE | N89: -2278237_5 | O89: CHITIET88 | P89: 87
A90: 80100 | B90: 1 | C90: 1363112 | D90: Receivables-Sales Invoices | E90: VNPay 07/05/2026 | F90: 42563 | G90: 5176 | H90: 0 | I90: 703082 | J90: VIETDT.HCM.NG | K90: 5 | L90: -703082 | M90: FALSE | N90: -703082_5 | O90: CHITIET89 | P90: 88
A91: 80100 | B91: 1 | C91: 1363112 | D91: Receivables-Sales Invoices | E91: VNPay 05/05/2026 | F91: 42561 | G91: 5179 | H91: 0 | I91: 650252 | J91: VIETDT.HCM.NG | K91: 5 | L91: -650252 | M91: FALSE | N91: -650252_5 | O91: CHITIET90 | P91: 89
A92: 80100 | B92: 1 | C92: 1363112 | D92: Receivables-Sales Invoices | E92: VNPay 06/05/2026 | F92: 42562 | G92: 5182 | H92: 0 | I92: 7759801 | J92: VIETDT.HCM.NG | K92: 5 | L92: -7759801 | M92: FALSE | N92: -7759801_5 | O92: CHITIET91 | P92: 90
A93: 80100 | B93: 1 | C93: 1363112 | D93: Receivables-Sales Invoices | E93: ZaloPay 04/05/2026 | F93: 42449 | G93: 5172 | H93: 0 | I93: 1072524 | J93: VIETDT.HCM.NG | K93: 5 | L93: -1072524 | M93: FALSE | N93: -1072524_5 | O93: CHITIET92 | P93: 91
A94: 80100 | B94: 1 | C94: 1363112 | D94: Receivables-Sales Invoices | E94: MService 06/05/2026 | F94: 42593 | G94: 5182 | H94: 0 | I94: 564165 | J94: VIETDT.HCM.NG | K94: 5 | L94: -564165 | M94: FALSE | N94: -564165_5 | O94: CHITIET93 | P94: 92
A95: 80100 | B95: 1 | C95: 1363112 | D95: Receivables-Sales Invoices | E95: Payoo 10/05/2026 | F95: 42644 | G95: 5164 | H95: 0 | I95: 256319 | J95: VIETDT.HCM.NG | K95: 5 | L95: -256319 | M95: FALSE | N95: -256319_5 | O95: CHITIET94 | P95: 93
A96: 80100 | B96: 1 | C96: 1363112 | D96: Receivables-Sales Invoices | E96: MService 03/05/2026 | F96: 42590 | G96: 5177 | H96: 0 | I96: 145427 | J96: VIETDT.HCM.NG | K96: 5 | L96: -145427 | M96: FALSE | N96: -145427_5 | O96: CHITIET95 | P96: 94
A97: 80100 | B97: 1 | C97: 1363112 | D97: Receivables-Sales Invoices | E97: MService 04/05/2026 | F97: 42591 | G97: 5172 | H97: 0 | I97: 175678 | J97: VIETDT.HCM.NG | K97: 5 | L97: -175678 | M97: FALSE | N97: -175678_5 | O97: CHITIET96 | P97: 95
A98: 80100 | B98: 1 | C98: 1363112 | D98: Receivables-Sales Invoices | E98: Viettel 06/05/2026 | F98: 42340 | G98: 5182 | H98: 0 | I98: 110109 | J98: VIETDT.HCM.NG | K98: 5 | L98: -110109 | M98: FALSE | N98: -110109_5 | O98: CHITIET97 | P98: 96
... A103: 80100 | B103: 1 | C103: 1363112 | D103: Receivables-Sales Invoices | E103: VNPay 03/05/2026 | F103: 42559 | G103: 5177 | H103: 0 | I103: 4164 | J103: VIETDT.HCM.NG | K103: 5 | L103: -4164 | M103: FALSE | N103: -4164_5 | O103: CHITIET102 | P103: 101
A104: Created with a trial version of Syncfusion Excel library or registered the wrong key in your application. Click here to obtain the valid key.

Sheet 136312_336312
P1: =HYPERLINK("#TONG_HOP!G1","TRO VE") -> TRO VE
A6: Created with a trial version of Syncfusion Excel library or registered the wrong key in your application. Click here to obtain the valid key.

Sheet 136313_336313
P1: =HYPERLINK("#TONG_HOP!G1","TRO VE") -> TRO VE
A6: Created with a trial version of Syncfusion Excel library or registered the wrong key in your application. Click here to obtain the valid key.

Sheet 136314_336314
A1: Madonvi | B1: NhomTK | C1: SoHieuTaiKhoan | D1: NGUON | E1: DienGiai | F1: SoCTPhanHeGL | G1: SoPSNo | H1: SoPSCo | I1: NguoiLapCT | J1: Thang | K1: NET | L1: Trung | M1: VLOOKUP_NET | N1: id | O1: rowOrder | P1: =HYPERLINK("#TONG_HOP!G1","TRO VE") -> TRO VE
A2: 82900 | B2: 2 | C2: 336314 | D2: MassAllocation-Allocation | E2: K/c 5114 (QL dây, cáp) > 3363114 | F2: 1624 | G2: 0 | H2: 253573360 | I2: DUYENTT.HCM.VTA | J2: 5 | K2: 253573360 | L2: FALSE | M2: 253573360_5 | N2: CHITIET1 | O2: 0
A6: Created with a trial version of Syncfusion Excel library or registered the wrong key in your application. Click here to obtain the valid key.

Sheet 136315_336315
P1: =HYPERLINK("#TONG_HOP!G1","TRO VE") -> TRO VE
A6: Created with a trial version of Syncfusion Excel library or registered the wrong key in your application. Click here to obtain the valid key.

Sheet 136318_336318
P1: =HYPERLINK("#TONG_HOP!G1","TRO VE") -> TRO VE
A6: Created with a trial version of Syncfusion Excel library or registered the wrong key in your application. Click here to obtain the valid key.

Sheet 136321_336321
P1: =HYPERLINK("#TONG_HOP!G1","TRO VE") -> TRO VE
A6: Created with a trial version of Syncfusion Excel library or registered the wrong key in your application. Click here to obtain the valid key.

Sheet 136331_336331
A1: Madonvi | B1: NhomTK | C1: SoHieuTaiKhoan | D1: NGUON | E1: DienGiai | F1: SoCTPhanHePhu | G1: SoCTPhanHeGL | H1: SoPSNo | I1: SoPSCo | J1: NguoiLapCT | K1: Thang | L1: NET | M1: Trung | N1: VLOOKUP_NET | O1: id | P1: =HYPERLINK("#TONG_HOP!G1","TRO VE") -> TRO VE
A2: 82900 | B2: 2 | C2: 336331 | D2: GL-MANUAL | E2: Hạch toán giá trị TSCĐ nhận điều động nội bộ TCT tháng 05/2026 | G2: 1641 | H2: 0 | I2: 2534843522 | J2: HUONGDTT.HCM.VTA | K2: 5 | L2: 2534843522 | M2: FALSE | N2: 2534843522_5 | O2: CHITIET1 | P2: 0
A3: 82900 | B3: 2 | C3: 336331 | D3: GL-MANUAL | E3: Kết chuyển chi phí khấu hao T05/2026 | G3: 1643 | H3: 9176034319 | I3: 0 | J3: HUONGDTT.HCM.VTA | K3: 5 | L3: -9176034319 | M3: FALSE | N3: -9176034319_5 | O3: CHITIET2 | P3: 1
A4: 82900 | B4: 2 | C4: 336331 | D4: GL-MANUAL | E4: Kết chuyển giá trị PDQT theo QĐ 369/30.05.26 CT XDM, cải tạo lưới điện THT và TBA thị xã Phú Mỹ năm 2024_23009 | G4: 1355 | H4: 0 | I4: 4281150500 | J4: HUONGDTT.HCM.VTA | K4: 5 | L4: 4281150500 | M4: FALSE | N4: 4281150500_5 | O4: CHITIET3 | P4: 2
A5: 82900 | B5: 2 | C5: 336331 | D5: GL-MANUAL | E5: Kết chuyển giá trị PDQT theo QĐ 330/20.05.26 CT Đầu tư, cải tạo hệ thống AC/DC tại các trạm 110kv năm 2023_23018 | G5: 1355 | H5: 0 | I5: 3630279342 | J5: HUONGDTT.HCM.VTA | K5: 5 | L5: 3630279342 | M5: FALSE | N5: 3630279342_5 | O5: CHITIET4 | P5: 3
A6: 82900 | B6: 2 | C6: 336331 | D6: GL-PAYABLE-MANUAL | E6: Hạch toán cấp vốn trả lãi vay MB hợp đồng 268718 TB3038(CV xin vốn 2336) trả lãi vay CT22003 | G6: 1493 | H6: 0 | I6: 197460524 | J6: LINH3NTT.HCM.VTA | K6: 5 | L6: 197460524 | M6: FALSE | N6: 197460524_5 | O6: CHITIET5 | P6: 4
A7: 82900 | B7: 2 | C7: 336331 | D7: GL-PAYABLE-MANUAL | E7: Kết chuyển CT hoàn thành phê duyệt quyết toán CT23018 | G7: 1389 | H7: 3630279342 | I7: 0 | J7: HIENNTK.HCM.VTA | K7: 5 | L7: -3630279342 | M7: FALSE | N7: -3630279342_5 | O7: CHITIET6 | P7: 5
A8: 82900 | B8: 2 | C8: 336331 | D8: GL-PAYABLE-MANUAL | E8: Kết chuyển CT hoàn thành phê duyệt quyết toán CT23009 | G8: 1390 | H8: 4281150500 | I8: 0 | J8: HIENNTK.HCM.VTA | K8: 5 | L8: -4281150500 | M8: FALSE | N8: -4281150500_5 | O8: CHITIET7 | P8: 6
A9: 82900 | B9: 2 | C9: 336331 | D9: GL-PAYABLE-MANUAL | E9: Hạch toán cấp vốn KHCB theo TB 2914/TB-EVNHCMC ngày 03.06.26 (CV xin vốn 1884) thanh toán hóa đơn 681 vật tư Cty cấp Recloser cho CT25039 | G9: 1378 | H9: 0 | I9: 1608000000 | J9: LINH3NTT.HCM.VTA | K9: 5 | L9: 1608000000 | M9: FALSE | N9: 1608000000_5 | O9: CHITIET8 | P9: 7
A10: 82900 | B10: 2 | C10: 336331 | D10: GL-PAYABLE-MANUAL | E10: Hạch toán cấp vốn theo TB2886/03.06.26 cấp vốn trả nợ gốc vay MB CT20013 | G10: 1379 | H10: 0 | I10: 309009803 | J10: LINH3NTT.HCM.VTA | K10: 5 | L10: 309009803 | M10: FALSE | N10: 309009803_5 | O10: CHITIET9 | P10: 8
A11: 82900 | B11: 2 | C11: 336331 | D11: GL-PAYABLE-MANUAL | E11: Hạch toán cấp vốn theo TB2886/03.06.26 cấp vốn trả nợ gốc vay MB CT20014 | G11: 1379 | H11: 0 | I11: 282323000 | J11: LINH3NTT.HCM.VTA | K11: 5 | L11: 282323000 | M11: FALSE | N11: 282323000_5 | O11: CHITIET10 | P11: 9
A12: 82900 | B12: 2 | C12: 336331 | D12: GL-PAYABLE-MANUAL | E12: Hạch toán cấp vốn theo TB2886/03.06.26 cấp vốn trả nợ gốc vay MB CT20015 | G12: 1379 | H12: 0 | I12: 211058250 | J12: LINH3NTT.HCM.VTA | K12: 5 | L12: 211058250 | M12: FALSE | N12: 211058250_5 | O12: CHITIET11 | P12: 10
A13: 82900 | B13: 2 | C13: 336331 | D13: GL-PAYABLE-MANUAL | E13: Hạch toán cấp vốn trả gốc lãi theo TB2888 ngày 03.06.26 (CV xin vốn 1997) trả nợ gốc vay Agribank CT20009 | G13: 1380 | H13: 0 | I13: 270947722 | J13: LINH3NTT.HCM.VTA | K13: 5 | L13: 270947722 | M13: FALSE | N13: 270947722_5 | O13: CHITIET12 | P13: 11
... A43: 82900 | B43: 2 | C43: 336331 | D43: GL-PAYABLE-MANUAL | E43: Hạch toán cấp vốn KHCB-TB2852/TB-EVNHCMC ngày 02.06.26-hóa đơn 25-xây lắp-cty 168 | G43: 1387 | H43: 0 | I43: 188684258 | J43: HIENNTK.HCM.VTA | K43: 5 | L43: 188684258 | M43: FALSE | N43: 188684258_5 | O43: CHITIET42 | P43: 41
A44: 80100 | B44: 1 | C44: 136331 | D44: Receivables-Misc Receipts | E44: Cấp KHCB theo TTr 1851/TCKT ngày 25/5/26 | F44: LV_T05/26_19 | G44: 5097 | H44: 609513700 | I44: 0 | J44: VIETDT.HCM.NG | K44: 5 | L44: 609513700 | M44: FALSE | N44: 609513700_5 | O44: CHITIET43 | P44: 42
A45: 80100 | B45: 1 | C45: 136331 | D45: Receivables-Misc Receipts | E45: Cấp KHCB theo TTr 1885/TCKT ngày 25/5/26 | F45: LV_T05/26_17 | G45: 5109 | H45: 877629907 | I45: 0 | J45: VIETDT.HCM.NG | K45: 5 | L45: 877629907 | M45: FALSE | N45: 877629907_5 | O45: CHITIET44 | P45: 43
A46: 80100 | B46: 1 | C46: 136331 | D46: Receivables-Misc Receipts | E46: Cấp KHCB thanh toán nợ gốc theo TTr 1637/TCKT ngày 11/5/26 | F46: LV_T05/26_04 | G46: 5103 | H46: 1584291719 | I46: 0 | J46: VIETDT.HCM.NG | K46: 5 | L46: 1584291719 | M46: FALSE | N46: 1584291719_5 | O46: CHITIET45 | P46: 44
A47: 80100 | B47: 1 | C47: 136331 | D47: Receivables-Misc Receipts | E47: Cấp KHCB theo TTr 1892/TCKT ngày 26/5/2026 | F47: LV_T05/26_18 | G47: 5097 | H47: 1601842444 | I47: 0 | J47: VIETDT.HCM.NG | K47: 5 | L47: 1601842444 | M47: FALSE | N47: 1601842444_5 | O47: CHITIET46 | P47: 45
A48: 80100 | B48: 1 | C48: 136331 | D48: Receivables-Misc Receipts | E48: Cấp KHCB (lãi vay)_TTr số 1734/TCKT ngày 18/5/26 | F48: LV_T05/26_07 | G48: 5110 | H48: 57001755 | I48: 0 | J48: VIETDT.HCM.NG | K48: 5 | L48: 57001755 | M48: FALSE | N48: 57001755_5 | O48: CHITIET47 | P48: 46
A49: 80100 | B49: 1 | C49: 136331 | D49: Receivables-Misc Receipts | E49: Cấp KHCB (nợ gốc)_TTr số 1734/TCKT ngày 18/5/26 | F49: LV_T05/26_07 | G49: 5110 | H49: 5821147015 | I49: 0 | J49: VIETDT.HCM.NG | K49: 5 | L49: 5821147015 | M49: FALSE | N49: 5821147015_5 | O49: CHITIET48 | P49: 47
A50: Created with a trial version of Syncfusion Excel library or registered the wrong key in your application. Click here to obtain the valid key.

Sheet 136341_336341
A1: Madonvi | B1: NhomTK | C1: SoHieuTaiKhoan | D1: NGUON | E1: DienGiai | F1: SoCTPhanHeGL | G1: SoPSNo | H1: SoPSCo | I1: NguoiLapCT | J1: Thang | K1: NET | L1: Trung | M1: VLOOKUP_NET | N1: id | O1: rowOrder | P1: =HYPERLINK("#TONG_HOP!G1","TRO VE") -> TRO VE
A2: 82900 | B2: 2 | C2: 336341 | D2: GL-MANUAL | E2: Kết chuyển chi phí khấu hao T05/2026 | F2: 1643 | G2: 5111360457 | H2: 0 | I2: HUONGDTT.HCM.VTA | J2: 5 | K2: -5111360457 | L2: FALSE | M2: -5111360457_5 | N2: CHITIET1 | O2: 0
A6: Created with a trial version of Syncfusion Excel library or registered the wrong key in your application. Click here to obtain the valid key.

Sheet 136351_336351
A1: Madonvi | B1: NhomTK | C1: SoHieuTaiKhoan | D1: NGUON | E1: DienGiai | F1: SoCTPhanHeGL | G1: SoPSNo | H1: SoPSCo | I1: NguoiLapCT | J1: Thang | K1: NET | L1: Trung | M1: VLOOKUP_NET | N1: id | O1: rowOrder | P1: =HYPERLINK("#TONG_HOP!G1","TRO VE") -> TRO VE
A6: Created with a trial version of Syncfusion Excel library or registered the wrong key in your application. Click here to obtain the valid key.

Sheet 136352_336352
P1: =HYPERLINK("#TONG_HOP!G1","TRO VE") -> TRO VE
A6: Created with a trial version of Syncfusion Excel library or registered the wrong key in your application. Click here to obtain the valid key.

Sheet 136358_336358
A1: Madonvi | B1: NhomTK | C1: SoHieuTaiKhoan | D1: NGUON | E1: DienGiai | F1: SoCTPhanHePhu | G1: SoCTPhanHeGL | H1: SoPSNo | I1: SoPSCo | J1: NguoiLapCT | K1: Thang | L1: NET | M1: Trung | N1: VLOOKUP_NET | O1: id | P1: =HYPERLINK("#TONG_HOP!G1","TRO VE") -> TRO VE
A2: 82900 | B2: 2 | C2: 336358 | D2: GL-MANUAL | E2: KC Thuế GTGT VTĐĐ- hđơn 710-19.05.26-TỔNG CÔNG TY ĐIỆN LỰC THÀNH PHỐ HỒ CHÍ MINH | G2: 1361 | H2: 18072915 | I2: 0 | J2: THANH5DT.HCM.VTA | K2: 5 | L2: -18072915 | M2: FALSE | N2: -18072915_5 | O2: CHITIET1 | P2: 0
A3: 82900 | B3: 2 | C3: 336358 | D3: GL-MANUAL | E3: KC Thuế GTGT VTĐĐ- hđơn 708-19.05.26-TỔNG CÔNG TY ĐIỆN LỰC THÀNH PHỐ HỒ CHÍ MINH | G3: 1361 | H3: 26588976 | I3: 0 | J3: THANH5DT.HCM.VTA | K3: 5 | L3: -26588976 | M3: FALSE | N3: -26588976_5 | O3: CHITIET2 | P3: 1
A4: 82900 | B4: 2 | C4: 336358 | D4: GL-MANUAL | E4: KC Thuế GTGT VTĐĐ- hđơn 679-13.05.26-TỔNG CÔNG TY ĐIỆN LỰC THÀNH PHỐ HỒ CHÍ MINH | G4: 1361 | H4: 53664000 | I4: 0 | J4: THANH5DT.HCM.VTA | K4: 5 | L4: -53664000 | M4: FALSE | N4: -53664000_5 | O4: CHITIET3 | P4: 2
A5: 82900 | B5: 2 | C5: 336358 | D5: GL-MANUAL | E5: HT bù trừ chi phí điện mua nội bộ trong tháng | G5: 1489 | H5: 1305522844714 | I5: 0 | J5: TUAN2HM.HCM.VTA | K5: 5 | L5: -1305522844714 | M5: FALSE | N5: -1305522844714_5 | O5: CHITIET4 | P5: 3
A6: 82900 | B6: 2 | C6: 336358 | D6: GL-MANUAL | E6: HT CP điện mua nội bộ T5/2026 (HĐ 819_05/06/2026) | G6: 1490 | H6: 0 | I6: 1409964672291 | J6: TUAN2HM.HCM.VTA | K6: 5 | L6: 1409964672291 | M6: FALSE | N6: 1409964672291_5 | O6: CHITIET5 | P6: 4
A7: 82900 | B7: 2 | C7: 336358 | D7: GL-MANUAL | E7: KC Thuế GTGT VTĐĐ- hđơn 709-19.05.26-TỔNG CÔNG TY ĐIỆN LỰC THÀNH PHỐ HỒ CHÍ MINH | G7: 1361 | H7: 13464000 | I7: 0 | J7: THANH5DT.HCM.VTA | K7: 5 | L7: -13464000 | M7: FALSE | N7: -13464000_5 | O7: CHITIET6 | P7: 5
A8: 82900 | B8: 2 | C8: 336358 | D8: GL-MANUAL | E8: Kết chuyển công nợ nội bộ tháng 05/2026 | G8: 1631 | H8: 47447508936 | I8: 0 | J8: DUYENTT.HCM.VTA | K8: 5 | L8: -47447508936 | M8: FALSE | N8: -47447508936_5 | O8: CHITIET7 | P8: 6
A9: 82900 | B9: 2 | C9: 336358 | D9: GL-PAYABLE-MANUAL | E9: PCVT kết chuyển lãi vay TK635111 về Tcty qua công nợ 336358 tháng 5.2026 | G9: 1383 | H9: 3758551984 | I9: 0 | J9: LINH3NTT.HCM.VTA | K9: 5 | L9: -3758551984 | M9: FALSE | N9: -3758551984_5 | O9: CHITIET8 | P9: 7
A10: 80100 | B10: 1 | C10: 136358 | D10: GL-RECEIVABLE-MANUAL | E10: Điều chuyển VTTB | G10: 5208 | H10: 102912000 | I10: 0 | J10: THIENDP.HCM.NG | K10: 5 | L10: 102912000 | M10: FALSE | N10: 102912000_5 | O10: CHITIET9 | P10: 8
A11: 80100 | B11: 1 | C11: 136358 | D11: GL-RECEIVABLE-MANUAL | E11: Điều chuyển VTTB | G11: 5286 | H11: 289543680 | I11: 0 | J11: THIENDP.HCM.NG | K11: 5 | L11: 289543680 | M11: FALSE | N11: 289543680_5 | O11: CHITIET10 | P11: 9
A12: 80100 | B12: 1 | C12: 136358 | D12: GL-RECEIVABLE-MANUAL | E12: Điều chuyển VTTB | G12: 5301 | H12: 102546720 | I12: 0 | J12: THIENDP.HCM.NG | K12: 5 | L12: 102546720 | M12: FALSE | N12: 102546720_5 | O12: CHITIET11 | P12: 10
A13: 80100 | B13: 1 | C13: 136358 | D13: GL-RECEIVABLE-MANUAL | E13: Điều chuyển VTTB | G13: 5285 | H13: 376000000 | I13: 0 | J13: THIENDP.HCM.NG | K13: 5 | L13: 376000000 | M13: FALSE | N13: 376000000_5 | O13: CHITIET12 | P13: 11
... A16: 80100 | B16: 1 | C16: 136358 | D16: GL-RECEIVABLE-MANUAL | E16: Điều chuyển VTTB | G16: 5284 | H16: 376000000 | I16: 0 | J16: THIENDP.HCM.NG | K16: 5 | L16: 376000000 | M16: FALSE | N16: 376000000_5 | O16: CHITIET15 | P16: 14
A17: 80100 | B17: 1 | C17: 136358 | D17: Receivables-Misc Receipts | E17: Cấp ĐMT T04/2026 TT1703-14/03/26 | F17: AB320526_TA | G17: 5110 | H17: 19995043636 | I17: 0 | J17: VIETDT.HCM.NG | K17: 5 | L17: 19995043636 | M17: FALSE | N17: 19995043636_5 | O17: CHITIET35 | P17: 34
A18: 82900 | B18: 2 | C18: 336358 | D18: Receivables-Misc Receipts | E18: Nhập tiền Tổng công ty HCM cấp tiền thanh toán Điện MTMN T04-2026 Đợt 1 | F18: G0526AG024 | G18: 1453 | H18: 0 | I18: 22000000000 | J18: CHAULTN.HCM.VTA | K18: 5 | L18: 22000000000 | M18: FALSE | N18: 22000000000_5 | O18: CHITIET36 | P18: 35
A19: Created with a trial version of Syncfusion Excel library or registered the wrong key in your application. Click here to obtain the valid key.

Sheet 1363611_3363611
A1: Madonvi | B1: NhomTK | C1: SoHieuTaiKhoan | D1: NGUON | E1: DienGiai | F1: SoCTPhanHePhu | G1: SoCTPhanHeGL | H1: SoPSNo | I1: SoPSCo | J1: NguoiLapCT | K1: Thang | L1: NET | M1: Trung | N1: VLOOKUP_NET | O1: id | P1: =HYPERLINK("#TONG_HOP!G1","TRO VE") -> TRO VE
A2: 80100 | B2: 1 | C2: 1363611 | D2: Receivables-Misc Receipts | E2: Cấp Thuế GTGT ĐMT T04/2026 TT1703-14/03/26 | F2: AB320526_TA | G2: 5110 | H2: 2004956364 | I2: 0 | J2: VIETDT.HCM.NG | K2: 5 | L2: 2004956364 | M2: FALSE | N2: 2004956364_5 | O2: CHITIET1 | P2: 0
A6: Created with a trial version of Syncfusion Excel library or registered the wrong key in your application. Click here to obtain the valid key.

Sheet 1363613_3363613
P1: =HYPERLINK("#TONG_HOP!G1","TRO VE") -> TRO VE
A6: Created with a trial version of Syncfusion Excel library or registered the wrong key in your application. Click here to obtain the valid key.

Sheet 1363614_3363614
P1: =HYPERLINK("#TONG_HOP!G1","TRO VE") -> TRO VE
A6: Created with a trial version of Syncfusion Excel library or registered the wrong key in your application. Click here to obtain the valid key.

Sheet 1363721_3363721
P1: =HYPERLINK("#TONG_HOP!G1","TRO VE") -> TRO VE
A6: Created with a trial version of Syncfusion Excel library or registered the wrong key in your application. Click here to obtain the valid key.

Sheet 1363728_3363728
P1: =HYPERLINK("#TONG_HOP!G1","TRO VE") -> TRO VE
A6: Created with a trial version of Syncfusion Excel library or registered the wrong key in your application. Click here to obtain the valid key.

Sheet 13638111_33638111
P1: =HYPERLINK("#TONG_HOP!G1","TRO VE") -> TRO VE
A6: Created with a trial version of Syncfusion Excel library or registered the wrong key in your application. Click here to obtain the valid key.

Sheet 13638118_33638118
P1: =HYPERLINK("#TONG_HOP!G1","TRO VE") -> TRO VE
A6: Created with a trial version of Syncfusion Excel library or registered the wrong key in your application. Click here to obtain the valid key.

Sheet 1363818_3363818
P1: =HYPERLINK("#TONG_HOP!G1","TRO VE") -> TRO VE
A6: Created with a trial version of Syncfusion Excel library or registered the wrong key in your application. Click here to obtain the valid key.

Sheet 1363821_3363821
P1: =HYPERLINK("#TONG_HOP!G1","TRO VE") -> TRO VE
A6: Created with a trial version of Syncfusion Excel library or registered the wrong key in your application. Click here to obtain the valid key.

Sheet 13638221_33638221
A1: Madonvi | B1: NhomTK | C1: SoHieuTaiKhoan | D1: NGUON | E1: DienGiai | F1: SoCTPhanHeGL | G1: SoPSNo | H1: SoPSCo | I1: NguoiLapCT | J1: Thang | K1: NET | L1: Trung | M1: VLOOKUP_NET | N1: id | O1: rowOrder | P1: =HYPERLINK("#TONG_HOP!G1","TRO VE") -> TRO VE
A2: 82900 | B2: 2 | C2: 33638221 | D2: GL-MANUAL | E2: Kết chuyển lợi nhuận thu nhập khác tháng 05/2026 - Vi phạm HĐ điện | F2: 1631 | G2: 0 | H2: 2468617 | I2: DUYENTT.HCM.VTA | J2: 5 | K2: 2468617 | L2: FALSE | M2: 2468617_5 | N2: CHITIET1 | O2: 0
A6: Created with a trial version of Syncfusion Excel library or registered the wrong key in your application. Click here to obtain the valid key.

Sheet 13638222_33638222
P1: =HYPERLINK("#TONG_HOP!G1","TRO VE") -> TRO VE
A6: Created with a trial version of Syncfusion Excel library or registered the wrong key in your application. Click here to obtain the valid key.

Sheet 13638223_33638223
P1: =HYPERLINK("#TONG_HOP!G1","TRO VE") -> TRO VE
A6: Created with a trial version of Syncfusion Excel library or registered the wrong key in your application. Click here to obtain the valid key.

Sheet 1363823_3363823
P1: =HYPERLINK("#TONG_HOP!G1","TRO VE") -> TRO VE
A6: Created with a trial version of Syncfusion Excel library or registered the wrong key in your application. Click here to obtain the valid key.

Sheet 1363825_3363825
P1: =HYPERLINK("#TONG_HOP!G1","TRO VE") -> TRO VE
A6: Created with a trial version of Syncfusion Excel library or registered the wrong key in your application. Click here to obtain the valid key.

Sheet 1363828_3363828
P1: =HYPERLINK("#TONG_HOP!G1","TRO VE") -> TRO VE
A6: Created with a trial version of Syncfusion Excel library or registered the wrong key in your application. Click here to obtain the valid key.

Sheet 1363829_3363829
P1: =HYPERLINK("#TONG_HOP!G1","TRO VE") -> TRO VE
A6: Created with a trial version of Syncfusion Excel library or registered the wrong key in your application. Click here to obtain the valid key.

Sheet 1363841_3363841
P1: =HYPERLINK("#TONG_HOP!G1","TRO VE") -> TRO VE
A6: Created with a trial version of Syncfusion Excel library or registered the wrong key in your application. Click here to obtain the valid key.

Sheet 1363842_3363842
P1: =HYPERLINK("#TONG_HOP!G1","TRO VE") -> TRO VE
A6: Created with a trial version of Syncfusion Excel library or registered the wrong key in your application. Click here to obtain the valid key.

Sheet 1363843_3363843
P1: =HYPERLINK("#TONG_HOP!G1","TRO VE") -> TRO VE
A6: Created with a trial version of Syncfusion Excel library or registered the wrong key in your application. Click here to obtain the valid key.

Sheet 1363844_3363844
P1: =HYPERLINK("#TONG_HOP!G1","TRO VE") -> TRO VE
A6: Created with a trial version of Syncfusion Excel library or registered the wrong key in your application. Click here to obtain the valid key.

Sheet 1363845_3363845
P1: =HYPERLINK("#TONG_HOP!G1","TRO VE") -> TRO VE
A6: Created with a trial version of Syncfusion Excel library or registered the wrong key in your application. Click here to obtain the valid key.

Sheet 1363847_3363847
A1: Madonvi | B1: NhomTK | C1: SoHieuTaiKhoan | D1: NGUON | E1: DienGiai | F1: SoCTPhanHeGL | G1: SoPSNo | H1: SoPSCo | I1: NguoiLapCT | J1: Thang | K1: NET | L1: Trung | M1: VLOOKUP_NET | N1: id | O1: rowOrder | P1: =HYPERLINK("#TONG_HOP!G1","TRO VE") -> TRO VE
A2: 82900 | B2: 2 | C2: 3363847 | D2: GL-MANUAL | E2: Kết chuyển lợi nhuận hoạt động tài chính tháng 05/2026 | F2: 1631 | G2: 0 | H2: 2095232 | I2: DUYENTT.HCM.VTA | J2: 5 | K2: 2095232 | L2: FALSE | M2: 2095232_5 | N2: CHITIET1 | O2: 0
A6: Created with a trial version of Syncfusion Excel library or registered the wrong key in your application. Click here to obtain the valid key.

Sheet 1363848_3363848
A1: Madonvi | B1: NhomTK | C1: SoHieuTaiKhoan | D1: NGUON | E1: DienGiai | F1: SoCTPhanHeGL | G1: SoPSNo | H1: SoPSCo | I1: NguoiLapCT | J1: Thang | K1: NET | L1: Trung | M1: VLOOKUP_NET | N1: id | O1: rowOrder | P1: =HYPERLINK("#TONG_HOP!G1","TRO VE") -> TRO VE
A2: 82900 | B2: 2 | C2: 3363848 | D2: GL-MANUAL | E2: Kết chuyển lợi nhuận thu nhập khác tháng 05/2026 - KHTSCĐ | F2: 1631 | G2: 0 | H2: 0 | I2: DUYENTT.HCM.VTA | J2: 5 | K2: 0 | L2: FALSE | M2: 0_5 | N2: CHITIET1 | O2: 0
A3: 82900 | B3: 2 | C3: 3363848 | D3: GL-MANUAL | E3: Kết chuyển lợi nhuận thu nhập khác tháng 05/2026 - Thu dư, thu khác | F3: 1631 | G3: 0 | H3: 8999937 | I3: DUYENTT.HCM.VTA | J3: 5 | K3: 8999937 | L3: FALSE | M3: 8999937_5 | N3: CHITIET2 | O3: 1
A4: 82900 | B4: 2 | C4: 3363848 | D4: GL-MANUAL | E4: Kết chuyển công nợ nội bộ, lợi nhuận tháng 05/2026 - Thanh lý VTTBTS | F4: 1631 | G4: 0 | H4: 0 | I4: DUYENTT.HCM.VTA | J4: 5 | K4: 0 | L4: FALSE | M4: 0_5 | N4: CHITIET3 | O4: 2
A6: Created with a trial version of Syncfusion Excel library or registered the wrong key in your application. Click here to obtain the valid key.

Sheet 1363883_3363883
A1: Madonvi | B1: NhomTK | C1: SoHieuTaiKhoan | D1: NGUON | E1: DienGiai | F1: SoCTPhanHeGL | G1: SoPSNo | H1: SoPSCo | I1: NguoiLapCT | J1: Thang | K1: NET | L1: Trung | M1: VLOOKUP_NET | N1: id | O1: rowOrder | P1: =HYPERLINK("#TONG_HOP!G1","TRO VE") -> TRO VE
A2: 82900 | B2: 2 | C2: 3363883 | D2: GL-MANUAL | E2: Thuế GTGT VTĐĐ- hđơn 666-11.05.26-TỔNG CÔNG TY ĐIỆN LỰC THÀNH PHỐ HỒ CHÍ MINH | F2: 1361 | G2: 0 | H2: 25728000 | I2: THANH5DT.HCM.VTA | J2: 5 | K2: 25728000 | L2: FALSE | M2: 25728000_5 | N2: CHITIET1 | O2: 0
A3: 82900 | B3: 2 | C3: 3363883 | D3: GL-MANUAL | E3: KC Thuế GTGT VTĐĐ- hđơn 666-11.05.26-TỔNG CÔNG TY ĐIỆN LỰC THÀNH PHỐ HỒ CHÍ MINH | F3: 1361 | G3: 25728000 | H3: 0 | I3: THANH5DT.HCM.VTA | J3: 5 | K3: -25728000 | L3: FALSE | M3: -25728000_5 | N3: CHITIET2 | O3: 1
A4: 82900 | B4: 2 | C4: 3363883 | D4: GL-MANUAL | E4: Thuế GTGT VTĐĐ- hđơn 681-13.05.26-TỔNG CÔNG TY ĐIỆN LỰC THÀNH PHỐ HỒ CHÍ MINH | F4: 1361 | G4: 0 | H4: 102912000 | I4: THANH5DT.HCM.VTA | J4: 5 | K4: 102912000 | L4: FALSE | M4: 102912000_5 | N4: CHITIET3 | O4: 2
A5: 82900 | B5: 2 | C5: 3363883 | D5: GL-MANUAL | E5: KC Thuế GTGT VTĐĐ- hđơn 681-13.05.26-TỔNG CÔNG TY ĐIỆN LỰC THÀNH PHỐ HỒ CHÍ MINH | F5: 1361 | G5: 102912000 | H5: 0 | I5: THANH5DT.HCM.VTA | J5: 5 | K5: -102912000 | L5: FALSE | M5: -102912000_5 | N5: CHITIET4 | O5: 3
A6: 82900 | B6: 2 | C6: 3363883 | D6: GL-MANUAL | E6: Thuế GTGT VTĐĐ- hđơn 760-26.05.26-TỔNG CÔNG TY ĐIỆN LỰC THÀNH PHỐ HỒ CHÍ MINH | F6: 1361 | G6: 0 | H6: 376000000 | I6: THANH5DT.HCM.VTA | J6: 5 | K6: 376000000 | L6: FALSE | M6: 376000000_5 | N6: CHITIET5 | O6: 4
A7: 82900 | B7: 2 | C7: 3363883 | D7: GL-MANUAL | E7: KC Thuế GTGT VTĐĐ- hđơn 760-26.05.26-TỔNG CÔNG TY ĐIỆN LỰC THÀNH PHỐ HỒ CHÍ MINH | F7: 1361 | G7: 376000000 | H7: 0 | I7: THANH5DT.HCM.VTA | J7: 5 | K7: -376000000 | L7: FALSE | M7: -376000000_5 | N7: CHITIET6 | O7: 5
A8: 82900 | B8: 2 | C8: 3363883 | D8: GL-MANUAL | E8: Thuế GTGT VTĐĐ- hđơn 761-26.05.26-TỔNG CÔNG TY ĐIỆN LỰC THÀNH PHỐ HỒ CHÍ MINH | F8: 1361 | G8: 0 | H8: 376000000 | I8: THANH5DT.HCM.VTA | J8: 5 | K8: 376000000 | L8: FALSE | M8: 376000000_5 | N8: CHITIET7 | O8: 6
A9: 82900 | B9: 2 | C9: 3363883 | D9: GL-MANUAL | E9: KC Thuế GTGT VTĐĐ- hđơn 761-26.05.26-TỔNG CÔNG TY ĐIỆN LỰC THÀNH PHỐ HỒ CHÍ MINH | F9: 1361 | G9: 376000000 | H9: 0 | I9: THANH5DT.HCM.VTA | J9: 5 | K9: -376000000 | L9: FALSE | M9: -376000000_5 | N9: CHITIET8 | O9: 7
A10: 82900 | B10: 2 | C10: 3363883 | D10: GL-MANUAL | E10: Thuế GTGT VTĐĐ- hđơn 752-25.05.26-TỔNG CÔNG TY ĐIỆN LỰC THÀNH PHỐ HỒ CHÍ MINH | F10: 1361 | G10: 0 | H10: 144771840 | I10: THANH5DT.HCM.VTA | J10: 5 | K10: 144771840 | L10: FALSE | M10: 144771840_5 | N10: CHITIET9 | O10: 8
A11: 82900 | B11: 2 | C11: 3363883 | D11: GL-MANUAL | E11: KC Thuế GTGT VTĐĐ- hđơn 752-25.05.26-TỔNG CÔNG TY ĐIỆN LỰC THÀNH PHỐ HỒ CHÍ MINH | F11: 1361 | G11: 144771840 | H11: 0 | I11: THANH5DT.HCM.VTA | J11: 5 | K11: -144771840 | L11: FALSE | M11: -144771840_5 | N11: CHITIET10 | O11: 9
A12: 82900 | B12: 2 | C12: 3363883 | D12: GL-MANUAL | E12: Thuế GTGT VTĐĐ- hđơn 762-26.05.26-TỔNG CÔNG TY ĐIỆN LỰC THÀNH PHỐ HỒ CHÍ MINH | F12: 1361 | G12: 0 | H12: 289543680 | I12: THANH5DT.HCM.VTA | J12: 5 | K12: 289543680 | L12: FALSE | M12: 289543680_5 | N12: CHITIET11 | O12: 10
A13: 82900 | B13: 2 | C13: 3363883 | D13: GL-MANUAL | E13: KC Thuế GTGT VTĐĐ- hđơn 762-26.05.26-TỔNG CÔNG TY ĐIỆN LỰC THÀNH PHỐ HỒ CHÍ MINH | F13: 1361 | G13: 289543680 | H13: 0 | I13: THANH5DT.HCM.VTA | J13: 5 | K13: -289543680 | L13: FALSE | M13: -289543680_5 | N13: CHITIET12 | O13: 11
... A38: 82900 | B38: 2 | C38: 3363883 | D38: GL-PAYABLE-MANUAL | E38: 25004_Điều chỉnh đối tượng 3363883-Nhập đ/động theo HĐ921-08.09.25 của TCTy ĐL TPHCM- chuyển vật tư từ CT25016 sang CT25004 | F38: 1553 | G38: 0 | H38: 369144160 | I38: HIENNTK.HCM.VTA | J38: 5 | K38: 369144160 | L38: FALSE | M38: 369144160_5 | N38: CHITIET37 | O38: 36
A39: Created with a trial version of Syncfusion Excel library or registered the wrong key in your application. Click here to obtain the valid key.

Sheet 1363888_3363888
P1: =HYPERLINK("#TONG_HOP!G1","TRO VE") -> TRO VE
A6: Created with a trial version of Syncfusion Excel library or registered the wrong key in your application. Click here to obtain the valid key.

Sheet 3363888_1363888
P1: =HYPERLINK("#TONG_HOP!G1","TRO VE") -> TRO VE
A6: Created with a trial version of Syncfusion Excel library or registered the wrong key in your application. Click here to obtain the valid key.

Sheet 136391_336391
P1: =HYPERLINK("#TONG_HOP!G1","TRO VE") -> TRO VE
A6: Created with a trial version of Syncfusion Excel library or registered the wrong key in your application. Click here to obtain the valid key.

Sheet 136392_336392
P1: =HYPERLINK("#TONG_HOP!G1","TRO VE") -> TRO VE
A6: Created with a trial version of Syncfusion Excel library or registered the wrong key in your application. Click here to obtain the valid key.

Sheet 136393_336393
P1: =HYPERLINK("#TONG_HOP!G1","TRO VE") -> TRO VE
A6: Created with a trial version of Syncfusion Excel library or registered the wrong key in your application. Click here to obtain the valid key.

Sheet 13681_33681
A1: Madonvi | B1: NhomTK | C1: SoHieuTaiKhoan | D1: NGUON | E1: DienGiai | F1: SoCTPhanHePhu | G1: SoCTPhanHeGL | H1: SoPSNo | I1: SoPSCo | J1: NguoiLapCT | K1: Thang | L1: NET | P1: =HYPERLINK("#TONG_HOP!G1","TRO VE") -> TRO VE
A2: 82900 | B2: 1 | C2: 13681 | D2: Cost Management-Inventory | E2: 25039-SX:Xuất vtư từ SXKD đ/c cho Ctr Trang bị Tbị REC, LBS có Scada trên LĐ PCVT | F2: 30768803 | G2: 1572 | H2: 2370368 | I2: 0 | J2: THANH5DT.HCM.VTA | K2: 5 | L2: 2370368
A3: 82900 | B3: 1 | C3: 13681 | D3: Cost Management-Inventory | E3: 25039-SX:Xuất vtư từ SXKD đ/c cho Ctr Trang bị Tbị REC, LBS có Scada trên LĐ PCVT | F3: 30768802 | G3: 1572 | H3: 2382761 | I3: 0 | J3: THANH5DT.HCM.VTA | K3: 5 | L3: 2382761
A4: 82900 | B4: 1 | C4: 13681 | D4: Cost Management-Inventory | E4: 25039-SX:Xuất vtư từ SXKD đ/c cho Ctr Trang bị Tbị REC, LBS có Scada trên LĐ PCVT | F4: 30768882 | G4: 1572 | H4: 2490000 | I4: 0 | J4: THANH5DT.HCM.VTA | K4: 5 | L4: 2490000
A5: 82900 | B5: 1 | C5: 13681 | D5: Cost Management-Inventory | E5: 25039-SX:Xuất vtư từ SXKD đ/c cho Ctr Trang bị Tbị REC, LBS có Scada trên LĐ PCVT | F5: 30768797 | G5: 1572 | H5: 2780000 | I5: 0 | J5: THANH5DT.HCM.VTA | K5: 5 | L5: 2780000
A6: 82900 | B6: 1 | C6: 13681 | D6: Cost Management-Inventory | E6: 25039-SX:Xuất vtư từ SXKD đ/c cho Ctr Trang bị Tbị REC, LBS có Scada trên LĐ PCVT | F6: 30768799 | G6: 1572 | H6: 3749854 | I6: 0 | J6: THANH5DT.HCM.VTA | K6: 5 | L6: 3749854
A7: 82900 | B7: 2 | C7: 33681 | D7: Cost Management-Inventory | E7: 25039-SX:Nhập vtư từ SXKD đ/c cho Ctr Trang bị Tbị REC, LBS có Scada trên LĐ PCVT | F7: 30799868 | G7: 1570 | H7: 0 | I7: 1295000 | J7: THANH5DT.HCM.VTA | K7: 5 | L7: 1295000
A8: 82900 | B8: 2 | C8: 33681 | D8: Cost Management-Inventory | E8: 25039-SX:Nhập vtư từ SXKD đ/c cho Ctr Trang bị Tbị REC, LBS có Scada trên LĐ PCVT | F8: 30771097 | G8: 1572 | H8: 0 | I8: 1780352 | J8: THANH5DT.HCM.VTA | K8: 5 | L8: 1780352
A9: 82900 | B9: 2 | C9: 33681 | D9: Cost Management-Inventory | E9: 25039-SX:Nhập vtư từ SXKD đ/c cho Ctr Trang bị Tbị REC, LBS có Scada trên LĐ PCVT | F9: 30771123 | G9: 1572 | H9: 0 | I9: 1945935 | J9: THANH5DT.HCM.VTA | K9: 5 | L9: 1945935
A10: 82900 | B10: 2 | C10: 33681 | D10: Cost Management-Inventory | E10: 25039-SX:Nhập vtư từ SXKD đ/c cho Ctr Trang bị Tbị REC, LBS có Scada trên LĐ PCVT | F10: 30771096 | G10: 1572 | H10: 0 | I10: 2370368 | J10: THANH5DT.HCM.VTA | K10: 5 | L10: 2370368
A11: 82900 | B11: 2 | C11: 33681 | D11: Cost Management-Inventory | E11: 25039-SX:Nhập vtư từ SXKD đ/c cho Ctr Trang bị Tbị REC, LBS có Scada trên LĐ PCVT | F11: 30771095 | G11: 1572 | H11: 0 | I11: 2382761 | J11: THANH5DT.HCM.VTA | K11: 5 | L11: 2382761
A12: 82900 | B12: 2 | C12: 33681 | D12: Cost Management-Inventory | E12: 25039-SX:Nhập vtư từ SXKD đ/c cho Ctr Trang bị Tbị REC, LBS có Scada trên LĐ PCVT | F12: 30771122 | G12: 1572 | H12: 0 | I12: 2490000 | J12: THANH5DT.HCM.VTA | K12: 5 | L12: 2490000
A13: 82900 | B13: 2 | C13: 33681 | D13: Cost Management-Inventory | E13: 25039-SX:Nhập vtư từ SXKD đ/c cho Ctr Trang bị Tbị REC, LBS có Scada trên LĐ PCVT | F13: 30771090 | G13: 1572 | H13: 0 | I13: 2780000 | J13: THANH5DT.HCM.VTA | K13: 5 | L13: 2780000
... A15: 82900 | B15: 2 | C15: 33681 | D15: Cost Management-Inventory | E15: 25039-SX:Nhập vtư từ SXKD đ/c cho Ctr Trang bị Tbị REC, LBS có Scada trên LĐ PCVT | F15: 30771094 | G15: 1572 | H15: 0 | I15: 4787165 | J15: THANH5DT.HCM.VTA | K15: 5 | L15: 4787165
A16: 82900 | B16: 2 | C16: 33681 | D16: GL-PAYABLE-MANUAL | E16: Điều chỉnh 13681-33681-từ CT23009 sang CT25009 do nhầm đối tượng | G16: 1353 | H16: 0 | I16: -10022533 | J16: HIENNTK.HCM.VTA | K16: 5 | L16: -10022533
A17: 82900 | B17: 2 | C17: 33681 | D17: GL-PAYABLE-MANUAL | E17: Điều chỉnh 13681-33681-từ CT23009 sang CT25009 do nhầm đối tượng -CP BHXH,BHYT...tháng 4-Ban QLDA | G17: 1353 | H17: 0 | I17: 10022533 | J17: HIENNTK.HCM.VTA | K17: 5 | L17: 10022533
A18: 82900 | B18: 2 | C18: 33681 | D18: GL-PAYABLE-MANUAL | E18: Điều chỉnh 13681-lương thêm giờ tháng 3/2025 của Ban QLDA do hạch toán trùng 2 lần | G18: 1353 | H18: 0 | I18: -109089718 | J18: HIENNTK.HCM.VTA | K18: 5 | L18: -109089718
A19: 82900 | B19: 1 | C19: 13681 | D19: GL-PAYABLE-MANUAL | E19: Điều chỉnh 13681-33681-từ CT23009 sang CT25009 do nhầm đối tượng | G19: 1353 | H19: -10022533 | I19: 0 | J19: HIENNTK.HCM.VTA | K19: 5 | L19: -10022533
A20: 82900 | B20: 1 | C20: 13681 | D20: GL-PAYABLE-MANUAL | E20: Điều chỉnh 13681-33681-từ CT23009 sang CT25009 do nhầm đối tượng -CP BHXH,BHYT...tháng 4-Ban QLDA | G20: 1353 | H20: 10022533 | I20: 0 | J20: HIENNTK.HCM.VTA | K20: 5 | L20: 10022533
A21: 82900 | B21: 1 | C21: 13681 | D21: GL-PAYABLE-MANUAL | E21: Điều chỉnh 13681-lương thêm giờ tháng 3/2025 của Ban QLDA do hạch toán trùng 2 lần | G21: 1353 | H21: -109089718 | I21: 0 | J21: HIENNTK.HCM.VTA | K21: 5 | L21: -109089718
A22: 82900 | B22: 1 | C22: 13681 | D22: Cost Management-Inventory | E22: 25039-SX:Xuất vtư từ SXKD đ/c cho Ctr Trang bị Tbị REC, LBS có Scada trên LĐ PCVT | F22: 30799839 | G22: 1570 | H22: 12000 | I22: 0 | J22: THANH5DT.HCM.VTA | K22: 5 | L22: 12000
A23: 82900 | B23: 1 | C23: 13681 | D23: Cost Management-Inventory | E23: 25039-SX:Xuất vtư từ SXKD đ/c cho Ctr Trang bị Tbị REC, LBS có Scada trên LĐ PCVT | F23: 30799844 | G23: 1570 | H23: 30207 | I23: 0 | J23: THANH5DT.HCM.VTA | K23: 5 | L23: 30207
A24: 82900 | B24: 1 | C24: 13681 | D24: Cost Management-Inventory | E24: 25039-SX:Xuất vtư từ SXKD đ/c cho Ctr Trang bị Tbị REC, LBS có Scada trên LĐ PCVT | F24: 30799842 | G24: 1570 | H24: 33600 | I24: 0 | J24: THANH5DT.HCM.VTA | K24: 5 | L24: 33600
A25: 82900 | B25: 1 | C25: 13681 | D25: Cost Management-Inventory | E25: 25039-SX:Xuất vtư từ SXKD đ/c cho Ctr Trang bị Tbị REC, LBS có Scada trên LĐ PCVT | F25: 30799845 | G25: 1570 | H25: 36646 | I25: 0 | J25: THANH5DT.HCM.VTA | K25: 5 | L25: 36646
A26: 82900 | B26: 1 | C26: 13681 | D26: Cost Management-Inventory | E26: 25039-SX:Xuất vtư từ SXKD đ/c cho Ctr Trang bị Tbị REC, LBS có Scada trên LĐ PCVT | F26: 30786944 | G26: 1571 | H26: 48000 | I26: 0 | J26: THANH5DT.HCM.VTA | K26: 5 | L26: 48000
A27: 82900 | B27: 2 | C27: 33681 | D27: Cost Management-Inventory | E27: 24017-SX:Xuất VTTB từ Ctr KNCT 2024 điều chuyển SXKD phục vụ SCTX | F27: 30680999 | G27: 1573 | H27: 45558700 | I27: 0 | J27: THANH5DT.HCM.VTA | K27: 5 | L27: -45558700
A28: 82900 | B28: 2 | C28: 33681 | D28: Cost Management-Inventory | E28: 25001-SX:Xuất VTTB từ Ctr NC THT TPVT,BR điều chuyển SXKD phục vụ SCTX | F28: 30680917 | G28: 1573 | H28: 85399035 | I28: 0 | J28: THANH5DT.HCM.VTA | K28: 5 | L28: -85399035
A29: 82900 | B29: 2 | C29: 33681 | D29: Cost Management-Inventory | E29: 24027-SX:Xuất VTTB từ Ctr CQT Tx Phú Mỹ điều chuyển SXKD phục vụ SCTX | F29: 30680867 | G29: 1573 | H29: 153964800 | I29: 0 | J29: THANH5DT.HCM.VTA | K29: 5 | L29: -153964800
A30: 82900 | B30: 2 | C30: 33681 | D30: Cost Management-Inventory | E30: 25001-SX:Xuất VTTB từ Ctr NC THT TPVT,BR điều chuyển SXKD phục vụ SCTX | F30: 30680918 | G30: 1573 | H30: 205962600 | I30: 0 | J30: THANH5DT.HCM.VTA | K30: 5 | L30: -205962600
A31: 82900 | B31: 2 | C31: 33681 | D31: Cost Management-Inventory | E31: 25039-SX:Nhập vtư từ SXKD đ/c cho Ctr Trang bị Tbị REC, LBS có Scada trên LĐ PCVT | F31: 30799885 | G31: 1570 | H31: 0 | I31: 12000 | J31: THANH5DT.HCM.VTA | K31: 5 | L31: 12000
A32: 82900 | B32: 2 | C32: 33681 | D32: Cost Management-Inventory | E32: 25039-SX:Nhập vtư từ SXKD đ/c cho Ctr Trang bị Tbị REC, LBS có Scada trên LĐ PCVT | F32: 30799890 | G32: 1570 | H32: 0 | I32: 30207 | J32: THANH5DT.HCM.VTA | K32: 5 | L32: 30207
A33: 82900 | B33: 2 | C33: 33681 | D33: Cost Management-Inventory | E33: 25039-SX:Nhập vtư từ SXKD đ/c cho Ctr Trang bị Tbị REC, LBS có Scada trên LĐ PCVT | F33: 30799888 | G33: 1570 | H33: 0 | I33: 33600 | J33: THANH5DT.HCM.VTA | K33: 5 | L33: 33600
... A77: 82900 | B77: 1 | C77: 13681 | D77: Cost Management-Inventory | E77: 25001 SX Nhập vật tư từ kho ĐTXD sang SXKD | F77: 30683307 | G77: 1573 | H77: 0 | I77: 205962600 | J77: THANH5DT.HCM.VTA | K77: 5 | L77: -205962600
A78: 82900 | B78: 1 | C78: 13681 | D78: GL-PAYABLE-MANUAL | E78: Điều chỉnh 13681-33681- do PX01.VH9.53.0102 ngày 10.12.25 xuất vật tư (điều từ sxkd) từ CT24028 sang CT25033 - | G78: 1353 | H78: -422173 | I78: 0 | J78: HIENNTK.HCM.VTA | K78: 5 | L78: -422173
A79: 82900 | B79: 1 | C79: 13681 | D79: GL-PAYABLE-MANUAL | E79: Điều chỉnh 13681-33681- do PX01.VH9.53.0102 ngày 10.12.25 xuất vật tư (điều từ sxkd) từ CT24028 sang CT25033 - | G79: 1353 | H79: 422173 | I79: 0 | J79: HIENNTK.HCM.VTA | K79: 5 | L79: 422173
A80: 82900 | B80: 1 | C80: 13681 | D80: Receivables-Misc Receipts | E80: Thanh toán chi phí đặt ăn công tác kiểm tra công trình ĐTXD năm 2026 - Hóa đơn 987/30.04.26 | F80: R0526SC0520 | G80: 1486 | H80: 2779529 | I80: 0 | J80: CHAULTN.HCM.VTA | K80: 5 | L80: 2779529
A81: 82900 | B81: 1 | C81: 13681 | D81: Receivables-Misc Receipts | E81: Thanh toán chi phí đặt ăn kiểm tra khối lượng xây lắp hoàn thành & chất lượng các công trình ĐTXD năm 2025 - Hóa đơn 1314/21.05.26 | F81: R0526SC0587 | G81: 1405 | H81: 3705555 | I81: 0 | J81: CHAULTN.HCM.VTA | K81: 5 | L81: 3705555
A82: 82900 | B82: 1 | C82: 13681 | D82: Receivables-Misc Receipts | E82: Thanh toán chi phí đặt ăn kiểm tra khối lượng xây lắp hoàn thành & chất lượng các công trình ĐTXD năm 2025 - Hóa đơn 1199;1245 ngày 19,21/05.26 | F82: R0526SC0586 | G82: 1405 | H82: 3699899 | I82: 0 | J82: CHAULTN.HCM.VTA | K82: 5 | L82: 3699899
A83: 82900 | B83: 1 | C83: 13681 | D83: Receivables-Misc Receipts | E83: Thanh toán chi phí đặt ăn kiểm tra khối lượng xây lắp hoàn thành & chất lượng các công trình ĐTXD năm 2025 - Hóa đơn 1199;1245 ngày 19,21/05.26 | F83: R0526SC0586 | G83: 1405 | H83: 3727778 | I83: 0 | J83: CHAULTN.HCM.VTA | K83: 5 | L83: 3727778
A84: 82900 | B84: 1 | C84: 13681 | D84: Receivables-Misc Receipts | E84: Nhập tiền từ TK ĐTXD tiền vật tư A cấp thừa ĐVTC đền tiền công trình F02F02F02 LT0K 25016 | F84: G0526SC0085 | G84: 1449 | H84: 0 | I84: 35640660 | J84: CHAULTN.HCM.VTA | K84: 5 | L84: -35640660
A85: 82900 | B85: 1 | C85: 13681 | D85: GL-PAYABLE-MANUAL | E85: Điều chỉnh 13681-03.VH1.57.0030/31.12.25-Xuất máy vi tính (hóa đơn 190824) | G85: 1353 | H85: -38879630 | I85: 0 | J85: HIENNTK.HCM.VTA | K85: 5 | L85: -38879630
A86: 82900 | B86: 1 | C86: 13681 | D86: GL-PAYABLE-MANUAL | E86: Điều chỉnh 13681-03.VH1.57.0030/31.12.25-Xuất máy vi tính (hóa đơn 190824) | G86: 1353 | H86: 38879630 | I86: 0 | J86: HIENNTK.HCM.VTA | K86: 5 | L86: 38879630
A87: 82900 | B87: 1 | C87: 13681 | D87: GL-PAYABLE-MANUAL | E87: Phải thu phí chuyển tiền ngân hàng BIDV CT25016 | G87: 1353 | H87: 9937069 | I87: 0 | J87: HIENNTK.HCM.VTA | K87: 5 | L87: 9937069
A88: 82900 | B88: 1 | C88: 13681 | D88: GL-PAYABLE-MANUAL | E88: P/BỔ Chi phí GIÁM SÁT ĐTXD - D00M.D00M.24015 (bổ sung) | G88: 1353 | H88: 1466208 | I88: 0 | J88: HIENNTK.HCM.VTA | K88: 5 | L88: 1466208
A89: 82900 | B89: 1 | C89: 13681 | D89: Payables-Purchase Invoices | E89: Giải trừ tạm ứng cho bà Vũ Thanh Nguyên phục vụ công tác kiểm tra khối lượng các công trình ĐTXD năm 2025 | F89: AP261312 | G89: 1551 | H89: 3711784 | I89: 0 | J89: DUNGLTP.HCM.VTA | K89: 5 | L89: 3711784
A90: 82900 | B90: 1 | C90: 13681 | D90: Payables-Purchase Invoices | E90: Giải trừ tạm ứng cho bà Vũ Thanh Nguyên phục vụ công tác kiểm tra khối lượng các công trình ĐTXD năm 2025 | F90: AP261312 | G90: 1551 | H90: 16704128 | I90: 0 | J90: DUNGLTP.HCM.VTA | K90: 5 | L90: 16704128
A91: 82900 | B91: 1 | C91: 13681 | D91: Payables-Purchase Invoices | E91: Giải trừ tạm ứng cho ông Vũ Thanh Tâm P.QLĐT phục vụ công tác kiểm tra khối lượng các công trình ĐTXD năm 2025 | F91: AP261313 | G91: 1551 | H91: 20919448 | I91: 0 | J91: DUNGLTP.HCM.VTA | K91: 5 | L91: 20919448
A92: 82900 | B92: 1 | C92: 13681 | D92: GL-PAYABLE-MANUAL | E92: Hạch toán công nợ chi phí bảo hiểm, kho bãi (biên bản 25.05.26) cty Quang Huy đền tiền vật tư A cấp | G92: 1387 | H92: 6062400 | I92: 0 | J92: HIENNTK.HCM.VTA | K92: 5 | L92: 6062400
A93: 82900 | B93: 1 | C93: 13681 | D93: Receivables-Misc Receipts | E93: Thanh toán chi phí đặt ăn kiểm tra khối lượng xây lắp hoàn thành & chất lượng các công trình ĐTXD năm 2025 - Hóa đơn 1380; 458 ngày 19,23/05.26 | F93: R0526SC0585 | G93: 1405 | H93: 7436869 | I93: 0 | J93: CHAULTN.HCM.VTA | K93: 5 | L93: 7436869
A94: 82900 | B94: 1 | C94: 13681 | D94: Receivables-Misc Receipts | E94: Thanh toán tiền đặt ăn lịch làm việc với UBND phương Phước Thắng_Hóa đơn 656/16.04.26 | F94: R0526SC0521 | G94: 1486 | H94: 9257000 | I94: 0 | J94: CHAULTN.HCM.VTA | K94: 5 | L94: 9257000
A95: 82900 | B95: 1 | C95: 13681 | D95: Receivables-Misc Receipts | E95: Thanh toán chi phí đặt ăn công tác kiểm điểm tiến độ thi công và quyết toán VTTB thu hồi công trình ĐTXD 2025 chuyển tiếp -Hóa đơn 1087/29.04.26 | F95: R0526SC0468 | G95: 1471 | H95: 9265000 | I95: 0 | J95: CHAULTN.HCM.VTA | K95: 5 | L95: 9265000
A96: 82900 | B96: 1 | C96: 13681 | D96: Receivables-Misc Receipts | E96: Thanh toán tiền thuê kho bãi tháng 02+03/2026 - HĐồng số 06-2026/HĐDV/PCVT-HKD.LINH ngày 31.12.25 | F96: R0526SC0496 | G96: 1448 | H96: 25000000 | I96: 0 | J96: CHAULTN.HCM.VTA | K96: 5 | L96: 25000000
A97: 82900 | B97: 1 | C97: 13681 | D97: Receivables-Misc Receipts | E97: Thanh toán tiền thuê kho bãi tháng 02+03/2026 - HĐồng số 06-2026/HĐDV/PCVT-HKD.LINH ngày 31.12.25 | F97: R0526SC0496 | G97: 1448 | H97: 25000000 | I97: 0 | J97: CHAULTN.HCM.VTA | K97: 5 | L97: 25000000
A98: 82900 | B98: 1 | C98: 13681 | D98: Receivables-Misc Receipts | E98: Thanh toán tiền thuê kho bãi tháng 02+03/2026 - HĐồng số 06-2026/HĐDV/PCVT-HKD.LINH ngày 31.12.25 | F98: R0526SC0496 | G98: 1448 | H98: 25000000 | I98: 0 | J98: CHAULTN.HCM.VTA | K98: 5 | L98: 25000000
A99: 82900 | B99: 1 | C99: 13681 | D99: Receivables-Misc Receipts | E99: Thanh toán tiền thuê kho bãi tháng 02+03/2026 - HĐồng số 06-2026/HĐDV/PCVT-HKD.LINH ngày 31.12.25 | F99: R0526SC0496 | G99: 1448 | H99: 25000000 | I99: 0 | J99: CHAULTN.HCM.VTA | K99: 5 | L99: 25000000
A100: 82900 | B100: 1 | C100: 13681 | D100: Receivables-Misc Receipts | E100: Thanh toán tiền thuê kho bãi tháng 01/2026->03/2026 - HĐồng số 05-2026/HĐDV/PCVT-HKD.NHI ngày 31.12.25 | F100: R0526SC0503 | G100: 1448 | H100: 32400000 | I100: 0 | J100: CHAULTN.HCM.VTA | K100: 5 | L100: 32400000
A101: 82900 | B101: 1 | C101: 13681 | D101: Receivables-Misc Receipts | E101: Thanh toán tiền thuê kho bãi tháng 01/2026->03/2026 - HĐồng số 05-2026/HĐDV/PCVT-HKD.NHI ngày 31.12.25 | F101: R0526SC0503 | G101: 1448 | H101: 32400000 | I101: 0 | J101: CHAULTN.HCM.VTA | K101: 5 | L101: 32400000
A102: 82900 | B102: 1 | C102: 13681 | D102: Cost Management-Inventory | E102: 25039-SX:Xuất vtư từ SXKD đ/c cho Ctr Trang bị Tbị REC, LBS có Scada trên LĐ PCVT | F102: 30799846 | G102: 1570 | H102: 95991 | I102: 0 | J102: THANH5DT.HCM.VTA | K102: 5 | L102: 95991
A103: 82900 | B103: 1 | C103: 13681 | D103: Cost Management-Inventory | E103: 25039-SX:Xuất vtư từ SXKD đ/c cho Ctr Trang bị Tbị REC, LBS có Scada trên LĐ PCVT | F103: 30786949 | G103: 1571 | H103: 120829 | I103: 0 | J103: THANH5DT.HCM.VTA | K103: 5 | L103: 120829
A104: 82900 | B104: 1 | C104: 13681 | D104: Cost Management-Inventory | E104: 25039-SX:Xuất vtư từ SXKD đ/c cho Ctr Trang bị Tbị REC, LBS có Scada trên LĐ PCVT | F104: 30786946 | G104: 1571 | H104: 134400 | I104: 0 | J104: THANH5DT.HCM.VTA | K104: 5 | L104: 134400
A105: 82900 | B105: 1 | C105: 13681 | D105: Cost Management-Inventory | E105: 25039-SX:Xuất vtư từ SXKD đ/c cho Ctr Trang bị Tbị REC, LBS có Scada trên LĐ PCVT | F105: 30786950 | G105: 1571 | H105: 146582 | I105: 0 | J105: THANH5DT.HCM.VTA | K105: 5 | L105: 146582
A106: 82900 | B106: 1 | C106: 13681 | D106: Cost Management-Inventory | E106: 25039-SX:Xuất vtư từ SXKD đ/c cho Ctr Trang bị Tbị REC, LBS có Scada trên LĐ PCVT | F106: 30799840 | G106: 1570 | H106: 157500 | I106: 0 | J106: THANH5DT.HCM.VTA | K106: 5 | L106: 157500
A107: 82900 | B107: 1 | C107: 13681 | D107: Cost Management-Inventory | E107: 25039-SX:Xuất vtư từ SXKD đ/c cho Ctr Trang bị Tbị REC, LBS có Scada trên LĐ PCVT | F107: 30799843 | G107: 1570 | H107: 176400 | I107: 0 | J107: THANH5DT.HCM.VTA | K107: 5 | L107: 176400
A108: 82900 | B108: 1 | C108: 13681 | D108: Receivables-Misc Receipts | E108: Thanh toán tiền thuê kho bãi tháng 01/2026->03/2026 - HĐồng số 05-2026/HĐDV/PCVT-HKD.NHI ngày 31.12.25 | F108: R0526SC0503 | G108: 1448 | H108: 32400000 | I108: 0 | J108: CHAULTN.HCM.VTA | K108: 5 | L108: 32400000
A109: 82900 | B109: 1 | C109: 13681 | D109: Receivables-Misc Receipts | E109: Thanh toán tiền thuê kho bãi tháng 01/2026->03/2026 - HĐồng số 05-2026/HĐDV/PCVT-HKD.NHI ngày 31.12.25 | F109: R0526SC0503 | G109: 1448 | H109: 32400000 | I109: 0 | J109: CHAULTN.HCM.VTA | K109: 5 | L109: 32400000
A110: 82900 | B110: 1 | C110: 13681 | D110: Receivables-Misc Receipts | E110: Nhập tiền từ TK ĐTXD tiền vật tư A cấp thừa ĐVTC đền tiền công trình F02F02F02 LT0K 25009 | F110: G0526SC0084 | G110: 1449 | H110: 0 | I110: 24153007 | J110: CHAULTN.HCM.VTA | K110: 5 | L110: -24153007
A111: 82900 | B111: 2 | C111: 33681 | D111: Cost Management-Inventory | E111: 25039-SX:Nhập vtư từ SXKD đ/c cho Ctr Trang bị Tbị REC, LBS có Scada trên LĐ PCVT | F111: 30788898 | G111: 1571 | H111: 0 | I111: 48000 | J111: THANH5DT.HCM.VTA | K111: 5 | L111: 48000
A112: 82900 | B112: 2 | C112: 33681 | D112: Cost Management-Inventory | E112: 25039-SX:Nhập vtư từ SXKD đ/c cho Ctr Trang bị Tbị REC, LBS có Scada trên LĐ PCVT | F112: 30799892 | G112: 1570 | H112: 0 | I112: 95991 | J112: THANH5DT.HCM.VTA | K112: 5 | L112: 95991
A113: 82900 | B113: 2 | C113: 33681 | D113: Cost Management-Inventory | E113: 25039-SX:Nhập vtư từ SXKD đ/c cho Ctr Trang bị Tbị REC, LBS có Scada trên LĐ PCVT | F113: 30788903 | G113: 1571 | H113: 0 | I113: 120829 | J113: THANH5DT.HCM.VTA | K113: 5 | L113: 120829
A114: 82900 | B114: 2 | C114: 33681 | D114: Cost Management-Inventory | E114: 25039-SX:Nhập vtư từ SXKD đ/c cho Ctr Trang bị Tbị REC, LBS có Scada trên LĐ PCVT | F114: 30788900 | G114: 1571 | H114: 0 | I114: 134400 | J114: THANH5DT.HCM.VTA | K114: 5 | L114: 134400
A115: 82900 | B115: 2 | C115: 33681 | D115: Cost Management-Inventory | E115: 25039-SX:Nhập vtư từ SXKD đ/c cho Ctr Trang bị Tbị REC, LBS có Scada trên LĐ PCVT | F115: 30788904 | G115: 1571 | H115: 0 | I115: 146582 | J115: THANH5DT.HCM.VTA | K115: 5 | L115: 146582
A116: 82900 | B116: 2 | C116: 33681 | D116: Cost Management-Inventory | E116: 25039-SX:Nhập vtư từ SXKD đ/c cho Ctr Trang bị Tbị REC, LBS có Scada trên LĐ PCVT | F116: 30799886 | G116: 1570 | H116: 0 | I116: 157500 | J116: THANH5DT.HCM.VTA | K116: 5 | L116: 157500
A117: 82900 | B117: 2 | C117: 33681 | D117: Cost Management-Inventory | E117: 25039-SX:Nhập vtư từ SXKD đ/c cho Ctr Trang bị Tbị REC, LBS có Scada trên LĐ PCVT | F117: 30799889 | G117: 1570 | H117: 0 | I117: 176400 | J117: THANH5DT.HCM.VTA | K117: 5 | L117: 176400
A118: 82900 | B118: 2 | C118: 33681 | D118: Cost Management-Inventory | E118: 25039-SX:Nhập vtư từ SXKD đ/c cho Ctr Trang bị Tbị REC, LBS có Scada trên LĐ PCVT | F118: 30788905 | G118: 1571 | H118: 0 | I118: 383963 | J118: THANH5DT.HCM.VTA | K118: 5 | L118: 383963
A119: 82900 | B119: 2 | C119: 33681 | D119: Cost Management-Inventory | E119: 25039-SX:Nhập vtư từ SXKD đ/c cho Ctr Trang bị Tbị REC, LBS có Scada trên LĐ PCVT | F119: 30799872 | G119: 1570 | H119: 0 | I119: 445088 | J119: THANH5DT.HCM.VTA | K119: 5 | L119: 445088
A120: 82900 | B120: 2 | C120: 33681 | D120: Cost Management-Inventory | E120: 25039-SX:Nhập vtư từ SXKD đ/c cho Ctr Trang bị Tbị REC, LBS có Scada trên LĐ PCVT | F120: 30771091 | G120: 1572 | H120: 0 | I120: 468000 | J120: THANH5DT.HCM.VTA | K120: 5 | L120: 468000
A121: 82900 | B121: 2 | C121: 33681 | D121: Cost Management-Inventory | E121: 25039-SX:Nhập vtư từ SXKD đ/c cho Ctr Trang bị Tbị REC, LBS có Scada trên LĐ PCVT | F121: 30799866 | G121: 1570 | H121: 0 | I121: 471377 | J121: THANH5DT.HCM.VTA | K121: 5 | L121: 471377
A122: 82900 | B122: 2 | C122: 33681 | D122: Cost Management-Inventory | E122: 25039-SX:Nhập vtư từ SXKD đ/c cho Ctr Trang bị Tbị REC, LBS có Scada trên LĐ PCVT | F122: 30799887 | G122: 1570 | H122: 0 | I122: 622500 | J122: THANH5DT.HCM.VTA | K122: 5 | L122: 622500
... A132: 82900 | B132: 2 | C132: 33681 | D132: Cost Management-Inventory | E132: 25039-SX:Nhập vtư từ SXKD đ/c cho Ctr Trang bị Tbị REC, LBS có Scada trên LĐ PCVT | F132: 30771098 | G132: 1572 | H132: 0 | I132: 54045440 | J132: THANH5DT.HCM.VTA | K132: 5 | L132: 54045440
A133: 82900 | B133: 2 | C133: 33681 | D133: Receivables-Misc Receipts | E133: Chuyển tiền cấn trừ công nợ ĐVTC đền tiền vật tư A cấp CT25016 | F133: R0026B0502 | G133: 1449 | H133: 24153007 | I133: 0 | J133: CHAULTN.HCM.VTA | K133: 5 | L133: -24153007
A134: 82900 | B134: 2 | C134: 33681 | D134: Receivables-Misc Receipts | E134: Chuyển tiền cấn trừ công nợ ĐVTC đền tiền vật tư A cấp CT25009 | F134: R0026B0501 | G134: 1449 | H134: 35640660 | I134: 0 | J134: CHAULTN.HCM.VTA | K134: 5 | L134: -35640660
A135: 82900 | B135: 2 | C135: 33681 | D135: GL-PAYABLE-MANUAL | E135: Điều chỉnh 13681-33681- do PX01.VH9.53.0102 ngày 10.12.25 xuất vật tư (điều từ sxkd) từ CT24028 sang CT25033 - | G135: 1353 | H135: 0 | I135: -422173 | J135: HIENNTK.HCM.VTA | K135: 5 | L135: -422173
A136: 82900 | B136: 2 | C136: 33681 | D136: GL-PAYABLE-MANUAL | E136: Điều chỉnh 13681-33681- do PX01.VH9.53.0102 ngày 10.12.25 xuất vật tư (điều từ sxkd) từ CT24028 sang CT25033 - | G136: 1353 | H136: 0 | I136: 422173 | J136: HIENNTK.HCM.VTA | K136: 5 | L136: 422173
A137: 82900 | B137: 2 | C137: 33681 | D137: GL-PAYABLE-MANUAL | E137: 25006_CP tiếp đoàn kiểm tra (hóa đơn 987) | G137: 1372 | H137: 0 | I137: 2779529 | J137: HIENNTK.HCM.VTA | K137: 5 | L137: 2779529
A138: 82900 | B138: 2 | C138: 33681 | D138: GL-PAYABLE-MANUAL | E138: 25004_CP tiếp đoàn kiểm tra khối lượng (hóa đơn 1314/ 21.05.26) | G138: 1372 | H138: 0 | I138: 3705555 | J138: HIENNTK.HCM.VTA | K138: 5 | L138: 3705555
A139: 82900 | B139: 2 | C139: 33681 | D139: GL-PAYABLE-MANUAL | E139: 25004_CP tiếp đoàn kiểm tra khối lượng (hóa đơn 1380, 1458/ 23.05.26) | G139: 1372 | H139: 0 | I139: 7436869 | J139: HIENNTK.HCM.VTA | K139: 5 | L139: 7436869
A140: 82900 | B140: 2 | C140: 33681 | D140: GL-PAYABLE-MANUAL | E140: 25004_CP tiếp đoàn kiểm tra khối lượng (hóa đơn 1199, 1245/ 21.05.26) | G140: 1372 | H140: 0 | I140: 3699899 | J140: HIENNTK.HCM.VTA | K140: 5 | L140: 3699899
A141: 82900 | B141: 2 | C141: 33681 | D141: GL-PAYABLE-MANUAL | E141: 25010_CP tiếp đoàn kiểm tra khối lượng (hóa đơn 1199, 1245/ 21.05.26) | G141: 1372 | H141: 0 | I141: 3727778 | J141: HIENNTK.HCM.VTA | K141: 5 | L141: 3727778
A142: 82900 | B142: 2 | C142: 33681 | D142: GL-PAYABLE-MANUAL | E142: 25010_CP QLDA (hóa đơn 1086,1153,1256,1126,1200/ 21.05.26) | G142: 1372 | H142: 0 | I142: 20919448 | J142: HIENNTK.HCM.VTA | K142: 5 | L142: 20919448
A143: 82900 | B143: 2 | C143: 33681 | D143: GL-PAYABLE-MANUAL | E143: 25010_CP QLDA (hóa đơn 1004,1023,1162,1109,1189/ 08.05.26) | G143: 1372 | H143: 0 | I143: 16704128 | J143: HIENNTK.HCM.VTA | K143: 5 | L143: 16704128
A144: 82900 | B144: 2 | C144: 33681 | D144: GL-PAYABLE-MANUAL | E144: 25001_CP QLDA (hóa đơn 1004,1023,1162,1109,1189/ 08.05.26) | G144: 1372 | H144: 0 | I144: 3711784 | J144: HIENNTK.HCM.VTA | K144: 5 | L144: 3711784
A145: 82900 | B145: 2 | C145: 33681 | D145: GL-PAYABLE-MANUAL | E145: 25005_CP thuê kho phường Phước Thắng tháng 2,3 tập kết vật tư | G145: 1372 | H145: 0 | I145: 25000000 | J145: HIENNTK.HCM.VTA | K145: 5 | L145: 25000000
A146: 82900 | B146: 2 | C146: 33681 | D146: GL-PAYABLE-MANUAL | E146: 25006_CP thuê kho phường Phước Thắng tháng 2,3 tập kết vật tư | G146: 1372 | H146: 0 | I146: 25000000 | J146: HIENNTK.HCM.VTA | K146: 5 | L146: 25000000
... A159: 82900 | B159: 2 | C159: 33681 | D159: GL-PAYABLE-MANUAL | E159: Hạch toán công nợ chi phí bảo hiểm, kho bãi (biên bản 25.05.26) cty Quang Huy đền tiền vật tư A cấp | G159: 1387 | H159: 0 | I159: 6062400 | J159: HIENNTK.HCM.VTA | K159: 5 | L159: 6062400
A160: Created with a trial version of Syncfusion Excel library or registered the wrong key in your application. Click here to obtain the valid key.

Sheet 13688_33688
P1: =HYPERLINK("#TONG_HOP!G1","TRO VE") -> TRO VE
A6: Created with a trial version of Syncfusion Excel library or registered the wrong key in your application. Click here to obtain the valid key.

Sheet 33688_13688
P1: =HYPERLINK("#TONG_HOP!G1","TRO VE") -> TRO VE
A6: Created with a trial version of Syncfusion Excel library or registered the wrong key in your application. Click here to obtain the valid key.

Sheet 13693_336391
P1: =HYPERLINK("#TONG_HOP!G1","TRO VE") -> TRO VE
A6: Created with a trial version of Syncfusion Excel library or registered the wrong key in your application. Click here to obtain the valid key.

Sheet 13838161_33638161
P1: =HYPERLINK("#TONG_HOP!G1","TRO VE") -> TRO VE
A6: Created with a trial version of Syncfusion Excel library or registered the wrong key in your application. Click here to obtain the valid key.

Sheet Evaluation Warning
A10: Created with a trial version of Syncfusion Excel library or registered the wrong key in your application. Click here to obtain the valid key.
